Workbook

Sheet Inspeção das Instalações
A1: Ação | B1: Data_Registro | C1: Setor | D1: Categoria por Tópico do FMS | E1: Setor Responsável | F1: Apontamento | G1: Conteção Imediata ? | H1: Gravidade | I1: Urgência | J1: Tendência | K1: Pontuação GUT | L1: Prioridade GUT | M1: Liderança | N1: Prazo | O1: Data Conclusão Real | P1: Status | Q1: Observações | R1: Indicador_Relacionado | S1: Ação_Proposta | T1: Base_GUT | U1: Column2 | V1: Column3 | W1: Column4 | X1: Column5 | Y1: Column6
A2: 1 | B2: 27 | C2: UCO | D2: Segurança | E2: SESMT | F2: Vestimentas ou calçados inadequados para as atividades. Atendimento parcial informado. | G2: Não | H2: 3 | I2: 3 | J2: 3 | K2: 27 | L2: Baixa | M2: A confirmar | N2: 45603 | O2: 45603 | P2: Concluído | Q2: Tratativa informada: Sim | R2: Segurança das instalações | S2: Reforçar a orientação sobre vestimentas e calçados e acompanhar a adesão. | T2: Modelo: ação 175 (linha 176)
A3: 2 | B3: 45573 | C3: UCO | D3: Segurança | E3: SESMT | F3: Uso de adornos durante as atividades. Atendimento parcial informado. | G3: Não | H3: 3 | I3: 3 | J3: 3 | K3: 27 | L3: Baixa | M3: A confirmar | N3: 45603 | O3: 45603 | P3: Concluído | Q3: Tratativa informada: Sim | R3: Segurança das instalações | S3: Orientar a equipe sobre a padronização de adornos e verificar a adesão. | T3: Modelo: ação 175 (linha 176)
A4: 3 | B4: 45573 | C4: UCO | D4: Segurança contra Incêndio | E4: SESMT | F4: Ausência informada de detectores de fumaça. | G4: Não | H4: 3 | I4: 3 | J4: 3 | K4: 27 | L4: Baixa | M4: A confirmar | N4: 45603 | O4: 45603 | P4: Concluído | Q4: Avaliar a aplicabilidade ao local antes de confirmar a não conformidade. | R4: Segurança contra incêndio | S4: Solicitar avaliação do SESMT sobre cobertura e necessidade de detectores. | T4: Modelo: ação 176 (linha 177) | U4: Concluído | V4: Tratativa informada: Sim | W4: Segurança das instalações | X4: Reforçar a orientação sobre vestimentas e calçados e acompanhar a adesão. | Y4: Modelo: ação 175 (linha 176)
A5: 4 | B5: 45573 | C5: UCO | D5: Segurança contra Incêndio | E5: SESMT | F5: Mapeamento da rota de fuga não disponível. | G5: Não | H5: 3 | I5: 3 | J5: 3 | K5: 27 | L5: Baixa | M5: A confirmar | N5: 45603 | O5: 45603 | P5: Concluído | Q5: Tratativa informada: Sim | R5: Segurança contra incêndio | S5: Solicitar atualização ou disponibilização do mapeamento da rota de fuga. | T5: Modelo: ação 212 (linha 213) | U5: Concluído | V5: Tratativa informada: Sim | W5: Segurança das instalações | X5: Orientar a equipe sobre a padronização de adornos e verificar a adesão. | Y5: Modelo: ação 175 (linha 176)
A6: 5 | B6: 45573 | C6: UCO | D6: Segurança contra Incêndio | E6: SESMT | F6: Equipe sem conhecimento completo da rota de fuga. | G6: Não | H6: 3 | I6: 3 | J6: 3 | K6: 27 | L6: Baixa | M6: A confirmar | N6: 45603 | O6: 45603 | P6: Concluído | Q6: Tratativa informada: Sim | R6: Segurança contra incêndio | S6: Orientar a equipe sobre a rota de fuga e verificar a compreensão. | T6: Modelo: ação 212 (linha 213) | U6: Concluído | V6: Avaliar a aplicabilidade ao local antes de confirmar a não conformidade. | W6: Segurança contra incêndio | X6: Solicitar avaliação do SESMT sobre cobertura e necessidade de detectores. | Y6: Modelo: ação 176 (linha 177)
A7: 6 | B7: 45573 | C7: UCO | D7: Segurança contra Incêndio | E7: SESMT | F7: Ausência informada de brigadistas no momento da inspeção. | G7: Não | L7: Pendente de avaliação | M7: A confirmar | N7: 45603 | O7: 45603 | P7: Concluído | Q7: Avaliar a aplicabilidade ao local antes de confirmar a não conformidade. Sem exemplo suficientemente equivalente no modelo para atribuir as três notas GUT. | R7: Segurança contra incêndio | S7: Solicitar ao SESMT avaliação da cobertura da brigada para o setor e horário. | T7: Sem referência equivalente no modelo | U7: Concluído | V7: Tratativa informada: Sim | W7: Segurança contra incêndio | X7: Solicitar atualização ou disponibilização do mapeamento da rota de fuga. | Y7: Modelo: ação 212 (linha 213)
A8: 7 | B8: 45573 | C8: UCO | D8: Sistemas Utilitários | E8: Manutenção | F8: Presença de benjamim ou extensão elétrica. | G8: Não | H8: 3 | I8: 3 | J8: 3 | K8: 27 | L8: Baixa | M8: A confirmar | N8: 45603 | O8: 45603 | P8: Concluído | Q8: Tratativa informada: Sim | R8: Segurança elétrica | S8: Solicitar avaliação e regularização das conexões elétricas. | T8: Modelo: ação 214 (linha 215) | U8: Concluído | V8: Tratativa informada: Sim | W8: Segurança contra incêndio | X8: Orientar a equipe sobre a rota de fuga e verificar a compreensão. | Y8: Modelo: ação 212 (linha 213)
A9: 8 | B9: 45573 | C9: UCO | D9: Equipamento Médico | E9: Manutenção | F9: Equipamento elétrico sem validação da engenharia. | G9: Não | H9: 3 | I9: 4 | J9: 3 | K9: 36 | L9: Moderada | M9: A confirmar | N9: 45603 | O9: 45603 | P9: Concluído | Q9: Tratativa informada: Sim | R9: Segurança elétrica | S9: Retirar o equipamento do uso até avaliação pela área responsável. | T9: Modelo: ação 123 (linha 124) | U9: Concluído | V9: Avaliar a aplicabilidade ao local antes de confirmar a não conformidade. Sem exemplo suficientemente equivalente no modelo para atribuir as três notas GUT. | W9: Segurança contra incêndio | X9: Solicitar ao SESMT avaliação da cobertura da brigada para o setor e horário. | Y9: Sem referência equivalente no modelo
A10: 9 | B10: 45573 | C10: UCO | D10: Segurança contra Incêndio | E10: SESMT | F10: Ausência de sinalização de limite de altura para armazenamento. | G10: Não | H10: 3 | I10: 3 | J10: 3 | K10: 27 | L10: Baixa | M10: A confirmar | N10: 45603 | O10: 45603 | P10: Concluído | Q10: Avaliar a aplicabilidade ao local antes de confirmar a não conformidade. Tratativa informada: Sim | R10: Segurança contra incêndio | S10: Solicitar definição e sinalização do limite de altura aplicável. | T10: Modelo: ação 179 (linha 180) | U10: Concluído | V10: Tratativa informada: Sim | W10: Segurança elétrica | X10: Solicitar avaliação e regularização das conexões elétricas. | Y10: Modelo: ação 214 (linha 215)
A11: 10 | B11: 45573 | C11: UCO | D11: Segurança contra Incêndio | E11: SESMT | F11: Itens armazenados acima do limite de altura. | G11: Não | H11: 3 | I11: 4 | J11: 3 | K11: 36 | L11: Moderada | M11: A confirmar | N11: 45603 | O11: 45603 | P11: Concluído | Q11: Tratativa informada: Sim | R11: Segurança contra incêndio | S11: Reorganizar os itens respeitando o limite de altura. | T11: Modelo: ação 159 (linha 160) | U11: Concluído | V11: Tratativa informada: Sim | W11: Segurança elétrica | X11: Retirar o equipamento do uso até avaliação pela área responsável. | Y11: Modelo: ação 123 (linha 124)
A12: 11 | B12: 45573 | C12: UCO | D12: Materiais e Resíduos Perigosos | E12: SESMT | F12: Identificação incompleta ou ausente no coletor de perfurocortantes. | G12: Não | H12: 3 | I12: 3 | J12: 3 | K12: 27 | L12: Baixa | M12: A confirmar | N12: 45603 | O12: 45603 | P12: Concluído | Q12: Tratativa informada: Sim | R12: Materiais e resíduos perigosos | S12: Regularizar a identificação dos coletores e orientar a equipe. | T12: Modelo: ação 204 (linha 205) | U12: Concluído | V12: Avaliar a aplicabilidade ao local antes de confirmar a não conformidade. Tratativa informada: Sim | W12: Segurança contra incêndio | X12: Solicitar definição e sinalização do limite de altura aplicável. | Y12: Modelo: ação 179 (linha 180)
A13: 12 | B13: 45573 | C13: UCO | D13: Materiais e Resíduos Perigosos | E13: SESMT | F13: Suporte de coletor de perfurocortantes em altura inadequada. Atendimento parcial informado. | G13: Não | H13: 2 | I13: 3 | J13: 3 | K13: 18 | L13: Baixa | M13: A confirmar | N13: 45603 | O13: 45603 | P13: Concluído | Q13: Tratativa informada: Sim | R13: Materiais e resíduos perigosos | S13: Solicitar avaliação e adequação do suporte do coletor. | T13: Modelo: ação 114 (linha 115) | U13: Concluído | V13: Tratativa informada: Sim | W13: Segurança contra incêndio | X13: Reorganizar os itens respeitando o limite de altura. | Y13: Modelo: ação 159 (linha 160)
A14: 13 | B14: 45573 | C14: UCO | D14: Sistemas Utilitários | E14: Manutenção | F14: Inadequação nos espelhos de tomadas, interruptores ou pontos de rede. Atendimento parcial informado. | G14: Não | H14: 3 | I14: 3 | J14: 3 | K14: 27 | L14: Baixa | M14: A confirmar | N14: 45603 | O14: 45603 | P14: Concluído | Q14: Tratativa informada: Não | R14: Segurança elétrica | S14: Abrir ou acompanhar OS para corrigir os espelhos indicados. | T14: Modelo: ação 305 (linha 306) | U14: Concluído | V14: Tratativa informada: Sim | W14: Materiais e resíduos perigosos | X14: Regularizar a identificação dos coletores e orientar a equipe. | Y14: Modelo: ação 204 (linha 205)
A15: 14 | B15: 45573 | C15: UCO | D15: Segurança | E15: CCIH | F15: Avisos sem proteção adequada para higienização. Atendimento parcial informado. | G15: Não | H15: 2 | I15: 3 | J15: 3 | K15: 18 | L15: Baixa | M15: A confirmar | N15: 45603 | O15: 45603 | P15: Concluído | Q15: Tratativa informada: Sim | R15: Controle de infecção e saneamento | S15: Adequar a proteção e a fixação dos avisos. | T15: Modelo: ação 110 (linha 111) | U15: Concluído | V15: Tratativa informada: Sim | W15: Materiais e resíduos perigosos | X15: Solicitar avaliação e adequação do suporte do coletor. | Y15: Modelo: ação 114 (linha 115)
A16: 15 | B16: 45573 | C16: UCO | D16: Segurança | E16: Manutenção | F16: Parede com integridade ou conservação inadequada. | G16: Não | H16: 3 | I16: 3 | J16: 3 | K16: 27 | L16: Baixa | M16: A confirmar | N16: 45603 | O16: 45603 | P16: Concluído | Q16: Tratativa informada: Não | R16: Infraestrutura predial | S16: Avaliar e reparar as superfícies e a origem dos danos. | T16: Modelo: ação 241 (linha 242) | U16: Concluído | V16: Tratativa informada: Não | W16: Segurança elétrica | X16: Abrir ou acompanhar OS para corrigir os espelhos indicados. | Y16: Modelo: ação 305 (linha 306)
A17: 16 | B17: 45573 | C17: UCO | D17: Segurança | E17: Hotelaria | F17: Mobiliário com rasgo ou defeito. Atendimento parcial informado. | G17: Não | H17: 3 | I17: 3 | J17: 3 | K17: 27 | L17: Baixa | M17: A confirmar | N17: 45603 | O17: 45603 | P17: Concluído | Q17: Tratativa informada: Sim | R17: Segurança das instalações | S17: Solicitar reparo ou substituição do mobiliário indicado. | T17: Modelo: ação 140 (linha 141) | U17: Concluído | V17: Tratativa informada: Sim | W17: Controle de infecção e saneamento | X17: Adequar a proteção e a fixação dos avisos. | Y17: Modelo: ação 110 (linha 111)
A18: 17 | B18: 45573 | C18: UCO | D18: Segurança | E18: Hotelaria | F18: Porta-copos ou dispenser com integridade ou funcionamento inadequado. Atendimento parcial informado. | G18: Não | H18: 3 | I18: 4 | J18: 3 | K18: 36 | L18: Moderada | M18: A confirmar | N18: 45603 | O18: 45603 | P18: Concluído | Q18: Tratativa informada: Não | R18: Controle de infecção e saneamento | S18: Solicitar reparo ou substituição dos suportes e dispensers indicados. | T18: Modelo: ação 173 (linha 174) | U18: Concluído | V18: Tratativa informada: Não | W18: Infraestrutura predial | X18: Avaliar e reparar as superfícies e a origem dos danos. | Y18: Modelo: ação 241 (linha 242)
A19: 18 | B19: 45573 | C19: UCO | D19: Segurança | E19: Hotelaria | F19: Área com limpeza visual inadequada. Atendimento parcial informado. | G19: Não | H19: 3 | I19: 4 | J19: 3 | K19: 36 | L19: Moderada | M19: A confirmar | N19: 45603 | O19: 45603 | P19: Concluído | Q19: Tratativa informada: Não | R19: Limpeza/conservação | S19: Providenciar limpeza e revisar a rotina de higienização. | T19: Modelo: ação 139 (linha 140) | U19: Concluído | V19: Tratativa informada: Sim | W19: Segurança das instalações | X19: Solicitar reparo ou substituição do mobiliário indicado. | Y19: Modelo: ação 140 (linha 141)
... A23: 22 | B23: 45580 | C23: 2D | D23: Segurança contra Incêndio | E23: SESMT | F23: Mapeamento da rota de fuga não disponível. | G23: Não | H23: 3 | I23: 3 | J23: 3 | K23: 27 | L23: Baixa | M23: A confirmar | N23: 45610 | O23: 45610 | P23: Concluído | Q23: Tratativa informada: Sim | R23: Segurança contra incêndio | S23: Solicitar atualização ou disponibilização do mapeamento da rota de fuga. | T23: Modelo: ação 212 (linha 213) | U23: Concluído | V23: Tratativa informada: Sim | W23: Segurança das instalações | X23: Reforçar a orientação sobre vestimentas e calçados e acompanhar a adesão. | Y23: Modelo: ação 175 (linha 176)
A24: 23 | B24: 45580 | C24: 2D | D24: Segurança contra Incêndio | E24: SESMT | F24: Ausência informada de brigadistas no momento da inspeção. | G24: Não | L24: Pendente de avaliação | M24: A confirmar | N24: 45610 | O24: 45610 | P24: Concluído | Q24: Avaliar a aplicabilidade ao local antes de confirmar a não conformidade. Sem exemplo suficientemente equivalente no modelo para atribuir as três notas GUT. | R24: Segurança contra incêndio | S24: Solicitar ao SESMT avaliação da cobertura da brigada para o setor e horário. | T24: Sem referência equivalente no modelo | U24: Concluído | V24: Tratativa informada: Sim | W24: Segurança elétrica | X24: Desobstruir os painéis e manter o acesso livre. | Y24: Modelo: ação 196 (linha 197)
A25: 24 | B25: 45580 | C25: 2D | D25: Segurança contra Incêndio | E25: SESMT | F25: Ausência de sinalização de limite de altura para armazenamento. | G25: Não | H25: 3 | I25: 3 | J25: 3 | K25: 27 | L25: Baixa | M25: A confirmar | N25: 45610 | O25: 45610 | P25: Concluído | Q25: Avaliar a aplicabilidade ao local antes de confirmar a não conformidade. Tratativa informada: Sim | R25: Segurança contra incêndio | S25: Solicitar definição e sinalização do limite de altura aplicável. | T25: Modelo: ação 179 (linha 180) | U25: Concluído | V25: Tratativa informada: Sim | W25: Segurança contra incêndio | X25: Solicitar atualização ou disponibilização do mapeamento da rota de fuga. | Y25: Modelo: ação 212 (linha 213)
A26: 25 | B26: 45580 | C26: 2D | D26: Segurança contra Incêndio | E26: SESMT | F26: Itens armazenados acima do limite de altura. Atendimento parcial informado. | G26: Não | H26: 3 | I26: 4 | J26: 3 | K26: 36 | L26: Moderada | M26: A confirmar | N26: 45610 | O26: 45610 | P26: Concluído | Q26: Tratativa informada: Sim | R26: Segurança contra incêndio | S26: Reorganizar os itens respeitando o limite de altura. | T26: Modelo: ação 159 (linha 160) | U26: Concluído | V26: Avaliar a aplicabilidade ao local antes de confirmar a não conformidade. Sem exemplo suficientemente equivalente no modelo para atribuir as três notas GUT. | W26: Segurança contra incêndio | X26: Solicitar ao SESMT avaliação da cobertura da brigada para o setor e horário. | Y26: Sem referência equivalente no modelo
A27: 26 | B27: 45580 | C27: 2D | D27: Materiais e Resíduos Perigosos | E27: SESMT | F27: Identificação incompleta ou ausente no coletor de perfurocortantes. Atendimento parcial informado. | G27: Não | H27: 3 | I27: 3 | J27: 3 | K27: 27 | L27: Baixa | M27: A confirmar | N27: 45610 | O27: 45610 | P27: Concluído | Q27: Tratativa informada: Sim | R27: Materiais e resíduos perigosos | S27: Regularizar a identificação dos coletores e orientar a equipe. | T27: Modelo: ação 204 (linha 205) | U27: Concluído | V27: Avaliar a aplicabilidade ao local antes de confirmar a não conformidade. Tratativa informada: Sim | W27: Segurança contra incêndio | X27: Solicitar definição e sinalização do limite de altura aplicável. | Y27: Modelo: ação 179 (linha 180)
A28: 27 | B28: 45580 | C28: 2D | D28: Sistemas Utilitários | E28: Manutenção | F28: Identificação de voltagem ausente ou incompleta nas tomadas. Atendimento parcial informado. | G28: Não | H28: 3 | I28: 3 | J28: 3 | K28: 27 | L28: Baixa | M28: A confirmar | N28: 45610 | O28: 45610 | P28: Concluído | R28: Segurança elétrica | S28: Providenciar identificação da voltagem após verificação técnica. | T28: Modelo: ação 240 (linha 241) | U28: Concluído | V28: Tratativa informada: Sim | W28: Segurança contra incêndio | X28: Reorganizar os itens respeitando o limite de altura. | Y28: Modelo: ação 159 (linha 160)
A29: 28 | B29: 45580 | C29: 2D | D29: Sistemas Utilitários | E29: Manutenção | F29: Torneira assistencial que exige o uso das mãos para fechamento. | G29: Não | H29: 3 | I29: 4 | J29: 3 | K29: 36 | L29: Moderada | M29: A confirmar | N29: 45610 | O29: 45610 | P29: Concluído | Q29: Tratativa informada: Não | R29: Controle de infecção e saneamento | S29: Solicitar adequação das torneiras ao modelo previsto para o uso. | T29: Modelo: ação 316 (linha 317) | U29: Concluído | V29: Tratativa informada: Sim | W29: Materiais e resíduos perigosos | X29: Regularizar a identificação dos coletores e orientar a equipe. | Y29: Modelo: ação 204 (linha 205)
A30: 29 | B30: 45580 | C30: 2D | D30: Segurança | E30: Manutenção | F30: Barreiras ou trancas de janelas inadequadas. | G30: Não | H30: 3 | I30: 3 | J30: 3 | K30: 27 | L30: Baixa | M30: A confirmar | N30: 45610 | O30: 45610 | P30: Concluído | Q30: Tratativa informada: Não | R30: Controle de infecção e saneamento | S30: Solicitar adequação das telas ou trancas das janelas. | T30: Modelo: ação 310 (linha 311) | U30: Concluído | W30: Segurança elétrica | X30: Providenciar identificação da voltagem após verificação técnica. | Y30: Modelo: ação 240 (linha 241)
A31: 30 | B31: 45580 | C31: 2D | D31: Materiais e Resíduos Perigosos | E31: CCIH | F31: Resíduo ou outro item disposto diretamente no chão. | G31: Não | H31: 3 | I31: 3 | J31: 3 | K31: 27 | L31: Baixa | M31: A confirmar | N31: 45610 | O31: 45610 | P31: Concluído | Q31: Tratativa informada: Sim | R31: Controle de infecção e saneamento | S31: Retirar os itens do chão e adequar o acondicionamento. | T31: Modelo: ação 172 (linha 173) | U31: Concluído | V31: Tratativa informada: Não | W31: Controle de infecção e saneamento | X31: Solicitar adequação das torneiras ao modelo previsto para o uso. | Y31: Modelo: ação 316 (linha 317)
A32: 31 | B32: 45580 | C32: 2D | D32: Segurança | E32: Manutenção | F32: Parede com integridade ou conservação inadequada. | G32: Não | H32: 3 | I32: 3 | J32: 3 | K32: 27 | L32: Baixa | M32: A confirmar | N32: 45610 | O32: 45610 | P32: Concluído | Q32: Tratativa informada: Não | R32: Infraestrutura predial | S32: Avaliar e reparar as superfícies e a origem dos danos. | T32: Modelo: ação 241 (linha 242) | U32: Concluído | V32: Tratativa informada: Não | W32: Controle de infecção e saneamento | X32: Solicitar adequação das telas ou trancas das janelas. | Y32: Modelo: ação 310 (linha 311)
A33: 32 | B33: 45580 | C33: 2D | D33: Sistemas Utilitários | E33: Manutenção | F33: Climatização com problema de funcionamento, sujidade ou vazamento. | G33: Não | H33: 3 | I33: 4 | J33: 3 | K33: 36 | L33: Moderada | M33: A confirmar | N33: 45610 | O33: 45610 | P33: Concluído | Q33: Tratativa informada: Não | R33: Climatização | S33: Solicitar avaliação, limpeza ou reparo do sistema de climatização. | T33: Modelo: ação 112 (linha 113) | U33: Concluído | V33: Tratativa informada: Sim | W33: Controle de infecção e saneamento | X33: Retirar os itens do chão e adequar o acondicionamento. | Y33: Modelo: ação 172 (linha 173)
A34: 33 | B34: 45580 | C34: 2D | D34: Segurança | E34: Hotelaria | F34: Mobiliário com rasgo ou defeito. Atendimento parcial informado. | G34: Não | H34: 3 | I34: 3 | J34: 3 | K34: 27 | L34: Baixa | M34: A confirmar | N34: 45610 | O34: 45610 | P34: Concluído | Q34: Tratativa informada: Não | R34: Segurança das instalações | S34: Solicitar reparo ou substituição do mobiliário indicado. | T34: Modelo: ação 140 (linha 141) | U34: Concluído | V34: Tratativa informada: Não | W34: Infraestrutura predial | X34: Avaliar e reparar as superfícies e a origem dos danos. | Y34: Modelo: ação 241 (linha 242)
A35: 34 | B35: 45580 | C35: 2D | D35: Segurança | E35: Manutenção | F35: Bate-maca com integridade inadequada. Atendimento parcial informado. | G35: Não | H35: 3 | I35: 3 | J35: 3 | K35: 27 | L35: Baixa | M35: A confirmar | N35: 45610 | O35: 45610 | P35: Concluído | Q35: Tratativa informada: Não | R35: Infraestrutura predial | S35: Solicitar reparo ou fixação do bate-maca. | T35: Modelo: ação 301 (linha 302) | U35: Concluído | V35: Tratativa informada: Não | W35: Climatização | X35: Solicitar avaliação, limpeza ou reparo do sistema de climatização. | Y35: Modelo: ação 112 (linha 113)
A36: 35 | B36: 45580 | C36: 2D | D36: Segurança | E36: Manutenção | F36: Cantoneira ausente ou sem integridade adequada. | G36: Não | H36: 3 | I36: 3 | J36: 3 | K36: 27 | L36: Baixa | M36: A confirmar | N36: 45610 | O36: 45610 | P36: Concluído | Q36: Tratativa informada: Não | R36: Infraestrutura predial | S36: Solicitar instalação, reparo ou fixação das cantoneiras. | T36: Modelo: ação 307 (linha 308) | U36: Concluído | V36: Tratativa informada: Não | W36: Segurança das instalações | X36: Solicitar reparo ou substituição do mobiliário indicado. | Y36: Modelo: ação 140 (linha 141)
A37: 36 | B37: 45580 | C37: 2D | D37: Segurança | E37: Hotelaria | F37: Área com limpeza visual inadequada. | G37: Não | H37: 3 | I37: 4 | J37: 3 | K37: 36 | L37: Moderada | M37: A confirmar | N37: 45610 | O37: 45610 | P37: Concluído | Q37: Tratativa informada: Sim | R37: Limpeza/conservação | S37: Providenciar limpeza e revisar a rotina de higienização. | T37: Modelo: ação 139 (linha 140) | U37: Concluído | V37: Tratativa informada: Não | W37: Infraestrutura predial | X37: Solicitar reparo ou fixação do bate-maca. | Y37: Modelo: ação 301 (linha 302)
A38: 37 | B38: 45587 | C38: 2ºC | D38: Segurança | E38: SESMT | F38: Vestimentas ou calçados inadequados para as atividades. Atendimento parcial informado. | G38: Não | H38: 3 | I38: 3 | J38: 3 | K38: 27 | L38: Baixa | M38: A confirmar | N38: 45617 | O38: 45610 | P38: Concluído | Q38: Tratativa informada: Sim | R38: Segurança das instalações | S38: Reforçar a orientação sobre vestimentas e calçados e acompanhar a adesão. | T38: Modelo: ação 175 (linha 176) | U38: Concluído | V38: Tratativa informada: Não | W38: Infraestrutura predial | X38: Solicitar instalação, reparo ou fixação das cantoneiras. | Y38: Modelo: ação 307 (linha 308)
A39: 38 | B39: 45587 | C39: 2ºC | D39: Sistemas Utilitários | E39: Área assistencial/administrativa | F39: Obstrução do acesso a painéis elétricos. Atendimento parcial informado. | G39: Não | H39: 3 | I39: 4 | J39: 3 | K39: 36 | L39: Moderada | M39: A confirmar | N39: 45617 | O39: 45617 | P39: Concluído | Q39: Tratativa informada: Sim | R39: Segurança elétrica | S39: Desobstruir os painéis e manter o acesso livre. | T39: Modelo: ação 196 (linha 197) | U39: Concluído | V39: Tratativa informada: Sim | W39: Limpeza/conservação | X39: Providenciar limpeza e revisar a rotina de higienização. | Y39: Modelo: ação 139 (linha 140)
A40: 39 | B40: 45587 | C40: 2ºC | D40: Segurança contra Incêndio | E40: SESMT | F40: Ausência informada de detectores de fumaça. | G40: Não | H40: 3 | I40: 3 | J40: 3 | K40: 27 | L40: Baixa | M40: A confirmar | N40: 45617 | O40: 45617 | P40: Concluído | Q40: Avaliar a aplicabilidade ao local antes de confirmar a não conformidade. | R40: Segurança contra incêndio | S40: Solicitar avaliação do SESMT sobre cobertura e necessidade de detectores. | T40: Modelo: ação 176 (linha 177) | U40: Concluído | V40: Tratativa informada: Sim | W40: Segurança das instalações | X40: Reforçar a orientação sobre vestimentas e calçados e acompanhar a adesão. | Y40: Modelo: ação 175 (linha 176)
A41: 40 | B41: 45587 | C41: 2ºC | D41: Segurança contra Incêndio | E41: SESMT | F41: Mapeamento da rota de fuga não disponível. | G41: Não | H41: 3 | I41: 3 | J41: 3 | K41: 27 | L41: Baixa | M41: A confirmar | N41: 45617 | O41: 45617 | P41: Concluído | Q41: Tratativa informada: Sim | R41: Segurança contra incêndio | S41: Solicitar atualização ou disponibilização do mapeamento da rota de fuga. | T41: Modelo: ação 212 (linha 213) | U41: Concluído | V41: Tratativa informada: Sim | W41: Segurança elétrica | X41: Desobstruir os painéis e manter o acesso livre. | Y41: Modelo: ação 196 (linha 197)
A42: 41 | B42: 45587 | C42: 2ºC | D42: Segurança contra Incêndio | E42: SESMT | F42: Equipe sem conhecimento completo da rota de fuga. | G42: Não | H42: 3 | I42: 3 | J42: 3 | K42: 27 | L42: Baixa | M42: A confirmar | N42: 45617 | O42: 45617 | P42: Concluído | Q42: Tratativa informada: Sim | R42: Segurança contra incêndio | S42: Orientar a equipe sobre a rota de fuga e verificar a compreensão. | T42: Modelo: ação 212 (linha 213) | U42: Concluído | V42: Avaliar a aplicabilidade ao local antes de confirmar a não conformidade. | W42: Segurança contra incêndio | X42: Solicitar avaliação do SESMT sobre cobertura e necessidade de detectores. | Y42: Modelo: ação 176 (linha 177)
A43: 42 | B43: 45587 | C43: 2ºC | D43: Segurança contra Incêndio | E43: SESMT | F43: Ausência informada de brigadistas no momento da inspeção. | G43: Não | L43: Pendente de avaliação | M43: A confirmar | N43: 45617 | O43: 45617 | P43: Concluído | Q43: Avaliar a aplicabilidade ao local antes de confirmar a não conformidade. Sem exemplo suficientemente equivalente no modelo para atribuir as três notas GUT. | R43: Segurança contra incêndio | S43: Solicitar ao SESMT avaliação da cobertura da brigada para o setor e horário. | T43: Sem referência equivalente no modelo | U43: Concluído | V43: Tratativa informada: Sim | W43: Segurança contra incêndio | X43: Solicitar atualização ou disponibilização do mapeamento da rota de fuga. | Y43: Modelo: ação 212 (linha 213)
A44: 43 | B44: 45587 | C44: 2ºC | D44: Materiais e Resíduos Perigosos | E44: Assistencial | F44: Coletor de perfurocortantes acima do limite de volume. | G44: Não | H44: 3 | I44: 5 | J44: 3 | K44: 45 | L44: Alta | M44: A confirmar | N44: 45617 | O44: 45617 | P44: Concluído | Q44: Tratativa informada: Sim | R44: Materiais e resíduos perigosos | S44: Substituir o coletor e reforçar a conferência do limite de preenchimento. | T44: Modelo: ação 286 (linha 287) | U44: Concluído | V44: Tratativa informada: Sim | W44: Segurança contra incêndio | X44: Orientar a equipe sobre a rota de fuga e verificar a compreensão. | Y44: Modelo: ação 212 (linha 213)
A45: 44 | B45: 45587 | C45: 2ºC | D45: Sistemas Utilitários | E45: Manutenção | F45: Inadequação nos espelhos de tomadas, interruptores ou pontos de rede. Atendimento parcial informado. | G45: Não | H45: 3 | I45: 3 | J45: 3 | K45: 27 | L45: Baixa | M45: A confirmar | N45: 45617 | O45: 45617 | P45: Concluído | Q45: Tratativa informada: Não | R45: Segurança elétrica | S45: Abrir ou acompanhar OS para corrigir os espelhos indicados. | T45: Modelo: ação 305 (linha 306) | U45: Concluído | V45: Avaliar a aplicabilidade ao local antes de confirmar a não conformidade. Sem exemplo suficientemente equivalente no modelo para atribuir as três notas GUT. | W45: Segurança contra incêndio | X45: Solicitar ao SESMT avaliação da cobertura da brigada para o setor e horário. | Y45: Sem referência equivalente no modelo
A46: 45 | B46: 45587 | C46: 2ºC | D46: Sistemas Utilitários | E46: Manutenção | F46: Tomada não funcionante ou em padrão antigo. | G46: Não | H46: 3 | I46: 3 | J46: 3 | K46: 27 | L46: Baixa | M46: A confirmar | N46: 45617 | O46: 45617 | P46: Concluído | Q46: Tratativa informada: Não | R46: Segurança elétrica | S46: Solicitar reparo ou substituição das tomadas indicadas. | T46: Modelo: ação 250 (linha 251) | U46: Concluído | V46: Tratativa informada: Sim | W46: Materiais e resíduos perigosos | X46: Substituir o coletor e reforçar a conferência do limite de preenchimento. | Y46: Modelo: ação 286 (linha 287)
A47: 46 | B47: 45587 | C47: 2ºC | D47: Sistemas Utilitários | E47: Manutenção | F47: Chamada de enfermagem sem funcionamento pleno. Atendimento parcial informado. | G47: Não | L47: Pendente de avaliação | M47: A confirmar | N47: 45617 | O47: 45617 | P47: Concluído | Q47: Tratativa informada: Sim Sem exemplo suficientemente equivalente no modelo para atribuir as três notas GUT. | R47: Utilidades críticas | S47: Solicitar avaliação e reparo da chamada de enfermagem. | T47: Sem referência equivalente no modelo | U47: Concluído | V47: Tratativa informada: Não | W47: Segurança elétrica | X47: Abrir ou acompanhar OS para corrigir os espelhos indicados. | Y47: Modelo: ação 305 (linha 306)
A48: 47 | B48: 45587 | C48: 2ºC | D48: Sistemas Utilitários | E48: Manutenção | F48: Lâmpada ou fita de LED queimada. | G48: Não | H48: 3 | I48: 3 | J48: 3 | K48: 27 | L48: Baixa | M48: A confirmar | N48: 45617 | O48: 45617 | P48: Concluído | Q48: Tratativa informada: Não | R48: Infraestrutura predial | S48: Solicitar substituição dos pontos de iluminação indicados. | T48: Modelo: ação 242 (linha 243) | U48: Concluído | V48: Tratativa informada: Não | W48: Segurança elétrica | X48: Solicitar reparo ou substituição das tomadas indicadas. | Y48: Modelo: ação 250 (linha 251)
A49: 48 | B49: 45587 | C49: 2ºC | D49: Sistemas Utilitários | E49: Manutenção | F49: Vazamento visível informado na área. | G49: Não | H49: 3 | I49: 3 | J49: 3 | K49: 27 | L49: Baixa | M49: A confirmar | N49: 45617 | O49: 45617 | P49: Concluído | Q49: Tratativa informada: Não | R49: Infraestrutura predial | S49: Solicitar identificação da origem e correção do vazamento. | T49: Modelo: ação 258 (linha 259) | U49: Concluído | V49: Tratativa informada: Sim Sem exemplo suficientemente equivalente no modelo para atribuir as três notas GUT. | W49: Utilidades críticas | X49: Solicitar avaliação e reparo da chamada de enfermagem. | Y49: Sem referência equivalente no modelo
A50: 49 | B50: 45587 | C50: 2ºC | D50: Materiais e Resíduos Perigosos | E50: CCIH | F50: Resíduo ou outro item disposto diretamente no chão. | G50: Não | H50: 3 | I50: 3 | J50: 3 | K50: 27 | L50: Baixa | M50: A confirmar | N50: 45617 | O50: 45617 | P50: Concluído | Q50: Tratativa informada: Sim | R50: Controle de infecção e saneamento | S50: Retirar os itens do chão e adequar o acondicionamento. | T50: Modelo: ação 172 (linha 173) | U50: Concluído | V50: Tratativa informada: Não | W50: Infraestrutura predial | X50: Solicitar substituição dos pontos de iluminação indicados. | Y50: Modelo: ação 242 (linha 243)
A51: 50 | B51: 45587 | C51: 2ºC | D51: Segurança | E51: CCIH | F51: Avisos sem proteção adequada para higienização. Atendimento parcial informado. | G51: Não | H51: 2 | I51: 3 | J51: 3 | K51: 18 | L51: Baixa | M51: A confirmar | N51: 45617 | O51: 45617 | P51: Concluído | Q51: Tratativa informada: Sim | R51: Controle de infecção e saneamento | S51: Adequar a proteção e a fixação dos avisos. | T51: Modelo: ação 110 (linha 111) | U51: Concluído | V51: Tratativa informada: Não | W51: Infraestrutura predial | X51: Solicitar identificação da origem e correção do vazamento. | Y51: Modelo: ação 258 (linha 259)
A52: 51 | B52: 45587 | C52: 2ºC | D52: Segurança | E52: Manutenção | F52: Parede com integridade ou conservação inadequada. Atendimento parcial informado. | G52: Não | H52: 3 | I52: 3 | J52: 3 | K52: 27 | L52: Baixa | M52: A confirmar | N52: 45617 | O52: 45617 | P52: Concluído | Q52: Tratativa informada: Sim | R52: Infraestrutura predial | S52: Avaliar e reparar as superfícies e a origem dos danos. | T52: Modelo: ação 241 (linha 242) | U52: Concluído | V52: Tratativa informada: Sim | W52: Controle de infecção e saneamento | X52: Retirar os itens do chão e adequar o acondicionamento. | Y52: Modelo: ação 172 (linha 173)
A53: 52 | B53: 45587 | C53: 2ºC | D53: Segurança | E53: Hotelaria | F53: Mobiliário com rasgo ou defeito. Atendimento parcial informado. | G53: Não | H53: 3 | I53: 3 | J53: 3 | K53: 27 | L53: Baixa | M53: A confirmar | N53: 45617 | O53: 45617 | P53: Concluído | Q53: Tratativa informada: Não | R53: Segurança das instalações | S53: Solicitar reparo ou substituição do mobiliário indicado. | T53: Modelo: ação 140 (linha 141) | U53: Concluído | V53: Tratativa informada: Sim | W53: Controle de infecção e saneamento | X53: Adequar a proteção e a fixação dos avisos. | Y53: Modelo: ação 110 (linha 111)
A54: 53 | B54: 45587 | C54: 2ºC | D54: Materiais e Resíduos Perigosos | E54: Hotelaria | F54: Lixeira com inadequação de tamanho, estado, funcionamento ou identificação. Atendimento parcial informado. | G54: Não | H54: 3 | I54: 4 | J54: 3 | K54: 36 | L54: Moderada | M54: A confirmar | N54: 45617 | O54: 45617 | P54: Concluído | Q54: Tratativa informada: Não | R54: Materiais e resíduos perigosos | S54: Avaliar e adequar ou substituir as lixeiras indicadas. | T54: Modelo: ação 328 (linha 329) | U54: Concluído | V54: Tratativa informada: Sim | W54: Infraestrutura predial | X54: Avaliar e reparar as superfícies e a origem dos danos. | Y54: Modelo: ação 241 (linha 242)
A55: 54 | B55: 45587 | C55: 2ºC | D55: Materiais e Resíduos Perigosos | E55: Área assistencial/administrativa | F55: Descarte de resíduo incompatível com a identificação da lixeira. Atendimento parcial informado. | G55: Não | H55: 3 | I55: 4 | J55: 3 | K55: 36 | L55: Moderada | M55: A confirmar | N55: 45617 | O55: 45617 | P55: Concluído | Q55: Tratativa informada: Sim | R55: Materiais e resíduos perigosos | S55: Corrigir a segregação de resíduos e reforçar as orientações à equipe. | T55: Modelo: ação 124 (linha 125) | U55: Concluído | V55: Tratativa informada: Não | W55: Segurança das instalações | X55: Solicitar reparo ou substituição do mobiliário indicado. | Y55: Modelo: ação 140 (linha 141)
A56: 55 | B56: 45587 | C56: 2ºC | D56: Segurança | E56: Hotelaria | F56: Sinalização das portas ausente ou incompleta. Atendimento parcial informado. | G56: Não | H56: 3 | I56: 3 | J56: 3 | K56: 27 | L56: Baixa | M56: A confirmar | N56: 45617 | O56: 45617 | P56: Concluído | Q56: Tratativa informada: Não | R56: Sinalização | S56: Solicitar adequação das sinalizações conforme o padrão do formulário. | T56: Modelo: ação 317 (linha 318) | U56: Concluído | V56: Tratativa informada: Não | W56: Materiais e resíduos perigosos | X56: Avaliar e adequar ou substituir as lixeiras indicadas. | Y56: Modelo: ação 328 (linha 329)
A57: 56 | B57: 45594 | C57: PS Adulto | D57: Avaliação de Riscos e Monitoramento | E57: Qualidade | F57: Inspeção sem acompanhamento do responsável ou de pessoa designada. | G57: Não | L57: Pendente de avaliação | M57: A confirmar | N57: 45624 | O57: 45617 | P57: Concluído | Q57: Sem exemplo suficientemente equivalente no modelo para atribuir as três notas GUT. | R57: Acompanhamento da inspeção | S57: Definir representante do setor e garantir acompanhamento nas próximas inspeções. | T57: Sem referência equivalente no modelo | U57: Concluído | V57: Tratativa informada: Sim | W57: Materiais e resíduos perigosos | X57: Corrigir a segregação de resíduos e reforçar as orientações à equipe. | Y57: Modelo: ação 124 (linha 125)
A58: 57 | B58: 45594 | C58: PS Adulto | D58: Sistemas Utilitários | E58: Área assistencial/administrativa | F58: Obstrução do acesso a painéis elétricos. Atendimento parcial informado. | G58: Não | H58: 3 | I58: 4 | J58: 3 | K58: 36 | L58: Moderada | M58: A confirmar | N58: 45624 | O58: 45624 | P58: Concluído | Q58: Tratativa informada: Sim | R58: Segurança elétrica | S58: Desobstruir os painéis e manter o acesso livre. | T58: Modelo: ação 196 (linha 197) | U58: Concluído | V58: Tratativa informada: Não | W58: Sinalização | X58: Solicitar adequação das sinalizações conforme o padrão do formulário. | Y58: Modelo: ação 317 (linha 318)
A59: 58 | B59: 45594 | C59: PS Adulto | D59: Segurança contra Incêndio | E59: SESMT | F59: Ausência informada de detectores de fumaça. | G59: Não | H59: 3 | I59: 3 | J59: 3 | K59: 27 | L59: Baixa | M59: A confirmar | N59: 45624 | O59: 45624 | P59: Concluído | Q59: Avaliar a aplicabilidade ao local antes de confirmar a não conformidade. | R59: Segurança contra incêndio | S59: Solicitar avaliação do SESMT sobre cobertura e necessidade de detectores. | T59: Modelo: ação 176 (linha 177) | U59: Concluído | V59: Sem exemplo suficientemente equivalente no modelo para atribuir as três notas GUT. | W59: Acompanhamento da inspeção | X59: Definir representante do setor e garantir acompanhamento nas próximas inspeções. | Y59: Sem referência equivalente no modelo
A60: 59 | B60: 45594 | C60: PS Adulto | D60: Segurança contra Incêndio | E60: SESMT | F60: Mapeamento da rota de fuga não disponível. | G60: Não | H60: 3 | I60: 3 | J60: 3 | K60: 27 | L60: Baixa | M60: A confirmar | N60: 45624 | O60: 45624 | P60: Concluído | Q60: Tratativa informada: Sim | R60: Segurança contra incêndio | S60: Solicitar atualização ou disponibilização do mapeamento da rota de fuga. | T60: Modelo: ação 212 (linha 213) | U60: Concluído | V60: Tratativa informada: Sim | W60: Segurança elétrica | X60: Desobstruir os painéis e manter o acesso livre. | Y60: Modelo: ação 196 (linha 197)
A61: 60 | B61: 45594 | C61: PS Adulto | D61: Segurança contra Incêndio | E61: SESMT | F61: Sinalização da rota de fuga ausente ou incompleta. Atendimento parcial informado. | G61: Não | H61: 3 | I61: 3 | J61: 3 | K61: 27 | L61: Baixa | M61: A confirmar | N61: 45624 | O61: 45624 | P61: Concluído | Q61: Tratativa informada: Sim | R61: Segurança contra incêndio | S61: Solicitar adequação da sinalização da rota de fuga. | T61: Modelo: ação 231 (linha 232) | U61: Concluído | V61: Avaliar a aplicabilidade ao local antes de confirmar a não conformidade. | W61: Segurança contra incêndio | X61: Solicitar avaliação do SESMT sobre cobertura e necessidade de detectores. | Y61: Modelo: ação 176 (linha 177)
A62: 61 | B62: 45594 | C62: PS Adulto | D62: Segurança contra Incêndio | E62: SESMT | F62: Equipe sem conhecimento completo da rota de fuga. | G62: Não | H62: 3 | I62: 3 | J62: 3 | K62: 27 | L62: Baixa | M62: A confirmar | N62: 45624 | O62: 45624 | P62: Concluído | Q62: Tratativa informada: Sim | R62: Segurança contra incêndio | S62: Orientar a equipe sobre a rota de fuga e verificar a compreensão. | T62: Modelo: ação 212 (linha 213) | U62: Concluído | V62: Tratativa informada: Sim | W62: Segurança contra incêndio | X62: Solicitar atualização ou disponibilização do mapeamento da rota de fuga. | Y62: Modelo: ação 212 (linha 213)
A63: 62 | B63: 45594 | C63: PS Adulto | D63: Sistemas Utilitários | E63: Manutenção | F63: Presença de benjamim ou extensão elétrica. | G63: Não | H63: 3 | I63: 3 | J63: 3 | K63: 27 | L63: Baixa | M63: A confirmar | N63: 45624 | O63: 45624 | P63: Concluído | Q63: Tratativa informada: Sim | R63: Segurança elétrica | S63: Solicitar avaliação e regularização das conexões elétricas. | T63: Modelo: ação 214 (linha 215) | U63: Concluído | V63: Tratativa informada: Sim | W63: Segurança contra incêndio | X63: Solicitar adequação da sinalização da rota de fuga. | Y63: Modelo: ação 231 (linha 232)
A64: 63 | B64: 45594 | C64: PS Adulto | D64: Segurança contra Incêndio | E64: SESMT | F64: Ausência de sinalização de limite de altura para armazenamento. | G64: Não | H64: 3 | I64: 3 | J64: 3 | K64: 27 | L64: Baixa | M64: A confirmar | N64: 45624 | O64: 45624 | P64: Concluído | Q64: Avaliar a aplicabilidade ao local antes de confirmar a não conformidade. Tratativa informada: Sim | R64: Segurança contra incêndio | S64: Solicitar definição e sinalização do limite de altura aplicável. | T64: Modelo: ação 179 (linha 180) | U64: Concluído | V64: Tratativa informada: Sim | W64: Segurança contra incêndio | X64: Orientar a equipe sobre a rota de fuga e verificar a compreensão. | Y64: Modelo: ação 212 (linha 213)
A65: 64 | B65: 45594 | C65: PS Adulto | D65: Materiais e Resíduos Perigosos | E65: SESMT | F65: Identificação incompleta ou ausente no coletor de perfurocortantes. Atendimento parcial informado. | G65: Não | H65: 3 | I65: 3 | J65: 3 | K65: 27 | L65: Baixa | M65: A confirmar | N65: 45624 | O65: 45624 | P65: Concluído | Q65: Tratativa informada: Sim | R65: Materiais e resíduos perigosos | S65: Regularizar a identificação dos coletores e orientar a equipe. | T65: Modelo: ação 204 (linha 205) | U65: Concluído | V65: Tratativa informada: Sim | W65: Segurança elétrica | X65: Solicitar avaliação e regularização das conexões elétricas. | Y65: Modelo: ação 214 (linha 215)
A66: 65 | B66: 45594 | C66: PS Adulto | D66: Materiais e Resíduos Perigosos | E66: Assistencial | F66: Coletor de perfurocortantes acima do limite de volume. Atendimento parcial informado. | G66: Não | H66: 3 | I66: 5 | J66: 3 | K66: 45 | L66: Alta | M66: A confirmar | N66: 45624 | O66: 45624 | P66: Concluído | Q66: Tratativa informada: Sim | R66: Materiais e resíduos perigosos | S66: Substituir o coletor e reforçar a conferência do limite de preenchimento. | T66: Modelo: ação 286 (linha 287) | U66: Concluído | V66: Avaliar a aplicabilidade ao local antes de confirmar a não conformidade. Tratativa informada: Sim | W66: Segurança contra incêndio | X66: Solicitar definição e sinalização do limite de altura aplicável. | Y66: Modelo: ação 179 (linha 180)
A67: 66 | B67: 45594 | C67: PS Adulto | D67: Sistemas Utilitários | E67: Manutenção | F67: Inadequação nos espelhos de tomadas, interruptores ou pontos de rede. Atendimento parcial informado. | G67: Não | H67: 3 | I67: 3 | J67: 3 | K67: 27 | L67: Baixa | M67: A confirmar | N67: 45624 | O67: 45624 | P67: Concluído | Q67: Tratativa informada: Não | R67: Segurança elétrica | S67: Abrir ou acompanhar OS para corrigir os espelhos indicados. | T67: Modelo: ação 305 (linha 306) | U67: Concluído | V67: Tratativa informada: Sim | W67: Materiais e resíduos perigosos | X67: Regularizar a identificação dos coletores e orientar a equipe. | Y67: Modelo: ação 204 (linha 205)
A68: 67 | B68: 45594 | C68: PS Adulto | D68: Sistemas Utilitários | E68: Manutenção | F68: Identificação de voltagem ausente ou incompleta nas tomadas. Atendimento parcial informado. | G68: Não | H68: 3 | I68: 3 | J68: 3 | K68: 27 | L68: Baixa | M68: A confirmar | N68: 45624 | O68: 45624 | P68: Concluído | R68: Segurança elétrica | S68: Providenciar identificação da voltagem após verificação técnica. | T68: Modelo: ação 240 (linha 241) | U68: Concluído | V68: Tratativa informada: Sim | W68: Materiais e resíduos perigosos | X68: Substituir o coletor e reforçar a conferência do limite de preenchimento. | Y68: Modelo: ação 286 (linha 287)
A69: 68 | B69: 45594 | C69: PS Adulto | D69: Segurança | E69: Manutenção | F69: Barreiras ou trancas de janelas inadequadas. Atendimento parcial informado. | G69: Não | H69: 3 | I69: 3 | J69: 3 | K69: 27 | L69: Baixa | M69: A confirmar | N69: 45624 | O69: 45624 | P69: Concluído | Q69: Tratativa informada: Não | R69: Controle de infecção e saneamento | S69: Solicitar adequação das telas ou trancas das janelas. | T69: Modelo: ação 310 (linha 311) | U69: Concluído | V69: Tratativa informada: Não | W69: Segurança elétrica | X69: Abrir ou acompanhar OS para corrigir os espelhos indicados. | Y69: Modelo: ação 305 (linha 306)
A70: 69 | B70: 45594 | C70: PS Adulto | D70: Materiais e Resíduos Perigosos | E70: Hotelaria | F70: Lixeira com tampa sem fechamento adequado. Atendimento parcial informado. | G70: Não | H70: 3 | I70: 4 | J70: 3 | K70: 36 | L70: Moderada | M70: A confirmar | N70: 45624 | O70: 45624 | P70: Concluído | Q70: Tratativa informada: Sim | R70: Materiais e resíduos perigosos | S70: Regularizar o fechamento ou substituir a lixeira. | T70: Modelo: ação 328 (linha 329) | U70: Concluído | W70: Segurança elétrica | X70: Providenciar identificação da voltagem após verificação técnica. | Y70: Modelo: ação 240 (linha 241)
A71: 70 | B71: 45594 | C71: PS Adulto | D71: Segurança | E71: CCIH | F71: Avisos sem proteção adequada para higienização. | G71: Não | H71: 2 | I71: 3 | J71: 3 | K71: 18 | L71: Baixa | M71: A confirmar | N71: 45624 | O71: 45624 | P71: Concluído | Q71: Tratativa informada: Sim | R71: Controle de infecção e saneamento | S71: Adequar a proteção e a fixação dos avisos. | T71: Modelo: ação 110 (linha 111) | U71: Concluído | V71: Tratativa informada: Não | W71: Controle de infecção e saneamento | X71: Solicitar adequação das telas ou trancas das janelas. | Y71: Modelo: ação 310 (linha 311)
A72: 71 | B72: 45594 | C72: PS Adulto | D72: Materiais e Resíduos Perigosos | E72: Assistencial | F72: Identificação ou armazenamento inadequado de almotolias abertas. | G72: Não | H72: 4 | I72: 5 | J72: 4 | K72: 80 | L72: Alta | M72: A confirmar | N72: 45624 | O72: 45624 | P72: Concluído | Q72: Tratativa informada: Sim | R72: Materiais e resíduos perigosos | S72: Regularizar identificação, armazenamento e controle de validade das almotolias. | T72: Modelo: ação 294 (linha 295) | U72: Concluído | V72: Tratativa informada: Sim | W72: Materiais e resíduos perigosos | X72: Regularizar o fechamento ou substituir a lixeira. | Y72: Modelo: ação 328 (linha 329)
A73: 72 | B73: 45594 | C73: PS Adulto | D73: Segurança | E73: Área assistencial/administrativa | F73: Alimentos inadequados ou armazenados de forma inadequada. | G73: Não | H73: 3 | I73: 4 | J73: 3 | K73: 36 | L73: Moderada | M73: A confirmar | N73: 45624 | O73: 45624 | P73: Concluído | Q73: Tratativa informada: Sim | R73: Controle de infecção e saneamento | S73: Revisar os alimentos e adequar o armazenamento. | T73: Modelo: ação 132 (linha 133) | U73: Concluído | V73: Tratativa informada: Sim | W73: Controle de infecção e saneamento | X73: Adequar a proteção e a fixação dos avisos. | Y73: Modelo: ação 110 (linha 111)
A74: 73 | B74: 45594 | C74: PS Adulto | D74: Segurança | E74: Manutenção | F74: Parede com integridade ou conservação inadequada. Atendimento parcial informado. | G74: Não | H74: 3 | I74: 3 | J74: 3 | K74: 27 | L74: Baixa | M74: A confirmar | N74: 45624 | O74: 45624 | P74: Concluído | Q74: Tratativa informada: Sim | R74: Infraestrutura predial | S74: Avaliar e reparar as superfícies e a origem dos danos. | T74: Modelo: ação 241 (linha 242) | U74: Concluído | V74: Tratativa informada: Sim | W74: Materiais e resíduos perigosos | X74: Regularizar identificação, armazenamento e controle de validade das almotolias. | Y74: Modelo: ação 294 (linha 295)
A75: 74 | B75: 45594 | C75: PS Adulto | D75: Sistemas Utilitários | E75: Manutenção | F75: Forro com integridade ou conservação inadequada. Atendimento parcial informado. | G75: Não | H75: 3 | I75: 3 | J75: 3 | K75: 27 | L75: Baixa | M75: A confirmar | N75: 45624 | O75: 45624 | P75: Concluído | Q75: Tratativa informada: Não | R75: Infraestrutura predial | S75: Avaliar e reparar o forro e a origem dos danos. | T75: Modelo: ação 304 (linha 305) | U75: Concluído | V75: Tratativa informada: Sim | W75: Controle de infecção e saneamento | X75: Revisar os alimentos e adequar o armazenamento. | Y75: Modelo: ação 132 (linha 133)
A76: 75 | B76: 45594 | C76: PS Adulto | D76: Sistemas Utilitários | E76: Manutenção | F76: Climatização com problema de funcionamento, sujidade ou vazamento. | G76: Não | H76: 3 | I76: 4 | J76: 3 | K76: 36 | L76: Moderada | M76: A confirmar | N76: 45624 | O76: 45624 | P76: Concluído | Q76: Tratativa informada: Não | R76: Climatização | S76: Solicitar avaliação, limpeza ou reparo do sistema de climatização. | T76: Modelo: ação 112 (linha 113) | U76: Concluído | V76: Tratativa informada: Sim | W76: Infraestrutura predial | X76: Avaliar e reparar as superfícies e a origem dos danos. | Y76: Modelo: ação 241 (linha 242)
A77: 76 | B77: 45594 | C77: PS Adulto | D77: Segurança | E77: Hotelaria | F77: Mobiliário com rasgo ou defeito. Atendimento parcial informado. | G77: Não | H77: 3 | I77: 3 | J77: 3 | K77: 27 | L77: Baixa | M77: A confirmar | N77: 45624 | O77: 45624 | P77: Concluído | Q77: Tratativa informada: Sim | R77: Segurança das instalações | S77: Solicitar reparo ou substituição do mobiliário indicado. | T77: Modelo: ação 140 (linha 141) | U77: Concluído | V77: Tratativa informada: Não | W77: Infraestrutura predial | X77: Avaliar e reparar o forro e a origem dos danos. | Y77: Modelo: ação 304 (linha 305)
A78: 77 | B78: 45594 | C78: PS Adulto | D78: Segurança | E78: Hotelaria | F78: Porta-copos ou dispenser com integridade ou funcionamento inadequado. Atendimento parcial informado. | G78: Não | H78: 3 | I78: 4 | J78: 3 | K78: 36 | L78: Moderada | M78: A confirmar | N78: 45624 | O78: 45624 | P78: Concluído | Q78: Tratativa informada: Sim | R78: Controle de infecção e saneamento | S78: Solicitar reparo ou substituição dos suportes e dispensers indicados. | T78: Modelo: ação 173 (linha 174) | U78: Concluído | V78: Tratativa informada: Não | W78: Climatização | X78: Solicitar avaliação, limpeza ou reparo do sistema de climatização. | Y78: Modelo: ação 112 (linha 113)
A79: 78 | B79: 45594 | C79: PS Adulto | D79: Materiais e Resíduos Perigosos | E79: Hotelaria | F79: Lixeira com inadequação de tamanho, estado, funcionamento ou identificação. Atendimento parcial informado. | G79: Não | H79: 3 | I79: 4 | J79: 3 | K79: 36 | L79: Moderada | M79: A confirmar | N79: 45624 | O79: 45624 | P79: Concluído | Q79: Tratativa informada: Sim | R79: Materiais e resíduos perigosos | S79: Avaliar e adequar ou substituir as lixeiras indicadas. | T79: Modelo: ação 328 (linha 329) | U79: Concluído | V79: Tratativa informada: Sim | W79: Segurança das instalações | X79: Solicitar reparo ou substituição do mobiliário indicado. | Y79: Modelo: ação 140 (linha 141)
A80: 79 | B80: 45594 | C80: PS Adulto | D80: Materiais e Resíduos Perigosos | E80: Área assistencial/administrativa | F80: Descarte de resíduo incompatível com a identificação da lixeira. Atendimento parcial informado. | G80: Não | H80: 3 | I80: 4 | J80: 3 | K80: 36 | L80: Moderada | M80: A confirmar | N80: 45624 | O80: 45624 | P80: Concluído | Q80: Tratativa informada: Sim | R80: Materiais e resíduos perigosos | S80: Corrigir a segregação de resíduos e reforçar as orientações à equipe. | T80: Modelo: ação 124 (linha 125) | U80: Concluído | V80: Tratativa informada: Sim | W80: Controle de infecção e saneamento | X80: Solicitar reparo ou substituição dos suportes e dispensers indicados. | Y80: Modelo: ação 173 (linha 174)
A81: 80 | B81: 45594 | C81: PS Adulto | D81: Segurança | E81: Hotelaria | F81: Sinalização das portas ausente ou incompleta. Atendimento parcial informado. | G81: Não | H81: 3 | I81: 3 | J81: 3 | K81: 27 | L81: Baixa | M81: A confirmar | N81: 45624 | O81: 45624 | P81: Concluído | Q81: Tratativa informada: Sim | R81: Sinalização | S81: Solicitar adequação das sinalizações conforme o padrão do formulário. | T81: Modelo: ação 317 (linha 318) | U81: Concluído | V81: Tratativa informada: Sim | W81: Materiais e resíduos perigosos | X81: Avaliar e adequar ou substituir as lixeiras indicadas. | Y81: Modelo: ação 328 (linha 329)
A82: 81 | B82: 45608 | C82: Oncologia- 1D | D82: Avaliação de Riscos e Monitoramento | E82: Qualidade | F82: Inspeção sem acompanhamento do responsável ou de pessoa designada. | G82: Não | L82: Pendente de avaliação | M82: A confirmar | N82: 45638 | O82: 45624 | P82: Concluído | Q82: Sem exemplo suficientemente equivalente no modelo para atribuir as três notas GUT. | R82: Acompanhamento da inspeção | S82: Definir representante do setor e garantir acompanhamento nas próximas inspeções. | T82: Sem referência equivalente no modelo | U82: Concluído | V82: Tratativa informada: Sim | W82: Materiais e resíduos perigosos | X82: Corrigir a segregação de resíduos e reforçar as orientações à equipe. | Y82: Modelo: ação 124 (linha 125)
A83: 82 | B83: 45608 | C83: Oncologia- 1D | D83: Segurança | E83: SESMT | F83: Vestimentas ou calçados inadequados para as atividades. Atendimento parcial informado. | G83: Não | H83: 3 | I83: 3 | J83: 3 | K83: 27 | L83: Baixa | M83: A confirmar | N83: 45638 | O83: 45638 | P83: Concluído | Q83: Tratativa informada: Sim | R83: Segurança das instalações | S83: Reforçar a orientação sobre vestimentas e calçados e acompanhar a adesão. | T83: Modelo: ação 175 (linha 176) | U83: Concluído | V83: Tratativa informada: Sim | W83: Sinalização | X83: Solicitar adequação das sinalizações conforme o padrão do formulário. | Y83: Modelo: ação 317 (linha 318)
A84: 83 | B84: 45608 | C84: Oncologia- 1D | D84: Segurança contra Incêndio | E84: SESMT | F84: Mapeamento da rota de fuga não disponível. | G84: Não | H84: 3 | I84: 3 | J84: 3 | K84: 27 | L84: Baixa | M84: A confirmar | N84: 45638 | O84: 45638 | P84: Concluído | Q84: Tratativa informada: Sim | R84: Segurança contra incêndio | S84: Solicitar atualização ou disponibilização do mapeamento da rota de fuga. | T84: Modelo: ação 212 (linha 213) | U84: Concluído | V84: Sem exemplo suficientemente equivalente no modelo para atribuir as três notas GUT. | W84: Acompanhamento da inspeção | X84: Definir representante do setor e garantir acompanhamento nas próximas inspeções. | Y84: Sem referência equivalente no modelo
A85: 84 | B85: 45608 | C85: Oncologia- 1D | D85: Segurança contra Incêndio | E85: SESMT | F85: Equipe sem conhecimento completo da rota de fuga. Atendimento parcial informado. | G85: Não | H85: 3 | I85: 3 | J85: 3 | K85: 27 | L85: Baixa | M85: A confirmar | N85: 45638 | O85: 45638 | P85: Concluído | Q85: Tratativa informada: Sim | R85: Segurança contra incêndio | S85: Orientar a equipe sobre a rota de fuga e verificar a compreensão. | T85: Modelo: ação 212 (linha 213) | U85: Concluído | V85: Tratativa informada: Sim | W85: Segurança das instalações | X85: Reforçar a orientação sobre vestimentas e calçados e acompanhar a adesão. | Y85: Modelo: ação 175 (linha 176)
A86: 85 | B86: 45608 | C86: Oncologia- 1D | D86: Segurança contra Incêndio | E86: SESMT | F86: Ausência informada de brigadistas no momento da inspeção. | G86: Não | L86: Pendente de avaliação | M86: A confirmar | N86: 45638 | O86: 45638 | P86: Concluído | Q86: Avaliar a aplicabilidade ao local antes de confirmar a não conformidade. Sem exemplo suficientemente equivalente no modelo para atribuir as três notas GUT. | R86: Segurança contra incêndio | S86: Solicitar ao SESMT avaliação da cobertura da brigada para o setor e horário. | T86: Sem referência equivalente no modelo | U86: Concluído | V86: Tratativa informada: Sim | W86: Segurança contra incêndio | X86: Solicitar atualização ou disponibilização do mapeamento da rota de fuga. | Y86: Modelo: ação 212 (linha 213)
A87: 86 | B87: 45608 | C87: Oncologia- 1D | D87: Segurança contra Incêndio | E87: SESMT | F87: Itens armazenados acima do limite de altura. Atendimento parcial informado. | G87: Não | H87: 3 | I87: 4 | J87: 3 | K87: 36 | L87: Moderada | M87: A confirmar | N87: 45638 | O87: 45638 | P87: Concluído | Q87: Tratativa informada: Sim | R87: Segurança contra incêndio | S87: Reorganizar os itens respeitando o limite de altura. | T87: Modelo: ação 159 (linha 160) | U87: Concluído | V87: Tratativa informada: Sim | W87: Segurança contra incêndio | X87: Orientar a equipe sobre a rota de fuga e verificar a compreensão. | Y87: Modelo: ação 212 (linha 213)
A88: 87 | B88: 45608 | C88: Oncologia- 1D | D88: Sistemas Utilitários | E88: Manutenção | F88: Inadequação nos espelhos de tomadas, interruptores ou pontos de rede. Atendimento parcial informado. | G88: Não | H88: 3 | I88: 3 | J88: 3 | K88: 27 | L88: Baixa | M88: A confirmar | N88: 45638 | O88: 45638 | P88: Concluído | Q88: Tratativa informada: Sim OS informada: Não registrado | R88: Segurança elétrica | S88: Abrir ou acompanhar OS para corrigir os espelhos indicados. | T88: Modelo: ação 305 (linha 306) | U88: Concluído | V88: Avaliar a aplicabilidade ao local antes de confirmar a não conformidade. Sem exemplo suficientemente equivalente no modelo para atribuir as três notas GUT. | W88: Segurança contra incêndio | X88: Solicitar ao SESMT avaliação da cobertura da brigada para o setor e horário. | Y88: Sem referência equivalente no modelo
A89: 88 | B89: 45608 | C89: Oncologia- 1D | D89: Sistemas Utilitários | E89: Manutenção | F89: Torneira assistencial que exige o uso das mãos para fechamento. Atendimento parcial informado. | G89: Não | H89: 3 | I89: 4 | J89: 3 | K89: 36 | L89: Moderada | M89: A confirmar | N89: 45638 | O89: 45638 | P89: Concluído | Q89: Tratativa informada: Não | R89: Controle de infecção e saneamento | S89: Solicitar adequação das torneiras ao modelo previsto para o uso. | T89: Modelo: ação 316 (linha 317) | U89: Concluído | V89: Tratativa informada: Sim | W89: Segurança contra incêndio | X89: Reorganizar os itens respeitando o limite de altura. | Y89: Modelo: ação 159 (linha 160)
A90: 89 | B90: 45608 | C90: Oncologia- 1D | D90: Segurança | E90: Manutenção | F90: Barreiras ou trancas de janelas inadequadas. | G90: Não | H90: 3 | I90: 3 | J90: 3 | K90: 27 | L90: Baixa | M90: A confirmar | N90: 45638 | O90: 45638 | P90: Concluído | Q90: Tratativa informada: Não | R90: Controle de infecção e saneamento | S90: Solicitar adequação das telas ou trancas das janelas. | T90: Modelo: ação 310 (linha 311) | U90: Concluído | V90: Tratativa informada: Sim OS informada: Não registrado | W90: Segurança elétrica | X90: Abrir ou acompanhar OS para corrigir os espelhos indicados. | Y90: Modelo: ação 305 (linha 306)
A91: 90 | B91: 45608 | C91: Oncologia- 1D | D91: Materiais e Resíduos Perigosos | E91: Hotelaria | F91: Lixeira com tampa sem fechamento adequado. Atendimento parcial informado. | G91: Não | H91: 3 | I91: 4 | J91: 3 | K91: 36 | L91: Moderada | M91: A confirmar | N91: 45638 | O91: 45638 | P91: Concluído | Q91: Tratativa informada: Sim | R91: Materiais e resíduos perigosos | S91: Regularizar o fechamento ou substituir a lixeira. | T91: Modelo: ação 328 (linha 329) | U91: Concluído | V91: Tratativa informada: Não | W91: Controle de infecção e saneamento | X91: Solicitar adequação das torneiras ao modelo previsto para o uso. | Y91: Modelo: ação 316 (linha 317)
A92: 91 | B92: 45608 | C92: Oncologia- 1D | D92: Segurança | E92: CCIH | F92: Avisos sem proteção adequada para higienização. Atendimento parcial informado. | G92: Não | H92: 2 | I92: 3 | J92: 3 | K92: 18 | L92: Baixa | M92: A confirmar | N92: 45638 | O92: 45638 | P92: Concluído | Q92: Tratativa informada: Sim | R92: Controle de infecção e saneamento | S92: Adequar a proteção e a fixação dos avisos. | T92: Modelo: ação 110 (linha 111) | U92: Concluído | V92: Tratativa informada: Não | W92: Controle de infecção e saneamento | X92: Solicitar adequação das telas ou trancas das janelas. | Y92: Modelo: ação 310 (linha 311)
A93: 92 | B93: 45608 | C93: Oncologia- 1D | D93: Materiais e Resíduos Perigosos | E93: Assistencial | F93: Identificação ou armazenamento inadequado de almotolias abertas. Atendimento parcial informado. | G93: Não | H93: 4 | I93: 5 | J93: 4 | K93: 80 | L93: Alta | M93: A confirmar | N93: 45638 | O93: 45638 | P93: Concluído | Q93: Tratativa informada: Sim | R93: Materiais e resíduos perigosos | S93: Regularizar identificação, armazenamento e controle de validade das almotolias. | T93: Modelo: ação 294 (linha 295) | U93: Concluído | V93: Tratativa informada: Sim | W93: Materiais e resíduos perigosos | X93: Regularizar o fechamento ou substituir a lixeira. | Y93: Modelo: ação 328 (linha 329)
A94: 93 | B94: 45608 | C94: Oncologia- 1D | D94: Sistemas Utilitários | E94: Manutenção | F94: Climatização com problema de funcionamento, sujidade ou vazamento. Atendimento parcial informado. | G94: Não | H94: 3 | I94: 4 | J94: 3 | K94: 36 | L94: Moderada | M94: A confirmar | N94: 45638 | O94: 45638 | P94: Concluído | Q94: Tratativa informada: Sim OS informada: Nao se aplica | R94: Climatização | S94: Solicitar avaliação, limpeza ou reparo do sistema de climatização. | T94: Modelo: ação 112 (linha 113) | U94: Concluído | V94: Tratativa informada: Sim | W94: Controle de infecção e saneamento | X94: Adequar a proteção e a fixação dos avisos. | Y94: Modelo: ação 110 (linha 111)
A95: 94 | B95: 45608 | C95: Oncologia- 1D | D95: Materiais e Resíduos Perigosos | E95: Área assistencial/administrativa | F95: Descarte de resíduo incompatível com a identificação da lixeira. Atendimento parcial informado. | G95: Não | H95: 3 | I95: 4 | J95: 3 | K95: 36 | L95: Moderada | M95: A confirmar | N95: 45638 | O95: 45638 | P95: Concluído | Q95: Tratativa informada: Sim | R95: Materiais e resíduos perigosos | S95: Corrigir a segregação de resíduos e reforçar as orientações à equipe. | T95: Modelo: ação 124 (linha 125) | U95: Concluído | V95: Tratativa informada: Sim | W95: Materiais e resíduos perigosos | X95: Regularizar identificação, armazenamento e controle de validade das almotolias. | Y95: Modelo: ação 294 (linha 295)
A96: 95 | B96: 45615 | C96: PSI | D96: Avaliação de Riscos e Monitoramento | E96: Qualidade | F96: Inspeção sem acompanhamento do responsável ou de pessoa designada. | G96: Não | L96: Pendente de avaliação | M96: A confirmar | N96: 45645 | O96: 45638 | P96: Concluído | Q96: Sem exemplo suficientemente equivalente no modelo para atribuir as três notas GUT. | R96: Acompanhamento da inspeção | S96: Definir representante do setor e garantir acompanhamento nas próximas inspeções. | T96: Sem referência equivalente no modelo | U96: Concluído | V96: Tratativa informada: Sim OS informada: Nao se aplica | W96: Climatização | X96: Solicitar avaliação, limpeza ou reparo do sistema de climatização. | Y96: Modelo: ação 112 (linha 113)
A97: 96 | B97: 45615 | C97: PSI | D97: Segurança | E97: SESMT | F97: Uso de adornos durante as atividades. | G97: Não | H97: 3 | I97: 3 | J97: 3 | K97: 27 | L97: Baixa | M97: A confirmar | N97: 45645 | O97: 45645 | P97: Concluído | Q97: Tratativa informada: Não | R97: Segurança das instalações | S97: Orientar a equipe sobre a padronização de adornos e verificar a adesão. | T97: Modelo: ação 175 (linha 176) | U97: Concluído | V97: Tratativa informada: Sim | W97: Materiais e resíduos perigosos | X97: Corrigir a segregação de resíduos e reforçar as orientações à equipe. | Y97: Modelo: ação 124 (linha 125)
A98: 97 | B98: 45615 | C98: PSI | D98: Segurança contra Incêndio | E98: SESMT | F98: Mapeamento da rota de fuga não disponível. | G98: Não | H98: 3 | I98: 3 | J98: 3 | K98: 27 | L98: Baixa | M98: A confirmar | N98: 45645 | O98: 45645 | P98: Concluído | Q98: Tratativa informada: Sim | R98: Segurança contra incêndio | S98: Solicitar atualização ou disponibilização do mapeamento da rota de fuga. | T98: Modelo: ação 212 (linha 213) | U98: Concluído | V98: Sem exemplo suficientemente equivalente no modelo para atribuir as três notas GUT. | W98: Acompanhamento da inspeção | X98: Definir representante do setor e garantir acompanhamento nas próximas inspeções. | Y98: Sem referência equivalente no modelo
A99: 98 | B99: 45615 | C99: PSI | D99: Segurança contra Incêndio | E99: SESMT | F99: Sinalização da rota de fuga ausente ou incompleta. Atendimento parcial informado. | G99: Não | H99: 3 | I99: 3 | J99: 3 | K99: 27 | L99: Baixa | M99: A confirmar | N99: 45645 | O99: 45645 | P99: Concluído | Q99: Tratativa informada: Sim | R99: Segurança contra incêndio | S99: Solicitar adequação da sinalização da rota de fuga. | T99: Modelo: ação 231 (linha 232) | U99: Concluído | V99: Tratativa informada: Não | W99: Segurança das instalações | X99: Orientar a equipe sobre a padronização de adornos e verificar a adesão. | Y99: Modelo: ação 175 (linha 176)
A100: 99 | B100: 45615 | C100: PSI | D100: Segurança contra Incêndio | E100: SESMT | F100: Ausência de sinalização de limite de altura para armazenamento. | G100: Não | H100: 3 | I100: 3 | J100: 3 | K100: 27 | L100: Baixa | M100: A confirmar | N100: 45645 | O100: 45645 | P100: Concluído | Q100: Avaliar a aplicabilidade ao local antes de confirmar a não conformidade. Tratativa informada: Sim | R100: Segurança contra incêndio | S100: Solicitar definição e sinalização do limite de altura aplicável. | T100: Modelo: ação 179 (linha 180) | U100: Concluído | V100: Tratativa informada: Sim | W100: Segurança contra incêndio | X100: Solicitar atualização ou disponibilização do mapeamento da rota de fuga. | Y100: Modelo: ação 212 (linha 213)
A101: 100 | B101: 45615 | C101: PSI | D101: Sistemas Utilitários | E101: Manutenção | F101: Identificação de voltagem ausente ou incompleta nas tomadas. Atendimento parcial informado. | G101: Não | H101: 3 | I101: 3 | J101: 3 | K101: 27 | L101: Baixa | M101: A confirmar | N101: 45645 | O101: 45645 | P101: Concluído | R101: Segurança elétrica | S101: Providenciar identificação da voltagem após verificação técnica. | T101: Modelo: ação 240 (linha 241) | U101: Concluído | V101: Tratativa informada: Sim | W101: Segurança contra incêndio | X101: Solicitar adequação da sinalização da rota de fuga. | Y101: Modelo: ação 231 (linha 232)
A102: 101 | B102: 45615 | C102: PSI | D102: Segurança | E102: Manutenção | F102: Barreiras ou trancas de janelas inadequadas. | G102: Não | H102: 3 | I102: 3 | J102: 3 | K102: 27 | L102: Baixa | M102: A confirmar | N102: 45645 | O102: 45645 | P102: Concluído | Q102: Tratativa informada: Não | R102: Controle de infecção e saneamento | S102: Solicitar adequação das telas ou trancas das janelas. | T102: Modelo: ação 310 (linha 311) | U102: Concluído | V102: Avaliar a aplicabilidade ao local antes de confirmar a não conformidade. Tratativa informada: Sim | W102: Segurança contra incêndio | X102: Solicitar definição e sinalização do limite de altura aplicável. | Y102: Modelo: ação 179 (linha 180)
A103: 102 | B103: 45615 | C103: PSI | D103: Proteção | E103: Manutenção | F103: Armário sob pia sem fechamento ou segregação adequados. Atendimento parcial informado. | G103: Não | H103: 3 | I103: 3 | J103: 3 | K103: 27 | L103: Baixa | M103: A confirmar | N103: 45645 | O103: 45645 | P103: Concluído | Q103: Tratativa informada: Não | R103: Segurança patrimonial | S103: Verificar o conteúdo e regularizar o fechamento dos armários sob pias. | T103: Modelo: ação 272 (linha 273) | U103: Concluído | W103: Segurança elétrica | X103: Providenciar identificação da voltagem após verificação técnica. | Y103: Modelo: ação 240 (linha 241)
...

Sheet Interações Rounds
A1: Categoria' | B1: Subcategoria | C1: Mês | D1: Número Mês | E1: Quantidade
A2: Infra e Hotelaria | B2: Ar Condicionado | C2: Janeiro | D2: 1 | E2: 6
A3: Infra e Hotelaria | B3: Ar Condicionado | C3: Fevereiro | D3: 2 | E3: 6
A4: Infra e Hotelaria | B4: Ar Condicionado | C4: Março | D4: 3 | E4: 20
A5: Infra e Hotelaria | B5: Ar Condicionado | C5: Abril | D5: 4 | E5: 11
A6: Infra e Hotelaria | B6: Ar Condicionado | C6: Maio | D6: 5 | E6: 8
A7: Infra e Hotelaria | B7: Ar Condicionado | C7: Junho | D7: 6 | E7: 1
A8: Infra e Hotelaria | B8: Ar Condicionado | C8: Julho | D8: 7 | E8: 0
A9: Infra e Hotelaria | B9: Ar Condicionado | C9: Agosto | D9: 8 | E9: 0
A10: Infra e Hotelaria | B10: Ar Condicionado | C10: Setembro | D10: 9 | E10: 0
A11: Infra e Hotelaria | B11: Ar Condicionado | C11: Outubro | D11: 10 | E11: 0
A12: Infra e Hotelaria | B12: Ar Condicionado | C12: Novembro | D12: 11 | E12: 2
A13: Infra e Hotelaria | B13: Ar Condicionado | C13: Dezembro | D13: 12 | E13: 2
... A193: Assistencial | B193: Problema/Demora alimentação | C193: Dezembro | D193: 12 | E193: 0
A194: Assistencial | C194: Janeiro | D194: 1 | E194: 0
A195: Assistencial | C195: Fevereiro | D195: 2 | E195: 0
A196: Assistencial | C196: Março | D196: 3 | E196: 0
A197: Assistencial | C197: Abril | D197: 4 | E197: 0
A198: Assistencial | C198: Maio | D198: 5 | E198: 0
A199: Assistencial | B199: Problema Solicitações Q24 | C199: Junho | D199: 6 | E199: 1
A200: Assistencial | B200: Problema Solicitações Q24 | C200: Julho | D200: 7 | E200: 0
A201: Assistencial | B201: Problema Solicitações Q24 | C201: Agosto | D201: 8 | E201: 0
A202: Assistencial | B202: Problema Solicitações Q24 | C202: Setembro | D202: 9 | E202: 0
A203: Assistencial | B203: Problema Solicitações Q24 | C203: Outubro | D203: 10 | E203: 0
A204: Assistencial | B204: Problema Solicitações Q24 | C204: Novembro | D204: 11 | E204: 0
A205: Assistencial | B205: Problema Solicitações Q24 | C205: Dezembro | D205: 12 | E205: 0
A206: Assistencial | B206: Demora Medicação | C206: Janeiro | D206: 1 | E206: 0
A207: Assistencial | B207: Demora Medicação | C207: Fevereiro | D207: 2 | E207: 0
A208: Assistencial | B208: Demora Medicação | C208: Março | D208: 3 | E208: 0
A209: Assistencial | B209: Demora Medicação | C209: Abril | D209: 4 | E209: 0
A210: Assistencial | B210: Demora Medicação | C210: Maio | D210: 5 | E210: 0
... A709: Sistemas Informações | B709: Dúvidas Solicitação de Prontuário | C709: Dezembro | D709: 12 | E709: 0

Sheet Rounds
A1: Responsáveis | B1: Setores | C1: Ano | D1: Meses | E1: Realizados | F1: Previstos | G1: Pendentes | H1: % de Realizados
A2: Melissa Cogo e Carmela | B2: 1°D | C2: 2026 | D2: Janeiro | E2: 12 | F2: 12 | G2: =Rounds!$F2-Rounds!$E2 | H2: =Rounds!$E2/Rounds!$F2
A3: Melissa Cogo e Carmela | B3: 1°D | C3: 2026 | D3: Fevereiro | E3: 12 | F3: 12 | G3: =Rounds!$F3-Rounds!$E3 | H3: =Rounds!$E3/Rounds!$F3
A4: Melissa Cogo e Carmela | B4: 1°D | C4: 2026 | D4: Março | E4: 12 | F4: 12 | G4: =Rounds!$F4-Rounds!$E4 | H4: =Rounds!$E4/Rounds!$F4
A5: Melissa Cogo e Carmela | B5: 1°D | C5: 2026 | D5: Abril | E5: 15 | F5: 15 | G5: =Rounds!$F5-Rounds!$E5 | H5: =Rounds!$E5/Rounds!$F5
A6: Melissa Cogo e Carmela | B6: 1°D | C6: 2026 | D6: Maio | E6: 12 | F6: 12 | G6: =Rounds!$F6-Rounds!$E6 | H6: =Rounds!$E6/Rounds!$F6
A7: Melissa Cogo e Carmela | B7: 1°D | C7: 2026 | D7: Junho | E7: 12 | F7: 12 | G7: =Rounds!$F7-Rounds!$E7 | H7: =Rounds!$E7/Rounds!$F7
A8: Melissa Cogo e Carmela | B8: 1°D | C8: 2026 | D8: Julho | E8: 15 | F8: 15 | G8: =Rounds!$F8-Rounds!$E8 | H8: =Table6[[#This Row],[Realizados]]/Table6[[#This Row],[Previstos]]
A9: Melissa Cogo e Carmela | B9: 1°D | C9: 2026 | D9: Agosto | E9: 12 | F9: 12 | G9: =Rounds!$F9-Rounds!$E9 | H9: 0
A10: Melissa Cogo e Carmela | B10: 1°D | C10: 2026 | D10: Setembro | E10: 15 | F10: 15 | G10: =Rounds!$F10-Rounds!$E10 | H10: =Table6[[#This Row],[Realizados]]/Table6[[#This Row],[Previstos]]
A11: Melissa Cogo e Carmela | B11: 1°D | C11: 2026 | D11: Outubro | E11: 0 | F11: 0 | G11: =Rounds!$F11-Rounds!$E11 | H11: 0
A12: Melissa Cogo e Carmela | B12: 1°D | C12: 2026 | D12: Novembro | E12: 0 | F12: 0 | G12: =Rounds!$F12-Rounds!$E12 | H12: 0
A13: Melissa Cogo e Carmela | B13: 1°D | C13: 2026 | D13: Dezembro | E13: 0 | F13: 0 | G13: =Rounds!$F13-Rounds!$E13 | H13: 0
A14: Danielle e Dr. Eduardo | B14: 2°C | C14: 2026 | D14: Janeiro | E14: 12 | F14: 12 | G14: =Rounds!$F14-Rounds!$E14 | H14: =Rounds!$E14/Rounds!$F14
A15: Danielle e Dr. Eduardo | B15: 2°C | C15: 2026 | D15: Fevereiro | E15: 12 | F15: 12 | G15: =Rounds!$F15-Rounds!$E15 | H15: =Rounds!$E15/Rounds!$F15
A16: Danielle e Dr. Eduardo | B16: 2°C | C16: 2026 | D16: Março | E16: 12 | F16: 12 | G16: =Rounds!$F16-Rounds!$E16 | H16: =Rounds!$E16/Rounds!$F16
A17: Danielle e Dr. Eduardo | B17: 2°C | C17: 2026 | D17: Abril | E17: 12 | F17: 15 | G17: =Rounds!$F17-Rounds!$E17 | H17: =Rounds!$E17/Rounds!$F17
A18: Danielle e Dr. Eduardo | B18: 2°C | C18: 2026 | D18: Maio | E18: 12 | F18: 12 | G18: =Rounds!$F18-Rounds!$E18 | H18: =Rounds!$E18/Rounds!$F18
A19: Danielle e Dr. Eduardo | B19: 2°C | C19: 2026 | D19: Junho | E19: 2 | F19: 12 | G19: =Rounds!$F19-Rounds!$E19 | H19: =Rounds!$E19/Rounds!$F19
A20: Danielle e Dr. Eduardo | B20: 2°C | C20: 2026 | D20: Julho | E20: 11 | F20: 14 | G20: =Rounds!$F20-Rounds!$E20 | H20: =Table6[[#This Row],[Realizados]]/Table6[[#This Row],[Previstos]]
A21: Danielle e Dr. Eduardo | B21: 2°C | C21: 2026 | D21: Agosto | E21: 12 | F21: 12 | G21: =Rounds!$F21-Rounds!$E21 | H21: 0
A22: Danielle e Dr. Eduardo | B22: 2°C | C22: 2026 | D22: Setembro | E22: 13 | F22: 15 | G22: =Rounds!$F22-Rounds!$E22 | H22: =Table6[[#This Row],[Realizados]]/Table6[[#This Row],[Previstos]]
A23: Danielle e Dr. Eduardo | B23: 2°C | C23: 2026 | D23: Outubro | E23: 0 | F23: 0 | G23: =Rounds!$F23-Rounds!$E23 | H23: 0
A24: Danielle e Dr. Eduardo | B24: 2°C | C24: 2026 | D24: Novembro | E24: 0 | F24: 0 | G24: =Rounds!$F24-Rounds!$E24 | H24: 0
A25: Danielle e Dr. Eduardo | B25: 2°C | C25: 2026 | D25: Dezembro | E25: 0 | F25: 0 | G25: =Rounds!$F25-Rounds!$E25 | H25: 0
A26: Dr. Giroto e Thiago | B26: 2°D | C26: 2026 | D26: Janeiro | E26: 4 | F26: 12 | G26: =Rounds!$F26-Rounds!$E26 | H26: =Rounds!$E26/Rounds!$F26
A27: Dr. Giroto e Thiago | B27: 2°D | C27: 2026 | D27: Fevereiro | E27: 11 | F27: 12 | G27: =Rounds!$F27-Rounds!$E27 | H27: =Rounds!$E27/Rounds!$F27
A28: Dr. Giroto e Thiago | B28: 2°D | C28: 2026 | D28: Março | E28: 8 | F28: 12 | G28: =Rounds!$F28-Rounds!$E28 | H28: =Rounds!$E28/Rounds!$F28
A29: Dr. Giroto e Thiago | B29: 2°D | C29: 2026 | D29: Abril | E29: 14 | F29: 15 | G29: =Rounds!$F29-Rounds!$E29 | H29: =Rounds!$E29/Rounds!$F29
A30: Dr. Giroto e Thiago | B30: 2°D | C30: 2026 | D30: Maio | E30: 9 | F30: 12 | G30: =Rounds!$F30-Rounds!$E30 | H30: =Rounds!$E30/Rounds!$F30
A31: Dr. Giroto e Thiago | B31: 2°D | C31: 2026 | D31: Junho | E31: 8 | F31: 12 | G31: =Rounds!$F31-Rounds!$E31 | H31: =Rounds!$E31/Rounds!$F31
A32: Dr. Giroto e Thiago | B32: 2°D | C32: 2026 | D32: Julho | E32: 10 | F32: 15 | G32: =Rounds!$F32-Rounds!$E32 | H32: =Table6[[#This Row],[Realizados]]/Table6[[#This Row],[Previstos]]
A33: Dr. Giroto e Thiago | B33: 2°D | C33: 2026 | D33: Agosto | E33: 10 | F33: 12 | G33: =Rounds!$F33-Rounds!$E33 | H33: 0
A34: Dr. Giroto e Thiago | B34: 2°D | C34: 2026 | D34: Setembro | E34: 9 | F34: 15 | G34: =Rounds!$F34-Rounds!$E34 | H34: =Table6[[#This Row],[Realizados]]/Table6[[#This Row],[Previstos]]
A35: Dr. Giroto e Thiago | B35: 2°D | C35: 2026 | D35: Outubro | E35: 0 | F35: 0 | G35: =Rounds!$F35-Rounds!$E35 | H35: 0
A36: Dr. Giroto e Thiago | B36: 2°D | C36: 2026 | D36: Novembro | E36: 0 | F36: 0 | G36: =Rounds!$F36-Rounds!$E36 | H36: 0
A37: Dr. Giroto e Thiago | B37: 2°D | C37: 2026 | D37: Dezembro | E37: 0 | F37: 0 | G37: =Rounds!$F37-Rounds!$E37 | H37: 0
A38: Lilian | B38: Semi 2 | C38: 2026 | D38: Janeiro | E38: 12 | F38: 12 | G38: =Rounds!$F38-Rounds!$E38 | H38: =Rounds!$E38/Rounds!$F38
A39: Lilian | B39: Semi 2 | C39: 2026 | D39: Fevereiro | E39: 12 | F39: 12 | G39: =Rounds!$F39-Rounds!$E39 | H39: =Rounds!$E39/Rounds!$F39
A40: Lilian | B40: Semi 2 | C40: 2026 | D40: Março | E40: 12 | F40: 12 | G40: =Rounds!$F40-Rounds!$E40 | H40: =Rounds!$E40/Rounds!$F40
A41: Lilian | B41: Semi 2 | C41: 2026 | D41: Abril | E41: 15 | F41: 15 | G41: =Rounds!$F41-Rounds!$E41 | H41: =Rounds!$E41/Rounds!$F41
A42: Lilian | B42: Semi 2 | C42: 2026 | D42: Maio | E42: 11 | F42: 12 | G42: =Rounds!$F42-Rounds!$E42 | H42: =Rounds!$E42/Rounds!$F42
A43: Lilian | B43: Semi 2 | C43: 2026 | D43: Junho | E43: 12 | F43: 12 | G43: =Rounds!$F43-Rounds!$E43 | H43: =Rounds!$E43/Rounds!$F43
A44: Lilian | B44: Semi 2 | C44: 2026 | D44: Julho | E44: 15 | F44: 15 | G44: =Rounds!$F44-Rounds!$E44 | H44: =Table6[[#This Row],[Realizados]]/Table6[[#This Row],[Previstos]]
A45: Lilian | B45: Semi 2 | C45: 2026 | D45: Agosto | E45: 12 | F45: 12 | G45: =Rounds!$F45-Rounds!$E45 | H45: 0
A46: Lilian | B46: Semi 2 | C46: 2026 | D46: Setembro | E46: 14 | F46: 15 | G46: =Rounds!$F46-Rounds!$E46 | H46: =Table6[[#This Row],[Realizados]]/Table6[[#This Row],[Previstos]]
A47: Lilian | B47: Semi 2 | C47: 2026 | D47: Outubro | E47: 0 | F47: 0 | G47: =Rounds!$F47-Rounds!$E47 | H47: 0
A48: Lilian | B48: Semi 2 | C48: 2026 | D48: Novembro | E48: 0 | F48: 0 | G48: =Rounds!$F48-Rounds!$E48 | H48: 0
A49: Lilian | B49: Semi 2 | C49: 2026 | D49: Dezembro | E49: 0 | F49: 0 | G49: =Rounds!$F49-Rounds!$E49 | H49: 0
A50: Dr. Gabriel | B50: UCO | C50: 2026 | D50: Janeiro | E50: 12 | F50: 12 | G50: =Rounds!$F50-Rounds!$E50 | H50: =Rounds!$E50/Rounds!$F50
A51: Dr. Gabriel | B51: UCO | C51: 2026 | D51: Fevereiro | E51: 12 | F51: 12 | G51: =Rounds!$F51-Rounds!$E51 | H51: =Rounds!$E51/Rounds!$F51
A52: Dr. Gabriel | B52: UCO | C52: 2026 | D52: Março | E52: 12 | F52: 12 | G52: =Rounds!$F52-Rounds!$E52 | H52: =Rounds!$E52/Rounds!$F52
A53: Dr. Gabriel | B53: UCO | C53: 2026 | D53: Abril | E53: 15 | F53: 15 | G53: =Rounds!$F53-Rounds!$E53 | H53: =Rounds!$E53/Rounds!$F53
A54: Dr. Gabriel | B54: UCO | C54: 2026 | D54: Maio | E54: 12 | F54: 12 | G54: =Rounds!$F54-Rounds!$E54 | H54: =Rounds!$E54/Rounds!$F54
A55: Dr. Gabriel | B55: UCO | C55: 2026 | D55: Junho | E55: 12 | F55: 12 | G55: =Rounds!$F55-Rounds!$E55 | H55: =Rounds!$E55/Rounds!$F55
A56: Dr. Gabriel | B56: UCO | C56: 2026 | D56: Julho | E56: 15 | F56: 15 | G56: =Rounds!$F56-Rounds!$E56 | H56: =Table6[[#This Row],[Realizados]]/Table6[[#This Row],[Previstos]]
A57: Dr. Gabriel | B57: UCO | C57: 2026 | D57: Agosto | E57: 12 | F57: 12 | G57: =Rounds!$F57-Rounds!$E57 | H57: 0
A58: Dr. Gabriel | B58: UCO | C58: 2026 | D58: Setembro | E58: 15 | F58: 15 | G58: =Rounds!$F58-Rounds!$E58 | H58: =Table6[[#This Row],[Realizados]]/Table6[[#This Row],[Previstos]]
A59: Dr. Gabriel | B59: UCO | C59: 2026 | D59: Outubro | E59: 0 | F59: 0 | G59: =Rounds!$F59-Rounds!$E59 | H59: 0
A60: Dr. Gabriel | B60: UCO | C60: 2026 | D60: Novembro | E60: 0 | F60: 0 | G60: =Rounds!$F60-Rounds!$E60 | H60: 0
A61: Dr. Gabriel | B61: UCO | C61: 2026 | D61: Dezembro | E61: 0 | F61: 0 | G61: =Rounds!$F61-Rounds!$E61 | H61: 0
A62: Bianca | B62: Semi 1 | C62: 2026 | D62: Janeiro | E62: 8 | F62: 12 | G62: =Rounds!$F62-Rounds!$E62 | H62: =Rounds!$E62/Rounds!$F62
A63: Bianca | B63: Semi 1 | C63: 2026 | D63: Fevereiro | E63: 10 | F63: 12 | G63: =Rounds!$F63-Rounds!$E63 | H63: =Rounds!$E63/Rounds!$F63
A64: Bianca | B64: Semi 1 | C64: 2026 | D64: Março | E64: 11 | F64: 12 | G64: =Rounds!$F64-Rounds!$E64 | H64: =Rounds!$E64/Rounds!$F64
A65: Bianca | B65: Semi 1 | C65: 2026 | D65: Abril | E65: 15 | F65: 15 | G65: =Rounds!$F65-Rounds!$E65 | H65: =Rounds!$E65/Rounds!$F65
A66: Bianca | B66: Semi 1 | C66: 2026 | D66: Maio | E66: 12 | F66: 12 | G66: =Rounds!$F66-Rounds!$E66 | H66: =Rounds!$E66/Rounds!$F66
A67: Bianca | B67: Semi 1 | C67: 2026 | D67: Junho | E67: 8 | F67: 12 | G67: =Rounds!$F67-Rounds!$E67 | H67: =Rounds!$E67/Rounds!$F67
A68: Bianca | B68: Semi 1 | C68: 2026 | D68: Julho | E68: 11 | F68: 15 | G68: =Rounds!$F68-Rounds!$E68 | H68: =Table6[[#This Row],[Realizados]]/Table6[[#This Row],[Previstos]]
A69: Bianca | B69: Semi 1 | C69: 2026 | D69: Agosto | E69: 12 | F69: 12 | G69: =Rounds!$F69-Rounds!$E69 | H69: 0
A70: Bianca | B70: Semi 1 | C70: 2026 | D70: Setembro | E70: 13 | F70: 15 | G70: =Rounds!$F70-Rounds!$E70 | H70: =Table6[[#This Row],[Realizados]]/Table6[[#This Row],[Previstos]]
A71: Bianca | B71: Semi 1 | C71: 2026 | D71: Outubro | E71: 0 | F71: 0 | G71: =Rounds!$F71-Rounds!$E71 | H71: 0
A72: Bianca | B72: Semi 1 | C72: 2026 | D72: Novembro | E72: 0 | F72: 0 | G72: =Rounds!$F72-Rounds!$E72 | H72: 0
A73: Bianca | B73: Semi 1 | C73: 2026 | D73: Dezembro | E73: 0 | F73: 0 | G73: =Rounds!$F73-Rounds!$E73 | H73: 0
A74: Melissa Savy | B74: 3°D | C74: 2026 | D74: Janeiro | E74: 6 | F74: 12 | G74: =Rounds!$F74-Rounds!$E74 | H74: =Rounds!$E74/Rounds!$F74
A75: Melissa Savy | B75: 3°D | C75: 2026 | D75: Fevereiro | E75: 5 | F75: 12 | G75: =Rounds!$F75-Rounds!$E75 | H75: =Rounds!$E75/Rounds!$F75
A76: Melissa Savy | B76: 3°D | C76: 2026 | D76: Março | E76: 8 | F76: 12 | G76: =Rounds!$F76-Rounds!$E76 | H76: =Rounds!$E76/Rounds!$F76
A77: Melissa Savy | B77: 3°D | C77: 2026 | D77: Abril | E77: 14 | F77: 15 | G77: =Rounds!$F77-Rounds!$E77 | H77: =Rounds!$E77/Rounds!$F77
A78: Melissa Savy | B78: 3°D | C78: 2026 | D78: Maio | E78: 10 | F78: 12 | G78: =Rounds!$F78-Rounds!$E78 | H78: =Rounds!$E78/Rounds!$F78
A79: Melissa Savy | B79: 3°D | C79: 2026 | D79: Junho | E79: 9 | F79: 12 | G79: =Rounds!$F79-Rounds!$E79 | H79: =Rounds!$E79/Rounds!$F79
A80: Melissa Savy | B80: 3°D | C80: 2026 | D80: Julho | E80: 15 | F80: 15 | G80: =Rounds!$F80-Rounds!$E80 | H80: =Table6[[#This Row],[Realizados]]/Table6[[#This Row],[Previstos]]
A81: Melissa Savy | B81: 3°D | C81: 2026 | D81: Agosto | E81: 12 | F81: 12 | G81: =Rounds!$F81-Rounds!$E81 | H81: 0
A82: Melissa Savy | B82: 3°D | C82: 2026 | D82: Setembro | E82: 13 | F82: 15 | G82: =Rounds!$F82-Rounds!$E82 | H82: =Table6[[#This Row],[Realizados]]/Table6[[#This Row],[Previstos]]
A83: Melissa Savy | B83: 3°D | C83: 2026 | D83: Outubro | E83: 0 | F83: 0 | G83: =Rounds!$F83-Rounds!$E83 | H83: 0
A84: Melissa Savy | B84: 3°D | C84: 2026 | D84: Novembro | E84: 0 | F84: 0 | G84: =Rounds!$F84-Rounds!$E84 | H84: 0
A85: Melissa Savy | B85: 3°D | C85: 2026 | D85: Dezembro | E85: 0 | F85: 0 | G85: =Rounds!$F85-Rounds!$E85 | H85: 0
A86: Claudia | B86: Neurologia | C86: 2026 | D86: Janeiro | E86: 11 | F86: 12 | G86: =Rounds!$F86-Rounds!$E86 | H86: =Rounds!$E86/Rounds!$F86
A87: Claudia | B87: Neurologia | C87: 2026 | D87: Fevereiro | E87: 12 | F87: 12 | G87: =Rounds!$F87-Rounds!$E87 | H87: =Rounds!$E87/Rounds!$F87
A88: Claudia | B88: Neurologia | C88: 2026 | D88: Março | E88: 12 | F88: 12 | G88: =Rounds!$F88-Rounds!$E88 | H88: =Rounds!$E88/Rounds!$F88
A89: Claudia | B89: Neurologia | C89: 2026 | D89: Abril | E89: 15 | F89: 15 | G89: =Rounds!$F89-Rounds!$E89 | H89: =Rounds!$E89/Rounds!$F89
A90: Claudia | B90: Neurologia | C90: 2026 | D90: Maio | E90: 11 | F90: 12 | G90: =Rounds!$F90-Rounds!$E90 | H90: =Rounds!$E90/Rounds!$F90
A91: Claudia | B91: Neurologia | C91: 2026 | D91: Junho | E91: 12 | F91: 12 | G91: =Rounds!$F91-Rounds!$E91 | H91: =Rounds!$E91/Rounds!$F91
A92: Claudia | B92: Neurologia | C92: 2026 | D92: Julho | E92: 15 | F92: 15 | G92: =Rounds!$F92-Rounds!$E92 | H92: =Table6[[#This Row],[Realizados]]/Table6[[#This Row],[Previstos]]
A93: Claudia | B93: Neurologia | C93: 2026 | D93: Agosto | E93: 12 | F93: 12 | G93: =Rounds!$F93-Rounds!$E93 | H93: 0
A94: Claudia | B94: Neurologia | C94: 2026 | D94: Setembro | E94: 15 | F94: 15 | G94: =Rounds!$F94-Rounds!$E94 | H94: =Table6[[#This Row],[Realizados]]/Table6[[#This Row],[Previstos]]
A95: Claudia | B95: Neurologia | C95: 2026 | D95: Outubro | E95: 0 | F95: 0 | G95: =Rounds!$F95-Rounds!$E95 | H95: 0
A96: Claudia | B96: Neurologia | C96: 2026 | D96: Novembro | E96: 0 | F96: 0 | G96: =Rounds!$F96-Rounds!$E96 | H96: 0
A97: Claudia | B97: Neurologia | C97: 2026 | D97: Dezembro | E97: 0 | F97: 0 | G97: =Rounds!$F97-Rounds!$E97 | H97: 0
A98: Simone | B98: PED/UTI PED | C98: 2026 | D98: Janeiro | E98: 11 | F98: 12 | G98: =Rounds!$F98-Rounds!$E98 | H98: =Rounds!$E98/Rounds!$F98
A99: Simone | B99: PED/UTI PED | C99: 2026 | D99: Fevereiro | E99: 10 | F99: 12 | G99: =Rounds!$F99-Rounds!$E99 | H99: =Rounds!$E99/Rounds!$F99
A100: Simone | B100: PED/UTI PED | C100: 2026 | D100: Março | E100: 7 | F100: 12 | G100: =Rounds!$F100-Rounds!$E100 | H100: =Rounds!$E100/Rounds!$F100
...

Sheet Interações Round
A1: Mês | B1: Ano | C1: Categoria | D1: Interação | E1: Quartos | F1: Setor
A2: Janeiro | B2: 2026 | C2: Infra e Hotelaria | D2: Climatização | E2: Quarto 112 | F2: 1°D
A3: Janeiro | B3: 2026 | C3: Infra e Hotelaria | D3: Hotelaria/Rouparia | E3: Quarto 315 | F3: 3°D
A4: Janeiro | B4: 2026 | C4: Infra e Hotelaria | D4: Hotelaria/Rouparia | E4: Quarto 432 | F4: PED/UTI PED
A5: Janeiro | B5: 2026 | C5: Infra e Hotelaria | D5: Manutenção/Instalações | E5: Setor | F5: 1°D
A6: Janeiro | B6: 2026 | C6: Infra e Hotelaria | D6: Manutenção/Instalações | E6: Setor | F6: UTI NEO/8°D
A7: Janeiro | B7: 2026 | C7: Infra e Hotelaria | D7: Climatização | E7: Quarto 405 | F7: 4°D
A8: Janeiro | B8: 2026 | C8: Infra e Hotelaria | D8: Hotelaria/Rouparia | E8: Quarto 415 | F8: 4°D
A9: Janeiro | B9: 2026 | C9: Infra e Hotelaria | D9: Manutenção/Instalações | E9: Quarto 317 | F9: Semi 1
A10: Janeiro | B10: 2026 | C10: Infra e Hotelaria | D10: Manutenção/Instalações | E10: Setor | F10: 1°D
A11: Janeiro | B11: 2026 | C11: Infra e Hotelaria | D11: Engenharia Clínica | E11: Quarto 432 | F11: PED/UTI PED
A12: Janeiro | B12: 2026 | C12: Infra e Hotelaria | D12: Climatização | E12: Quarto 214 | F12: 2°D
A13: Janeiro | B13: 2026 | C13: Infra e Hotelaria | D13: Manutenção/Instalações | E13: Quarto 704 | F13: Maternidade
... A4056: Março | B4056: 2023 | C4056: Sistemas de Informação | D4056: Dispositivos Digitais | E4056: Setor | F4056: 1°D
A4057: Março | B4057: 2023 | C4057: Sistemas de Informação | D4057: Dispositivos Digitais | E4057: 203 | F4057: 2°D
A4058: Março | B4058: 2023 | C4058: Sistemas de Informação | D4058: Dispositivos Digitais | E4058: Setor | F4058: Centro Cirúrgico
A4059: Março | B4059: 2023 | C4059: Sistemas de Informação | D4059: Dispositivos Digitais | E4059: Agrupado na fonte — UTI | F4059: Não informado na fonte
A4060: Março | B4060: 2023 | C4060: Sistemas de Informação | D4060: Dispositivos Digitais | E4060: Agrupado na fonte — UTI | F4060: Não informado na fonte
A4061: Março | B4061: 2023 | C4061: Sistemas de Informação | D4061: Dispositivos Digitais | E4061: Paciente relata estar sem na acomodação | F4061: Não informado na fonte
A4062: Março | B4062: 2023 | C4062: Sistemas de Informação | D4062: Dispositivos Digitais | E4062: Posto enf 2ºD | F4062: Não informado na fonte
A4063: Abril | B4063: 2023 | C4063: Infra e Hotelaria | D4063: Manutenção/Instalações | E4063: Agrupado na fonte — UTI A | F4063: Não informado na fonte
A4064: Abril | B4064: 2023 | C4064: Infra e Hotelaria | D4064: Manutenção/Instalações | E4064: Agrupado na fonte — UTI A | F4064: Não informado na fonte
A4065: Abril | B4065: 2023 | C4065: Infra e Hotelaria | D4065: Manutenção/Instalações | E4065: Mater | F4065: Não informado na fonte
A4066: Abril | B4066: 2023 | C4066: Infra e Hotelaria | D4066: Engenharia Clínica | E4066: Setor | F4066: 3°D
A4067: Abril | B4067: 2023 | C4067: Infra e Hotelaria | D4067: Engenharia Clínica | E4067: Setor | F4067: Não informado na fonte
A4068: Abril | B4068: 2023 | C4068: Assistencial | D4068: Medicamentos/Farmácia | E4068: Setor | F4068: 2°D
A4069: Abril | B4069: 2023 | C4069: Assistencial | D4069: Medicamentos/Farmácia | E4069: Setor | F4069: Não informado na fonte
... A4071: Abril | B4071: 2023 | C4071: Sistemas de Informação | D4071: Sistemas/TI/Conectividade | E4071: Setor | F4071: Não informado na fonte
A4072: Maio | B4072: 2023 | C4072: Infra e Hotelaria | D4072: Manutenção/Instalações | E4072: 102 | F4072: 1°D
A4073: Maio | B4073: 2023 | C4073: Infra e Hotelaria | D4073: Manutenção/Instalações | E4073: Setor | F4073: UTI NEO/8°D
A4074: Maio | B4074: 2023 | C4074: Infra e Hotelaria | D4074: Manutenção/Instalações | E4074: Setor | F4074: UTI NEO/8°D
A4075: Maio | B4075: 2023 | C4075: Infra e Hotelaria | D4075: Manutenção/Instalações | E4075: Agrupado na fonte — UCO/3ºC/102/802 | F4075: Não informado na fonte
A4076: Maio | B4076: 2023 | C4076: Infra e Hotelaria | D4076: Manutenção/Instalações | E4076: Agrupado na fonte — UCO/3ºC/102/802 | F4076: Não informado na fonte
A4077: Maio | B4077: 2023 | C4077: Infra e Hotelaria | D4077: Manutenção/Instalações | E4077: Agrupado na fonte — UCO/3ºC/102/802 | F4077: Não informado na fonte
A4078: Maio | B4078: 2023 | C4078: Infra e Hotelaria | D4078: Manutenção/Instalações | E4078: Agrupado na fonte — UCO/3ºC/102/802 | F4078: Não informado na fonte
A4079: Maio | B4079: 2023 | C4079: Infra e Hotelaria | D4079: Manutenção/Instalações | E4079: Agrupado na fonte — UCO/3ºC/102/802 | F4079: Não informado na fonte
A4080: Maio | B4080: 2023 | C4080: Infra e Hotelaria | D4080: Manutenção/Instalações | E4080: Agrupado na fonte — UCO/3ºC/102/802 | F4080: Não informado na fonte
A4081: Maio | B4081: 2023 | C4081: Infra e Hotelaria | D4081: Manutenção/Instalações | E4081: Agrupado na fonte — UCO/3ºC/102/802 | F4081: Não informado na fonte
A4082: Maio | B4082: 2023 | C4082: Infra e Hotelaria | D4082: Manutenção/Instalações | E4082: Setor | F4082: Não informado na fonte
A4083: Maio | B4083: 2023 | C4083: Infra e Hotelaria | D4083: Hotelaria/Rouparia | E4083: 802 | F4083: Não informado na fonte
A4084: Maio | B4084: 2023 | C4084: Infra e Hotelaria | D4084: Engenharia Clínica | E4084: Centro cirurgico | F4084: Não informado na fonte
A4085: Maio | B4085: 2023 | C4085: Sistemas de Informação | D4085: Sistemas/TI/Conectividade | E4085: Setor | F4085: UTI NEO/8°D
A4086: Maio | B4086: 2023 | C4086: Sistemas de Informação | D4086: Sistemas/TI/Conectividade | E4086: Setor | F4086: UTI NEO/8°D
A4087: Junho | B4087: 2023 | C4087: Infra e Hotelaria | D4087: Climatização | E4087: Quarto 305 | F4087: 3°D
A4088: Junho | B4088: 2023 | C4088: Infra e Hotelaria | D4088: Climatização | E4088: Setor | F4088: UTI NEO/8°D
A4089: Junho | B4089: 2023 | C4089: Infra e Hotelaria | D4089: Manutenção/Instalações | E4089: 102 | F4089: 1°D
A4090: Junho | B4090: 2023 | C4090: Infra e Hotelaria | D4090: Manutenção/Instalações | E4090: 110 | F4090: 1°D
A4091: Junho | B4091: 2023 | C4091: Infra e Hotelaria | D4091: Manutenção/Instalações | E4091: 305 | F4091: Não informado na fonte
A4092: Junho | B4092: 2023 | C4092: Infra e Hotelaria | D4092: Manutenção/Instalações | E4092: 322 | F4092: Não informado na fonte
A4093: Junho | B4093: 2023 | C4093: Infra e Hotelaria | D4093: Manutenção/Instalações | E4093: 334 | F4093: Não informado na fonte
A4094: Junho | B4094: 2023 | C4094: Infra e Hotelaria | D4094: Manutenção/Instalações | E4094: Setor | F4094: Neurologia
A4095: Junho | B4095: 2023 | C4095: Infra e Hotelaria | D4095: Manutenção/Instalações | E4095: Setor | F4095: 4°D
A4096: Junho | B4096: 2023 | C4096: Infra e Hotelaria | D4096: Manutenção/Instalações | E4096: 416 | F4096: Não informado na fonte
A4097: Junho | B4097: 2023 | C4097: Infra e Hotelaria | D4097: Manutenção/Instalações | E4097: 417 | F4097: Não informado na fonte
A4098: Junho | B4098: 2023 | C4098: Infra e Hotelaria | D4098: Manutenção/Instalações | E4098: 427 | F4098: Não informado na fonte
A4099: Junho | B4099: 2023 | C4099: Infra e Hotelaria | D4099: Manutenção/Instalações | E4099: Setor | F4099: Neurologia
A4100: Junho | B4100: 2023 | C4100: Infra e Hotelaria | D4100: Manutenção/Instalações | E4100: 802 | F4100: Não informado na fonte
A4101: Junho | B4101: 2023 | C4101: Infra e Hotelaria | D4101: Manutenção/Instalações | E4101: Quarto 810 | F4101: UTI NEO/8°D
A4102: Junho | B4102: 2023 | C4102: Infra e Hotelaria | D4102: Manutenção/Instalações | E4102: 811 | F4102: Não informado na fonte
A4103: Junho | B4103: 2023 | C4103: Infra e Hotelaria | D4103: Manutenção/Instalações | E4103: 811 | F4103: Não informado na fonte
A4104: Junho | B4104: 2023 | C4104: Infra e Hotelaria | D4104: Manutenção/Instalações | E4104: Quarto 104 | F4104: 1°D
A4105: Junho | B4105: 2023 | C4105: Infra e Hotelaria | D4105: Manutenção/Instalações | E4105: Quarto 414 | F4105: Não informado na fonte
A4106: Junho | B4106: 2023 | C4106: Infra e Hotelaria | D4106: Manutenção/Instalações | E4106: Uco | F4106: Não informado na fonte
A4107: Junho | B4107: 2023 | C4107: Infra e Hotelaria | D4107: Hotelaria/Rouparia | E4107: 103 | F4107: 1°D
A4108: Junho | B4108: 2023 | C4108: Infra e Hotelaria | D4108: Hotelaria/Rouparia | E4108: Setor | F4108: 4°D
A4109: Junho | B4109: 2023 | C4109: Infra e Hotelaria | D4109: Hotelaria/Rouparia | E4109: 705 | F4109: Não informado na fonte
A4110: Junho | B4110: 2023 | C4110: Infra e Hotelaria | D4110: Hotelaria/Rouparia | E4110: 812 | F4110: Não informado na fonte
A4111: Junho | B4111: 2023 | C4111: Infra e Hotelaria | D4111: Hotelaria/Rouparia | E4111: Quarto 312 | F4111: 3°D
A4112: Junho | B4112: 2023 | C4112: Infra e Hotelaria | D4112: Hotelaria/Rouparia | E4112: Enfermegem | F4112: Não informado na fonte
A4113: Junho | B4113: 2023 | C4113: Infra e Hotelaria | D4113: Higiene/Limpeza | E4113: Setor | F4113: 2°D
A4114: Junho | B4114: 2023 | C4114: Infra e Hotelaria | D4114: Higiene/Limpeza | E4114: Setor | F4114: UTI NEO/8°D
A4115: Junho | B4115: 2023 | C4115: Infra e Hotelaria | D4115: Higiene/Limpeza | E4115: Setor | F4115: UTI NEO/8°D
A4116: Junho | B4116: 2023 | C4116: Infra e Hotelaria | D4116: Higiene/Limpeza | E4116: 805 | F4116: Não informado na fonte
A4117: Junho | B4117: 2023 | C4117: Infra e Hotelaria | D4117: Higiene/Limpeza | E4117: Quarto 336 | F4117: UCO
A4118: Junho | B4118: 2023 | C4118: Infra e Hotelaria | D4118: Higiene/Limpeza | E4118: Quarto 110 | F4118: 1°D
A4119: Junho | B4119: 2023 | C4119: Infra e Hotelaria | D4119: Higiene/Limpeza | E4119: Setor | F4119: 2°D
A4120: Junho | B4120: 2023 | C4120: Infra e Hotelaria | D4120: Higiene/Limpeza | E4120: Setor | F4120: UCO
A4121: Junho | B4121: 2023 | C4121: Infra e Hotelaria | D4121: Higiene/Limpeza | E4121: Quarto 419 | F4121: Neurologia
A4122: Junho | B4122: 2023 | C4122: Infra e Hotelaria | D4122: Higiene/Limpeza | E4122: Quarto 332A | F4122: UCO
A4123: Junho | B4123: 2023 | C4123: Infra e Hotelaria | D4123: Higiene/Limpeza | E4123: Quarto 306 | F4123: 3°D
A4124: Junho | B4124: 2023 | C4124: Infra e Hotelaria | D4124: Higiene/Limpeza | E4124: Quarto 711 | F4124: Maternidade
A4125: Junho | B4125: 2023 | C4125: Infra e Hotelaria | D4125: Higiene/Limpeza | E4125: Quarto 210 | F4125: 2°D
A4126: Junho | B4126: 2023 | C4126: Infra e Hotelaria | D4126: Higiene/Limpeza | E4126: Quarto 812 | F4126: UTI NEO/8°D
A4127: Junho | B4127: 2023 | C4127: Infra e Hotelaria | D4127: Higiene/Limpeza | E4127: Quarto 317 | F4127: Semi 1
A4128: Junho | B4128: 2023 | C4128: Infra e Hotelaria | D4128: Higiene/Limpeza | E4128: Quarto 808 | F4128: UTI NEO/8°D
A4129: Junho | B4129: 2023 | C4129: Infra e Hotelaria | D4129: Higiene/Limpeza | E4129: Imagem | F4129: Não informado na fonte
A4130: Junho | B4130: 2023 | C4130: Infra e Hotelaria | D4130: Conforto/Barulho | E4130: 102 | F4130: 1°D
A4131: Junho | B4131: 2023 | C4131: Infra e Hotelaria | D4131: Conforto/Barulho | E4131: Setor | F4131: 3°D
A4132: Junho | B4132: 2023 | C4132: Infra e Hotelaria | D4132: Conforto/Barulho | E4132: Quarto 417 | F4132: Não informado na fonte
A4133: Junho | B4133: 2023 | C4133: Infra e Hotelaria | D4133: Conforto/Barulho | E4133: Quarto 418 | F4133: Não informado na fonte
A4134: Junho | B4134: 2023 | C4134: Infra e Hotelaria | D4134: Engenharia Clínica | E4134: Setor | F4134: 2°C
A4135: Junho | B4135: 2023 | C4135: Infra e Hotelaria | D4135: Engenharia Clínica | E4135: Setor | F4135: Neurologia
A4136: Junho | B4136: 2023 | C4136: Infra e Hotelaria | D4136: Engenharia Clínica | E4136: Setor | F4136: 4°D
A4137: Junho | B4137: 2023 | C4137: Infra e Hotelaria | D4137: Engenharia Clínica | E4137: Setor | F4137: Neurologia
A4138: Junho | B4138: 2023 | C4138: Infra e Hotelaria | D4138: Engenharia Clínica | E4138: Setor | F4138: Neurologia
A4139: Junho | B4139: 2023 | C4139: Infra e Hotelaria | D4139: Engenharia Clínica | E4139: Setor | F4139: UTI NEO/8°D
A4140: Junho | B4140: 2023 | C4140: Infra e Hotelaria | D4140: Engenharia Clínica | E4140: Setor | F4140: UTI NEO/8°D
A4141: Junho | B4141: 2023 | C4141: Infra e Hotelaria | D4141: Engenharia Clínica | E4141: Setor | F4141: UTI NEO/8°D
A4142: Junho | B4142: 2023 | C4142: Infra e Hotelaria | D4142: Engenharia Clínica | E4142: Equipe de Enf 4ºC | F4142: Não informado na fonte
... A4149: Junho | B4149: 2023 | C4149: Assistencial | D4149: Nutrição/Alimentação | E4149: Quarto 711 | F4149: Não informado na fonte
...

Sheet Planos de ação Huddle
A2: Ação | B2: Data_Registro | C2: Mês | D2: Ano | E2: Unidade | F2: Setor | G2: Categoria | H2: O_que_aconteceu | I2: Status | J2: Liderança | K2: Observação
A3: 1 | B3: 45518 | C3: Agosto | D3: 2024 | E3: HVC | F3: Operações | G3: Assistencial | H3: Avental - Qualidade | I3: Concluído | J3: Simone
A4: 2 | B4: 45518 | C4: Agosto | D4: 2024 | E4: HVC | F4: Laboratório | G4: Assistencial | H4: Hemoculturas - Atenção Global | I4: Concluído | J4: Não informado | K4: Risco de decisão clínica incorreta por erro de amostra ou comunicação.
A5: 3 | B5: 45518 | C5: Agosto | D5: 2024 | E5: HVC | F5: Operações / Enfermagem | G5: Sistemas de Informações | H5: Quality24 - Concierge: Adesão SLA | I5: Concluído | J5: Simone / Lilian | K5: Recorrência de baixa adesão, atraso e ausência de encerramento dos chamados.
A6: 4 | B6: 45518 | C6: Agosto | D6: 2024 | E6: HVC | F6: Operações | G6: Assistencial | H6: Nutrição - atraso dieta | I6: Concluído | J6: Simone | K6: Recorrência de atrasos e risco de dieta inadequada ao paciente.
A7: 5 | B7: 45518 | C7: Agosto | D7: 2024 | E7: HVC | F7: Operações | G7: Infra e Hotelaria | H7: Higiene CME | I7: Concluído | J7: Simone | K7: Risco de infecção e interrupção cirúrgica com recorrência e pendências abertas.
A8: 6 | B8: 45518 | C8: Agosto | D8: 2024 | E8: HVC | F8: Operações | G8: Infra e Hotelaria | H8: Higiene Noturno | I8: Concluído | J8: Simone | K8: Recorrência, pendências abertas e impacto na segurança e experiência.
A9: 7 | B9: 45518 | C9: Agosto | D9: 2024 | E9: HVC | F9: NSP | G9: Assistencial | H9: Falha na Identificação do Paciente PA | I9: Concluído | J9: Não informado | K9: Risco de evento grave, recorrência elevada e falhas em barreiras essenciais.
A10: 8 | B10: 45518 | C10: Agosto | D10: 2024 | E10: HVC | F10: NSP | G10: Assistencial | H10: Número de Punções alto/ FLEBITE | I10: Concluído | J10: Déborah | K10: Recorrência de flebite, perdas de acesso e extravasamentos.
A11: 9 | B11: 45518 | C11: Agosto | D11: 2024 | E11: HVC | F11: Enfermagem | G11: Assistencial | H11: Prótese com lateralidade errada | I11: Concluído | J11: Não informado | K11: Risco de evento grave, recorrência elevada e falhas em barreiras essenciais.
A12: 10 | B12: 45518 | C12: Agosto | D12: 2024 | E12: HVC | F12: Operações | G12: Infra e Hotelaria | H12: Elevador parou com paciente entubado | I12: Concluído | J12: Januário
A13: 11 | B13: 45518 | C13: Agosto | D13: 2024 | E13: HVC | F13: Operações / Enfermagem | G13: Sistemas de Informações | H13: Quality24 - Concierge: Uso da ferramenta | I13: Concluído | J13: Regiane | K13: Recorrência de baixa adesão, atraso e ausência de encerramento dos chamados.
A14: 12 | B14: 45519 | C14: Agosto | D14: 2024 | E14: HVC | F14: Enfermagem | G14: Sistemas de Informações | H14: Processo Toten PS | I14: Concluído | J14: Bianca
A15: 13 | B15: 45519 | C15: Agosto | D15: 2024 | E15: HVC | F15: Operações | G15: Fluxo do Paciente | H15: Mãe e filho descream da maternidade sem a enfermagem e sem assinar alta. recepção ligpou no posto de enfermagem, a qual pediu para paciente retornar. | I15: Concluído | J15: Rose, Milena e Milena | K15: Potencial de dano grave, exposição legal e recorrência em unidades distintas.
A16: 14 | B16: 45519 | C16: Agosto | D16: 2024 | E16: HVC | F16: Operações | G16: Infra e Hotelaria | H16: Higiene-piso liso no 1D | I16: Concluído | J16: Não informado | K16: Recorrência, pendências abertas e impacto na segurança e experiência.
A17: 15 | B17: 45519 | C17: Agosto | D17: 2024 | E17: HVC | F17: Operações | G17: Infra e Hotelaria | H17: Quebra pistola CME | I17: Concluído | J17: Januário | K17: Risco de infecção e interrupção cirúrgica com recorrência e pendências abertas.
A18: 16 | B18: 45520 | C18: Agosto | D18: 2024 | E18: HVC | F18: Assistencial | G18: Assistencial | H18: Alergia - aplicação de protocolo | I18: Concluído | J18: Deborah/ Patrícia Borges | K18: Potencial de dano grave e necessidade de barreira antes da exposição.
A19: 17 | B19: 45520 | C19: Agosto | D19: 2024 | E19: HVC | F19: Assistencial | G19: Assistencial Médico | H19: Atraso na solicitação de PICC | I19: Concluído | J19: Deborah/ Dra. Larissa | K19: Recorrência de flebite, perdas de acesso e extravasamentos.
A20: 18 | B20: 45520 | C20: Agosto | D20: 2024 | E20: HVC | F20: NSP | G20: Assistencial | H20: Reabordagem cirúrgica - gatilho (paciente 103/ dreno) | I20: Concluído | J20: Leticia/Catarina | K20: Risco cirúrgico, cancelamentos e falhas de lateralidade/material.
A21: 19 | B21: 45520 | C21: Agosto | D21: 2024 | E21: HVC | F21: Secretaria | G21: Fluxo do Paciente | H21: Processo Secretaria - novo fluxo alta ( paciente neuro internado sem acompanhante) | I21: Concluído | J21: Juliana/Lilian/ Ana Carol | K21: Recorrência e impacto em espera, ocupação e continuidade do cuidado.
A22: 20 | B22: 45520 | C22: Agosto | D22: 2024 | E22: HVC | F22: NSP | G22: Assistencial | H22: Lesão por pressão paciente centro cirúrgico | I22: Concluído | J22: Não informado | K22: Alta recorrência e potencial de prolongamento da internação.
A23: 21 | B23: 45523 | C23: Agosto | D23: 2024 | E23: HVC | F23: Operações / Enfermagem | G23: Infra e Hotelaria | H23: Controle de Acesso - maternidade | I23: Concluído | J23: Não informado | K23: Baixa frequência, porém alto potencial de dano, exposição e violação de área restrita.
A24: 22 | B24: 45523 | C24: Agosto | D24: 2024 | E24: HVC | F24: Operações | G24: Infra e Hotelaria | H24: Ar Condicionado parado - Hemodinâmica | I24: Concluído | J24: Januário | K24: Recorrência e impacto direto em áreas críticas e equipamentos.
A25: 23 | B25: 45523 | C25: Agosto | D25: 2024 | E25: HVC | F25: Operações | G25: Sistemas de Informações | H25: Nutrição atraso - Quality | I25: Concluído | J25: Regiane | K25: Recorrência de baixa adesão, atraso e ausência de encerramento dos chamados.
A26: 24 | B26: 45524 | C26: Agosto | D26: 2024 | E26: HVC | F26: PSI | G26: Assistencial | H26: Transição de criança PSI sem oxigênio | I26: Concluído | J26: Bianca
A27: 25 | B27: 45524 | C27: Agosto | D27: 2024 | E27: HVC | F27: Operações | G27: Infra e Hotelaria | H27: Higiene - estão ficando apenas 2 colaboradores - banheiro sem papel | I27: Concluído | J27: Simone | K27: Risco de queda da capacidade operacional em áreas críticas.
A28: 26 | B28: 45524 | C28: Agosto | D28: 2024 | E28: HVC | F28: Operações | G28: Infra e Hotelaria | H28: Higiene - sem colaborador na Hemodinâmica | I28: Concluído | J28: Simone | K28: Risco de queda da capacidade operacional em áreas críticas.
A29: 27 | B29: 45524 | C29: Agosto | D29: 2024 | E29: HVC | F29: Operações | G29: Infra e Hotelaria | H29: Ar condicionado no conforto médico do CC não funciona | I29: Concluído | J29: Simone | K29: Recorrência e impacto direto em áreas críticas e equipamentos.
A30: 28 | B30: 45524 | C30: Agosto | D30: 2024 | E30: HVC | F30: Operações | G30: Sistemas de Informações | H30: UTI Neo - ponto de atenção reconhecimento facil e necessidade de uma pessoa para suporte em relação ao sistema | I30: Concluído | J30: Simone e Arnaldo
A31: 29 | B31: 45524 | C31: Agosto | D31: 2024 | E31: HVC | F31: UTI Pediátrica | G31: Assistencial | H31: Troca bico mamadeira | I31: Concluído | J31: Juliana | K31: Recorrência de atrasos e risco de dieta inadequada ao paciente.
A32: 30 | B32: 45524 | C32: Agosto | D32: 2024 | E32: HVC | F32: Operações | G32: Infra e Hotelaria | H32: Reposição de água nas alas | I32: Concluído | J32: Simone
A33: 31 | B33: 45525 | C33: Agosto | D33: 2024 | E33: HVC | F33: Hemodinâmica | G33: Fluxo do Paciente | H33: Atraso na angioplastia porque médico não solicitou materiais | I33: Concluído | J33: Não informado | K33: Atrasos repetidos com cancelamentos, jejum prolongado e impacto na alta.
A34: 32 | B34: 45525 | C34: Agosto | D34: 2024 | E34: HVC | F34: Operações | G34: Infra e Hotelaria | H34: Falha de profissional de higiene na Hemodinâmica e CME | I34: Concluído | J34: Simone | K34: Risco de infecção e interrupção cirúrgica com recorrência e pendências abertas.
A35: 33 | B35: 45525 | C35: Agosto | D35: 2024 | E35: HVC | F35: Enfermagem | G35: Assistencial | H35: Clexane no 2D em horário errado | I35: Concluído | J35: Lilian | K35: Maior volume de interações priorizadas e potencial de dano evitável.
A36: 34 | B36: 45525 | C36: Agosto | D36: 2024 | E36: HVC | F36: Operações | G36: Sistemas de Informações | H36: Reconhecimento facial não funcionou a noite na UTI Neo - por questões sistêmicas, não é problema no cadastro. equipe precisa de suporte no período noturno | I36: Concluído | J36: Simone | K36: Falhas recorrentes com desvio de fluxo e aumento de filas.
A37: 35 | B37: 45526 | C37: Agosto | D37: 2024 | E37: HVC | F37: Centro Cirúrgico | G37: Assistencial | H37: Paciente fez procedimento anos atras e a chave solicitada não era compatível | I37: Concluído | J37: Não informado
A38: 36 | B38: 45526 | C38: Agosto | D38: 2024 | E38: HVC | F38: CME | G38: Infra e Hotelaria | H38: Autoclave quebrada | I38: Concluído | J38: Simone | K38: Risco de infecção e interrupção cirúrgica com recorrência e pendências abertas.
A39: 37 | B39: 45526 | C39: Agosto | D39: 2024 | E39: HVC | F39: Farmácia | G39: Assistencial | H39: Troca de medicação 6 andar (problema com prescrição) | I39: Concluído | J39: Não informado | K39: Maior volume de interações priorizadas e potencial de dano evitável.
A40: 38 | B40: 45526 | C40: Agosto | D40: 2024 | E40: HVC | F40: SCIH/CCIH | G40: Assistencial | H40: Paciente em quarto compartilhado (com necessidade de isolamento) Neta quem alertou equipe de enfermagem. | I40: Concluído | J40: Não informado | K40: Recorrência em precauções, isolamento e adesão às práticas de prevenção.
A41: 39 | B41: 45526 | C41: Agosto | D41: 2024 | E41: HVC | F41: Enfermagem Alas | G41: Infra e Hotelaria | H41: Quarto 334 com cano quebrado na madrugada | I41: Concluído | J41: Simone | K41: Alta recorrência e risco de queda, incêndio, dano patrimonial ou interrupção.
A42: 40 | B42: 45526 | C42: Agosto | D42: 2024 | E42: HVC | F42: UCO | G42: Assistencial Médico | H42: Ocorrência em 21/08 PICC | I42: Concluído | J42: Simone / Lilian | K42: Recorrência de flebite, perdas de acesso e extravasamentos.
A43: 41 | B43: 45526 | C43: Agosto | D43: 2024 | E43: HVC | F43: Operações | G43: Sistemas de Informações | H43: Materno Infantil - ponto de atenção reconhecimento facil e necessidade de uma pessoa para suporte em relação ao sistema. | I43: Concluído | J43: Simone
A44: 42 | B44: 45530 | C44: Agosto | D44: 2024 | E44: HVC | F44: Enfermagem | G44: Assistencial | H44: Cancelamento artrospatia de quadrial material sujo | I44: Concluído | J44: Não informado | K44: Risco cirúrgico, cancelamentos e falhas de lateralidade/material.
A45: 43 | B45: 45530 | C45: Agosto | D45: 2024 | E45: HVC | F45: Farmácia | G45: Infra e Hotelaria | H45: Problemas dispenário 4 andar, devido a chuva. | I45: Concluído | J45: Simone | K45: Alta recorrência e risco de queda, incêndio, dano patrimonial ou interrupção.
A46: 44 | B46: 45530 | C46: Agosto | D46: 2024 | E46: HVC | F46: Nutrição | G46: Infra e Hotelaria | H46: Lactário sem estoque - sem código NAN Supreme 2 Falta | I46: Concluído | J46: Juliana | K46: Recorrência de atrasos e risco de dieta inadequada ao paciente.
A47: 45 | B47: 45530 | C47: Agosto | D47: 2024 | E47: HVC | F47: UTI | G47: Assistencial | H47: UTI - reintubação domigo (PCR - foco deterioração) | I47: Concluído | J47: Não informado | K47: Potencial de óbito ou dano grave e necessidade de resposta tempo-dependente.
A48: 46 | B48: 45530 | C48: Agosto | D48: 2024 | E48: HVC | F48: Operações | G48: Sistemas de Informações | H48: Reconhecimento facial não funionou a noite na UTI Neo - por questões sistêmicas, não é problema no cadastro. equipe precisa de suporte no período noturno | I48: Concluído | J48: Simone | K48: Falhas recorrentes com desvio de fluxo e aumento de filas.
A49: 47 | B49: 45530 | C49: Agosto | D49: 2024 | E49: HVC | F49: UTI Adulto | G49: Assistencial | H49: Lesão por pressão 607 - paciente sem colchão adequado (Adilson verificar com Carol) | I49: Concluído | J49: Lilian / Carol | K49: Alta recorrência e potencial de prolongamento da internação.
A50: 48 | B50: 45531 | C50: Agosto | D50: 2024 | E50: HVC | F50: Farmácia | G50: Infra e Hotelaria | H50: Dispensário inoperante - placas queimadas | I50: Concluído | J50: Simone
A51: 49 | B51: 45531 | C51: Agosto | D51: 2024 | E51: HVC | F51: Farmácia | G51: Assistencial | H51: Seringa BD com cabelo e cortizonal sem pó dentro - notificado | I51: Concluído | J51: Simone
A52: 50 | B52: 45531 | C52: Agosto | D52: 2024 | E52: HVC | F52: Pronto Atendimento | G52: Assistencial | H52: Especialista - Flebite PA | I52: Concluído | J52: Não informado | K52: Recorrência de flebite, perdas de acesso e extravasamentos.
A53: 51 | B53: 45531 | C53: Agosto | D53: 2024 | E53: HVC | F53: Enfermagem Alas | G53: Fluxo do Paciente | H53: 334 A paciente robótica precisa vaga UTI e não tem disponível | I53: Concluído | J53: Não informado | K53: Recorrência e impacto em espera, ocupação e continuidade do cuidado.
A54: 52 | B54: 45531 | C54: Agosto | D54: 2024 | E54: HVC | F54: UTI | G54: Assistencial | H54: Paciente foi extubar e apresentou pneumotorax | I54: Concluído | J54: Não informado | K54: Potencial de óbito ou dano grave e necessidade de resposta tempo-dependente.
A55: 53 | B55: 45531 | C55: Agosto | D55: 2024 | E55: HVC | F55: Enfermagem Alas | G55: Fluxo do Paciente | H55: Atraso na colonoscopia - rever fluxo de acolhimento | I55: Concluído | J55: Não informado | K55: Atrasos repetidos com cancelamentos, jejum prolongado e impacto na alta.
A56: 54 | B56: 45532 | C56: Agosto | D56: 2024 | E56: HVC | F56: Farmácia | G56: Assistencial | H56: Dispensado agua para sondagem ao inves de soro - sem dano | I56: Concluído | J56: Déborah | K56: Maior volume de interações priorizadas e potencial de dano evitável.
A57: 55 | B57: 45532 | C57: Agosto | D57: 2024 | E57: HVC | F57: Nutrição | G57: Assistencial | H57: Dieta restrita para paciente | I57: Concluído | J57: Juliana | K57: Recorrência de atrasos e risco de dieta inadequada ao paciente.
A58: 56 | B58: 45532 | C58: Agosto | D58: 2024 | E58: HVC | F58: Pronto Atendimento | G58: Assistencial Médico | H58: Paciente do PA sem prescrição | I58: Concluído | J58: Não informado | K58: Maior volume de interações priorizadas e potencial de dano evitável.
A59: 57 | B59: 45532 | C59: Agosto | D59: 2024 | E59: HVC | F59: Centro Cirúrgico | G59: Assistencial | H59: Troca de material de OPME | I59: Concluído | J59: Patrícia / Simone | K59: Risco cirúrgico, cancelamentos e falhas de lateralidade/material.
A60: 58 | B60: 45532 | C60: Agosto | D60: 2024 | E60: HVC | F60: Operações | G60: Infra e Hotelaria | H60: Higiene CC - apenas 2 pessoas (uma passou mal) | I60: Concluído | J60: Simone | K60: Risco de queda da capacidade operacional em áreas críticas.
A61: 59 | B61: 45532 | C61: Agosto | D61: 2024 | E61: HVC | F61: Imagem / Radiologia | G61: Assistencial Médico | H61: RM leito 110 cancelada - paciente com nausea - sera avaliada sedação | I61: Concluído | J61: Jéssica | K61: Atrasos repetidos com cancelamentos, jejum prolongado e impacto na alta.
A62: 60 | B62: 45532 | C62: Agosto | D62: 2024 | E62: HVC | F62: UTI | G62: Sistemas de Informações | H62: Falso médico entrando em contato com pacientes | I62: Concluído | J62: Carol | K62: Evento de baixa frequência, mas alto impacto financeiro, reputacional e de privacidade.
A63: 61 | B63: 45533 | C63: Agosto | D63: 2024 | E63: HVC | F63: Farmácia | G63: Assistencial | H63: Dispensação errada - dexametazona - foi escrito decadron | I63: Concluído | J63: Patrícia / Simone | K63: Maior volume de interações priorizadas e potencial de dano evitável.
... A65: 63 | B65: 45533 | C65: Agosto | D65: 2024 | E65: HVC | F65: Centro Cirúrgico | G65: Assistencial | H65: Quase queda paciente cirurgia robótica | I65: Concluído | J65: Não informado | K65: Recorrência e registro de eventos com dano.
A66: 64 | B66: 45533 | C66: Agosto | D66: 2024 | E66: HVC | F66: Imagem / Radiologia | G66: Assistencial | H66: Dificuldade no acesso em paciente 319 B - paciente de reinternação | I66: Concluído | J66: Não informado
A67: 65 | B67: 45533 | C67: Agosto | D67: 2024 | E67: HVC | F67: Imagem / Radiologia | G67: Infra e Hotelaria | H67: Acesso de pessoa estranha na Imagem - disse que seria benchmarking | I67: Concluído | J67: Simone | K67: Baixa frequência, porém alto potencial de dano, exposição e violação de área restrita.
A68: 66 | B68: 45534 | C68: Agosto | D68: 2024 | E68: HVC | F68: Nutrição | G68: Assistencial | H68: Rever fluxo de refeição para acompanhante | I68: Concluído | J68: Não informado | K68: Recorrência de atrasos e risco de dieta inadequada ao paciente.
A69: 67 | B69: 45534 | C69: Agosto | D69: 2024 | E69: HVC | F69: Imagem / Radiologia | G69: Assistencial Médico | H69: Pico de atraso na imagem ontem - atraso raio x | I69: Concluído | J69: Não informado | K69: Atrasos repetidos com cancelamentos, jejum prolongado e impacto na alta.
A70: 68 | B70: 45537 | C70: Setembro | D70: 2024 | E70: HVC | F70: Farmácia | G70: Assistencial | H70: Troca de etiqueta na Farmácia - identificado pela enfermagem | I70: Concluído | J70: Não informado | K70: Maior volume de interações priorizadas e potencial de dano evitável.
A71: 69 | B71: 45537 | C71: Setembro | D71: 2024 | E71: HVC | F71: SCIH/CCIH | G71: Assistencial | H71: Notificar meningites e maculosa | I71: Concluído | J71: Não informado | K71: Recorrência em precauções, isolamento e adesão às práticas de prevenção.
A72: 70 | B72: 45537 | C72: Setembro | D72: 2024 | E72: HVC | F72: Imagem / Radiologia | G72: Assistencial Médico | H72: Rever fluxo exame imagem - atraso | I72: Concluído | J72: Não informado | K72: Atrasos repetidos com cancelamentos, jejum prolongado e impacto na alta.
A73: 71 | B73: 45538 | C73: Setembro | D73: 2024 | E73: HVC | F73: Não informado | G73: Infra e Hotelaria | H73: Falta travesseiro oitavo andar | I73: Concluído | J73: Não informado | K73: Recorrência, pendências abertas e impacto na segurança e experiência.
A74: 72 | B74: 45538 | C74: Setembro | D74: 2024 | E74: HVC | F74: Farmácia | G74: Assistencial | H74: Dispensação Defenidrin sem diluição na pediatria - criança teve reação | I74: Concluído | J74: Não informado | K74: Maior volume de interações priorizadas e potencial de dano evitável.
A75: 73 | B75: 45538 | C75: Setembro | D75: 2024 | E75: HVC | F75: NSP | G75: Assistencial | H75: Transferência de paciente do PSA>UTI - sem passagem de plantão | I75: Concluído | J75: Não informado | K75: Risco de perda de informação clínica em transferências e resultados críticos.
A76: 74 | B76: 45538 | C76: Setembro | D76: 2024 | E76: HVC | F76: Gestão de Leitos | G76: Fluxo do Paciente | H76: PS solicitou internação em SEMI, mas paciente foi encaminhada para 8 Andar | I76: Concluído | J76: Não informado | K76: Recorrência e impacto em espera, ocupação e continuidade do cuidado.
A77: 75 | B77: 45538 | C77: Setembro | D77: 2024 | E77: HVC | F77: Farmácia | G77: Assistencial | H77: Entrega de psico deixada balcão semi | I77: Concluído | J77: Não informado | K77: Maior volume de interações priorizadas e potencial de dano evitável.
A78: 76 | B78: 45538 | C78: Setembro | D78: 2024 | E78: HVC | F78: Farmácia | G78: Assistencial | H78: Preparo amiodarona com equipo errado | I78: Concluído | J78: Não informado | K78: Maior volume de interações priorizadas e potencial de dano evitável.
... A81: 79 | B81: 45538 | C81: Setembro | D81: 2024 | E81: HVC | F81: Especialistas | G81: Assistencial Médico | H81: Alinhar comunicação quanto ao PICC junto equipe médica (caso paciente com traqueo) | I81: Concluído | J81: Não informado | K81: Recorrência de flebite, perdas de acesso e extravasamentos.
A82: 80 | B82: 45539 | C82: Setembro | D82: 2024 | E82: HVC | F82: Centro Cirúrgico | G82: Infra e Hotelaria | H82: Rever proteção contra mosquito na sala cirúrgico | I82: Concluído | J82: Januário
A83: 81 | B83: 45539 | C83: Setembro | D83: 2024 | E83: HVC | F83: CAF | G83: Assistencial | H83: Erro de fracionamento identificado na farmácia. Notificar Near Miss | I83: Concluído | J83: Paloma | K83: Maior volume de interações priorizadas e potencial de dano evitável.
A84: 82 | B84: 45539 | C84: Setembro | D84: 2024 | E84: HVC | F84: Imagem / Radiologia | G84: Assistencial Médico | H84: Imagem - criança da UTI com tomografia agendada com sedação, crianças sem jejum. Notificar cancelamento de exame/reagendado | I84: Concluído | J84: Jessica/Milena | K84: Atrasos repetidos com cancelamentos, jejum prolongado e impacto na alta.
A85: 83 | B85: 45539 | C85: Setembro | D85: 2024 | E85: HVC | F85: Semi | G85: Fluxo do Paciente | H85: Internação para psiquiatria com alta após 1 hora de internação | I85: Concluído | J85: Carolina | K85: Recorrência e impacto em espera, ocupação e continuidade do cuidado.
A86: 84 | B86: 45539 | C86: Setembro | D86: 2024 | E86: HVC | F86: Imagem / Radiologia | G86: Assistencial Médico | H86: Atraso de 1 hora. 01 aparelho com drenagem e outro com demanda eletiva, avc, pacientes internados. | I86: Concluído | J86: Jéssica
A87: 85 | B87: 45539 | C87: Setembro | D87: 2024 | E87: HVC | F87: Imagem / Radiologia | G87: Assistencial Médico | H87: Pendencia de doppler pois necessita radiologista | I87: Concluído | J87: Jéssica
A88: 86 | B88: 45539 | C88: Setembro | D88: 2024 | E88: HVC | F88: Imagem / Radiologia | G88: Assistencial Médico | H88: 321-B e 403 verificar porque solicitação de tomo após meia noite | I88: Concluído | J88: Dra Larissa
A89: 87 | B89: 45540 | C89: Setembro | D89: 2024 | E89: HVC | F89: Nutrição | G89: Sistemas de Informações | H89: Quality - ponto de atenção Nutrição | I89: Concluído | J89: Juliana | K89: Recorrência de baixa adesão, atraso e ausência de encerramento dos chamados.
A90: 88 | B90: 45540 | C90: Setembro | D90: 2024 | E90: HVC | F90: TI | G90: Sistemas de Informações | H90: We now sistema tasy | I90: Concluído | J90: Não informado | K90: Impacto em continuidade, registro clínico e produtividade.
A91: 89 | B91: 45540 | C91: Setembro | D91: 2024 | E91: HVC | F91: Semi | G91: Assistencial Médico | H91: Exame tomografia cancelado - falha comunicação | I91: Concluído | J91: Não informado | K91: Atrasos repetidos com cancelamentos, jejum prolongado e impacto na alta.
A92: 90 | B92: 45540 | C92: Setembro | D92: 2024 | E92: HVC | F92: Higiene | G92: Infra e Hotelaria | H92: Higienização falha na terminal da UTI pediátrica | I92: Concluído | J92: Não informado
A93: 91 | B93: 45541 | C93: Setembro | D93: 2024 | E93: HVC | F93: NAE | G93: Assistencial | H93: Lesão pressão na uco | I93: Concluído | J93: Adilson | K93: Alta recorrência e potencial de prolongamento da internação.
A94: 92 | B94: 45541 | C94: Setembro | D94: 2024 | E94: HVC | F94: NSP | G94: Assistencial | H94: Falha de comunicação no resultado crítico | I94: Concluído | J94: Não informado | K94: Risco de perda de informação clínica em transferências e resultados críticos.
A95: 93 | B95: 45541 | C95: Setembro | D95: 2024 | E95: HVC | F95: NSP | G95: Assistencial | H95: Queda no 307 | I95: Concluído | J95: Não informado | K95: Recorrência e registro de eventos com dano.
A96: 94 | B96: 45541 | C96: Setembro | D96: 2024 | E96: HVC | F96: Gestão de Leitos | G96: Assistencial | H96: Passagem de sonda enteral sem sucesso leito 603 (paciente com reconstrução facial) - fazer com endoscopia | I96: Concluído | J96: Não informado
A97: 95 | B97: 45544 | C97: Setembro | D97: 2024 | E97: HVC | F97: Farmácia | G97: Assistencial | H97: Erro fracionamento - paracetamol | I97: Concluído | J97: Não informado | K97: Maior volume de interações priorizadas e potencial de dano evitável.
A98: 96 | B98: 45544 | C98: Setembro | D98: 2024 | E98: HVC | F98: NSP | G98: Assistencial | H98: Falha identificação e transição cuidado paciente | I98: Concluído | J98: Não informado | K98: Risco de evento grave, recorrência elevada e falhas em barreiras essenciais.
A99: 97 | B99: 45544 | C99: Setembro | D99: 2024 | E99: HVC | F99: NSP | G99: Assistencial | H99: Falha comunicação resultado crítico do laboratorio | I99: Concluído | J99: Não informado | K99: Risco de decisão clínica incorreta por erro de amostra ou comunicação.
A100: 98 | B100: 45544 | C100: Setembro | D100: 2024 | E100: HVC | F100: Farmácia | G100: Assistencial | H100: Troca rótulo soro de paciente | I100: Concluído | J100: Não informado | K100: Risco de evento grave, recorrência elevada e falhas em barreiras essenciais.
A101: 99 | B101: 45544 | C101: Setembro | D101: 2024 | E101: HVC | F101: Nutrição | G101: Infra e Hotelaria | H101: Reclamação de cardápio por acompanhante materno | I101: Concluído | J101: Não informado | K101: Recorrência de atrasos e risco de dieta inadequada ao paciente.
A102: 100 | B102: 45545 | C102: Setembro | D102: 2024 | E102: HVC | F102: NSP | G102: Assistencial | H102: Paciente holandesa com ano de nascimento errado - CC | I102: Concluído | J102: Não informado | K102: Risco de evento grave, recorrência elevada e falhas em barreiras essenciais.
A103: 101 | B103: 45545 | C103: Setembro | D103: 2024 | E103: HVC | F103: NSP | G103: Assistencial | H103: Queda internação 2D - idoso foi colocar calça sozinho | I103: Concluído | J103: Não informado | K103: Recorrência e registro de eventos com dano.
A104: 102 | B104: 45546 | C104: Setembro | D104: 2024 | E104: HVC | F104: Recepção | G104: Assistencial | H104: CC - processo de cadastro na recepção - ano de nascimento errado (paciente CC) | I104: Concluído | J104: Não informado | K104: Risco de evento grave, recorrência elevada e falhas em barreiras essenciais.
...

Sheet Pacientes Watcher
A1: Prontuário | B1: N° Atendimento | C1: Ano | D1: Paciente | E1: Nascimento | F1: Data de entrada | G1: Data Alta/óbito | H1: Setor inicial | I1: Setor final | J1: Última evolução | K1: Responsável | L1: Motivo | M1: Desfecho final | N1: Histórico de setores | O1: Observações de qualidade
A2: 509988 | B2: 6269543 | C2: 2024 | D2: RMZC | E2: 0 | F2: 45495 | G2: 45499 | H2: 3B | I2: 3B | J2: Estável | K2: Oncologia | L2: Remoção/Transporte | M2: Alta | N2: 3B | O2: Data de nascimento válida não disponível
A3: 347729 | B3: 6345785 | C3: 2024 | D3: PMMR | E3: 0 | F3: 45495 | G3: 45498 | H3: UTIA | I3: 1D | J3: Crítico | K3: Oncologia | L3: Reabordagem | M3: Óbito | N3: UTIA → 102 → 1D | O3: Data de nascimento válida não disponível
A4: 830835 | B4: 6355731 | C4: 2024 | D4: LQP | E4: 0 | F4: 45495 | G4: 45518 | H4: 1D | I4: 1D | J4: Estável | K4: Oncologia | L4: Remoção/Transporte | M4: Alta | N4: 1D | O4: Data de nascimento válida não disponível
A5: 139781 | B5: 6361323 | C5: 2024 | D5: JAB | E5: 0 | F5: 45496 | G5: 45499 | H5: 330B | I5: 330B | J5: Crítico | K5: Oncologia | L5: Deteriorização Clinica | M5: Óbito | N5: 330B | O5: Data de nascimento válida não disponível
A6: 14784 | B6: 6372412 | C6: 2024 | D6: IMFS | E6: 0 | F6: 45495 | G6: 45496 | H6: 109 | I6: 109 | J6: Crítico | K6: Oncologia | L6: Pós queixa crítica | M6: Alta | N6: 109 | O6: Data de nascimento válida não disponível
A7: 844241 | B7: 6373599 | C7: 2024 | D7: JTB | E7: 0 | F7: 45495 | G7: 45496 | H7: 713 | I7: 713 | J7: Estável | K7: Maternidade | L7: Pós queixa crítica | M7: Alta | N7: 713 | O7: Data de nascimento válida não disponível
A8: 587210 | B8: 6376082 | C8: 2024 | D8: JVML | E8: 0 | F8: 45495 | G8: 45496 | H8: 715 | I8: 715 | J8: Estável | K8: Maternidade | L8: Pós queixa crítica | M8: Alta | N8: 715 | O8: Data de nascimento válida não disponível
A9: 75196 | B9: 6376601 | C9: 2024 | D9: AB | E9: 0 | F9: 45495 | G9: 45496 | H9: 2C | I9: 2C | J9: Crítico | K9: Clínica Médica | L9: Deteriorização | M9: Óbito | N9: 2C | O9: Data de nascimento válida não disponível
A10: 6376730 | B10: 6376730 | C10: 2024 | D10: ALVL | E10: 0 | F10: 45495 | G10: 45511 | H10: 3D | I10: 3D | J10: Crítico | K10: Clínica Médica | L10: Deteriorização | M10: Alta | N10: 3D | O10: Data de nascimento válida não disponível
A11: #VALUE! | B11: 0 | C11: 2024 | D11: IMFS | E11: 0 | F11: 45495 | G11: 45498 | H11: 109 | I11: 109 | J11: Crítico | K11: Oncologia | L11: Pós queixa crítica | M11: Óbito | N11: 109 | O11: Data de nascimento válida não disponível | Prontuário não informado
A12: 6369902 | B12: 6369902 | C12: 2024 | D12: ATVN | E12: 0 | F12: 45496 | G12: 45509 | H12: 809 | I12: 809 | J12: Crítico | K12: Clínica Médica | L12: Pós queixa crítica | M12: Alta | N12: 809 | O12: Data de nascimento válida não disponível
A13: 385376 | B13: 6376582 | C13: 2024 | D13: V.M.Q | E13: 0 | F13: 45495 | G13: 45498 | H13: 426 | I13: 426 | J13: Estável | K13: Pediatria | L13: Pós evento adverso | S/Reação | M13: Alta | N13: 426 | O13: Data de nascimento válida não disponível
A14: 376178 | B14: 888712 | C14: 2024 | D14: KPPS | E14: 0 | F14: 45496 | G14: 45498 | H14: 425 | I14: 425 | J14: Estável | K14: Pediatria | L14: Pós queixa crítica | S/demandas | M14: Alta | N14: 425 | O14: Data de nascimento válida não disponível
A15: 53644 | B15: 890313 | C15: 2024 | D15: RBA | E15: 0 | F15: 45496 | G15: 45498 | H15: 707 | I15: 707 | J15: Estável | K15: Maternidade | L15: Pós queixa crítica | Resolvido | M15: Alta | N15: 707 | O15: Data de nascimento válida não disponível
A16: 475613 | B16: 6370180 | C16: 2024 | D16: SBF | E16: 27948 | F16: 45492 | G16: 45499 | H16: 216A | I16: 216A | J16: Estável | K16: Ortopedia/trauma | L16: Aguarda cirurgia | M16: Alta | N16: 216A
A17: 105488 | B17: 6370757 | C17: 2024 | D17: CV | E17: 17818 | F17: 45492 | G17: 45499 | H17: 331B | I17: 331B | J17: Estável | K17: Neurocir | L17: Risco de conflito | M17: Alta | N17: 331B
A18: 666136 | B18: 6378502 | C18: 2024 | D18: DVVL | E18: 29762 | F18: 45496 | G18: 45499 | H18: 334A | I18: 109 | J18: Estável | K18: Hematologia | L18: Quimioterapia | M18: Alta | N18: 334A → 109 | O18: Mesmas iniciais e nascimento associados a prontuários distintos: 6378502, 666136
A19: 334003 | B19: 6379812 | C19: 2024 | D19: FABLR | E19: 0 | F19: 45498 | G19: 45499 | I19: 0 | K19: 2º D | L19: Pós evento adverso | M19: Alta | N19: 0 | O19: Data de nascimento válida não disponível
A20: 794588 | B20: 794588 | C20: 2024 | D20: LRC | E20: 40066 | F20: 45489 | G20: 45555 | H20: 435 | I20: 435/430/425 | J20: Estável | K20: UTI PED/Ped | L20: Risco de conflito | M20: Alta | N20: 435 → 435/430 → 435/430/426 → 435/430/425A → 435/430/425
A21: 405850 | B21: 405850 | C21: 2024 | D21: ML | E21: 0 | F21: 45502 | G21: 45509 | H21: 8D | I21: 8D | J21: Estável | K21: Hematologia | L21: Aguarda Liberação Convênio | M21: Alta | N21: 8D | O21: Data de nascimento válida não disponível
A22: 57543 | B22: 57543 | C22: 2024 | D22: AFAS | E22: 43577 | F22: 45498 | G22: 45510 | H22: 429 | I22: 429 | J22: Estável | K22: UTI PED | L22: Pós queixa crítica | M22: Alta | N22: 429
A23: 603315 | B23: 603315 | C23: 2024 | D23: MBFB | E23: 32029 | F23: 45501 | G23: 45503 | H23: 708 | I23: 708 | J23: Estável | K23: Maternidade | L23: Risco de conflito | M23: Alta | N23: 708
A24: 666136 | B24: 666136 | C24: 2024 | D24: DVVL | E24: 29762 | F24: 45502 | G24: 45523 | H24: 104 | I24: 104 | J24: Estável | K24: Hematologia | L24: Quimioterapia | M24: Alta | N24: 104 | O24: Mesmas iniciais e nascimento associados a prontuários distintos: 6378502, 666136
A25: 891054 | B25: 891054 | C25: 2024 | D25: JMS | E25: 45201 | F25: 45501 | G25: 45504 | H25: 428 | I25: 428 | J25: Estável | K25: PED | L25: Risco de conflito | M25: Alta | N25: 428
A26: 891061 | B26: 891061 | C26: 2024 | D26: MAZG | E26: 0 | F26: 45502 | G26: 45509 | H26: 1D | I26: 1D | J26: Estável | K26: Clínica Médica | L26: Paracentese | M26: Alta | N26: 1D | O26: Data de nascimento válida não disponível
A27: 393544 | B27: 393544 | C27: 2024 | D27: MB | E27: 33190 | F27: 45504 | G27: 45505 | H27: 711 | I27: 711 | J27: Estável | K27: Maternidade | L27: Pós queixa crítica | M27: Alta | N27: 711
A28: 514378 | B28: 514378 | C28: 2024 | D28: ACV | E28: 35228 | F28: 45505 | G28: 45510 | H28: 903 | I28: 903 | J28: Estável | K28: OBS/Maternidade | L28: Risco de conflito | M28: Alta | N28: 903 → 714
A29: 557614 | B29: 557614 | C29: 2024 | D29: MASBB | E29: 31825 | F29: 45505 | G29: 45509 | H29: 713 | I29: 713 | J29: Estável | K29: Maternidade | L29: Risco de conflito | M29: Alta | N29: 713
A30: 108414 | B30: 108414 | C30: 2024 | D30: EFAL | E30: 15793 | F30: 45503 | G30: 45518 | H30: 416 | I30: 416 | J30: Estável | K30: Neurologia | L30: Reabordagem | M30: Alta | N30: 416 → 308 | O30: Mesmas iniciais e nascimento associados a prontuários distintos: 108414, 6423875
A31: 42080 | B31: 42080 | C31: 2024 | D31: JRS | E31: 19863 | F31: 45504 | G31: 45518 | H31: 802 | I31: 802 | J31: Estável | K31: Clínica Médica | L31: Reabordagem | M31: Alta | N31: 802 | O31: Mesmas iniciais e nascimento associados a prontuários distintos: 42080, 6541529 | Prontuário associado a identificações de paciente distintas
A32: 780060 | B32: 780060 | C32: 2024 | D32: BBS | E32: 44780 | F32: 45500 | G32: 45510 | H32: 428A | I32: 428A | J32: Estável | K32: Pediatria | L32: Pós queixa crítica | M32: Alta | N32: 428A
A33: 363106 | B33: 6376908 | C33: 2024 | D33: GLV | E33: 30528 | F33: 45496 | G33: 45516 | H33: 806 | I33: 806 | J33: Crítico | K33: Clínica Médica | L33: Pós queixa crítica | M33: Alta | N33: 806
A34: 394310 | B34: 394310 | C34: 2024 | D34: PAP | E34: 24473 | F34: 45506 | G34: 45518 | H34: 224 | I34: 224 | J34: Estável | K34: Cirurgia | L34: Risco de conflito | M34: Alta | N34: 224
A35: 512097 | B35: 512097 | C35: 2024 | D35: RCCN | E35: 24952 | F35: 45507 | G35: 45524 | H35: 801 | I35: 801 | J35: Estável | K35: Infecto/Ortop | L35: Pós queixa crítica | M35: Alta | N35: 801
A36: 799617 | B36: 799617 | C36: 2024 | D36: TSA | E36: 33252 | F36: 45504 | G36: 45539 | H36: 108 | I36: 302 | J36: Paliativo | K36: Oncologia | L36: Risco de conflito | M36: Óbito | N36: 108 → 310 → 302
A37: 12466 | B37: 12466 | C37: 2024 | D37: LGG | E37: 34056 | F37: 45512 | G37: 45539 | H37: 111 | I37: 111 | J37: Estável | K37: Hematologia | L37: TMO | M37: Alta | N37: 111
A38: 322003 | B38: 322003 | C38: 2024 | D38: DAMG | E38: 24696 | F38: 45512 | G38: 45530 | H38: 106 | I38: 106 | J38: Estável | K38: Hematologia | L38: TMO | M38: Alta | N38: 106
A39: 889643 | B39: 889643 | C39: 2024 | D39: DFM | E39: 45493 | F39: 45493 | G39: 45524 | H39: 503 | I39: 503 | J39: Estável | K39: UTI NEO | L39: Risco de conflito | M39: Alta | N39: 503 → 503/707
A40: 639002 | B40: 639002 | C40: 2024 | D40: VRBM | E40: 30882 | F40: 45512 | G40: 45519 | H40: 709 | I40: 709 | J40: Estável | K40: Maternidade | L40: Risco de conflito | M40: Alta | N40: 709 → 709/343
A41: 433205 | B41: 433205 | C41: 2024 | D41: IBC | E41: 21001 | F41: 45516 | G41: 45552 | H41: 101 | I41: 101 | J41: Estável | K41: Hematologia | L41: TMO | M41: Alta | N41: 101
A42: 6419009 | B42: 6419009 | C42: 2024 | D42: WRN | E42: 18570 | F42: 45516 | G42: 45517 | H42: 410 | I42: 410 | J42: Estável | K42: Clínica Médica | L42: Risco de conflito | M42: Alta | N42: 410 | O42: Mesmas iniciais e nascimento associados a prontuários distintos: 607649, 6419009
A43: 669926 | B43: 669926 | C43: 2024 | D43: HGO | E43: 43013 | F43: 45512 | G43: 45518 | H43: 433 | I43: 433 | J43: Estável | K43: UTI PED | L43: Risco de conflito | M43: Alta | N43: 433
A44: 526529 | B44: 526529 | C44: 2024 | D44: LLN | E44: 42738 | F44: 45517 | G44: 45520 | H44: 423A | I44: 423A | J44: Estável | K44: Pediatria | L44: Risco de conflito | M44: Alta | N44: 423A → 423A/431
A45: 607649 | B45: 607649 | C45: 2024 | D45: WRN | E45: 18570 | F45: 45516 | G45: 45524 | H45: 410 | I45: 410 | J45: Estável | K45: Clínica Médica | L45: Risco de conflito | M45: Alta | N45: 410 | O45: Mesmas iniciais e nascimento associados a prontuários distintos: 607649, 6419009
A46: 847233 | B46: 847233 | C46: 2024 | D46: IMLS | E46: 30498 | F46: 45514 | G46: 45523 | H46: 711 | I46: 711 | J46: Estável | K46: Maternidade | L46: Reabordagem | M46: Alta | N46: 711 → 711/321
A47: 6423875 | B47: 6423875 | C47: 2024 | D47: EFAL | E47: 15793 | F47: 45518 | G47: 45538 | H47: 316 | I47: 812 | J47: Estável | K47: Neurologia | L47: Reabordagem | M47: Alta | N47: 316 → 812 | O47: Mesmas iniciais e nascimento associados a prontuários distintos: 108414, 6423875
A48: 670678 | B48: 670678 | C48: 2024 | D48: RVS | E48: 22196 | F48: 45519 | G48: 45523 | H48: 609 | I48: 609 | J48: Crítico | K48: UTI A | L48: Reabordagem | M48: Óbito | N48: 609 | O48: Mesmas iniciais e nascimento associados a prontuários distintos: 6423102, 670678
A49: 863757 | B49: 863757 | C49: 2024 | D49: ARC | E49: 0 | F49: 45519 | G49: 45534 | H49: 425 | I49: 425 | J49: Estável | K49: Pediatria | L49: Risco de conflito | M49: Alta | N49: 425 → 425/435 | O49: Data de nascimento não pôde ser interpretada: 26/06/20218 | Data de nascimento válida não disponível
A50: 6423102 | B50: 6423102 | C50: 2024 | D50: RVS | E50: 22196 | F50: 45519 | G50: 45524 | H50: 609 | I50: 609 | J50: Crítico | K50: UTI A | L50: Reabordagem | M50: Óbito | N50: 609 | O50: Mesmas iniciais e nascimento associados a prontuários distintos: 6423102, 670678
A51: 670678 | B51: 6426102 | C51: 2024 | D51: ARC | E51: 0 | F51: 45519 | G51: 45524 | H51: 425/435 | I51: 425/435 | J51: Estável | K51: Pediatria | L51: Risco de conflito | M51: Óbito | N51: 425/435 | O51: Data de nascimento não pôde ser interpretada: 26/06/20218 | Data de nascimento válida não disponível
A52: 893715 | B52: 893715 | C52: 2024 | D52: ARSP | E52: 45517 | F52: 45517 | G52: 45527 | H52: 505 | I52: 505 | J52: Estável | K52: UTI NEO | L52: Aguarda cirurgia | M52: Estabilização | N52: 505
A53: 142274 | B53: 142274 | C53: 2024 | D53: WC | E53: 12544 | F53: 45521 | G53: 45538 | H53: 308 | I53: 308 | J53: Estável | K53: Clínica médica | L53: Reabordagem | M53: Óbito | N53: 308
A54: 13544 | B54: 13544 | C54: 2024 | D54: ALS | E54: 16669 | F54: 45524 | G54: 45558 | H54: 307 | I54: 331 | J54: Estável | K54: Nefrologia | L54: Pós evento adverso | M54: Alta | N54: 307 → 318 → 331
A55: 486241 | B55: 486241 | C55: 2024 | D55: RHE | E55: 31697 | F55: 45526 | G55: 45531 | H55: 207 | I55: 207 | J55: Estável | K55: Radiologia | L55: Pós queixa crítica | M55: Alta | N55: 207
A56: 413557 | B56: 413557 | C56: 2024 | D56: RCB | E56: 21945 | F56: 45531 | G56: 45555 | H56: 110 | I56: 110 | J56: Estável | K56: Oncologia | L56: Quimioterapia | M56: Alta | N56: 110
A57: 615676 | B57: 615676 | C57: 2024 | D57: BNLS | E57: 34765 | F57: 45527 | G57: 45534 | H57: 703 | I57: 703 | J57: Estável | K57: Mater/UTI Neo | L57: Pós queixa crítica | M57: Alta | N57: 703
A58: 894176 | B58: 894176 | C58: 2024 | D58: JRC | E58: 22197 | F58: 45519 | G58: 45552 | H58: 334A | I58: 334A | J58: Crítico | K58: Oncologia/Cirurgia | L58: Pós evento adverso | M58: Alta | N58: 334A
A59: 895462 | B59: 895462 | C59: 2024 | D59: DAMO | E59: 29403 | F59: 45530 | G59: 45534 | H59: 704 | I59: 704 | J59: Estável | K59: Maternidade | L59: Risco de conflito | M59: Alta | N59: 704
A60: 138951 | B60: 138951 | C60: 2024 | D60: MM | E60: 12987 | F60: 45564 | G60: 45552 | H60: 404 | I60: 404 | J60: Estável | K60: Catarina/Simone | L60: Risco de conflito | M60: Alta | N60: 404 | O60: Data de entrada posterior à data do Huddle | Prontuário não informado
A61: 896654 | B61: 896654 | C61: 2024 | D61: GSS | E61: 43452 | F61: 45533 | G61: 45537 | H61: 430 | I61: 430 | J61: Estável | K61: UTI PED | L61: Risco de conflito | M61: Alta | N61: 430
A62: 567117 | B62: 567117 | C62: 2024 | D62: SMM | E62: 45308 | F62: 45537 | G62: 45540 | H62: 332B | I62: 332B | J62: Estável | K62: Catarina | L62: Pós evento adverso | M62: Alta | N62: 332B
A63: 6464037 | B63: 6464037 | C63: 2024 | D63: JLOS | E63: 17659 | F63: 45538 | G63: 45551 | H63: 604 | I63: 604 / 406 | J63: Estável | K63: Carolina | L63: Reabordagem | M63: Alta | N63: 604 → 604 / 406 | O63: Data de nascimento válida não disponível
A64: 176466 | B64: 176466 | C64: 2024 | D64: MCS | E64: 19683 | F64: 45528 | G64: 45572 | H64: 307 | I64: 303 | J64: Estável | K64: Catarina | L64: Pós evento adverso | M64: Óbito | N64: 307 → 303
A65: 793173 | B65: 793173 | C65: 2024 | D65: GRS | E65: 43007 | F65: 45540 | G65: 45544 | H65: 429 | I65: 429 | J65: Estável | K65: Milena | L65: Risco de conflito | M65: Alta | N65: 429
A66: 770693 | B66: 770693 | C66: 2024 | D66: MSG | E66: 43815 | F66: 45543 | G66: 45548 | H66: 430 | I66: 430/423 | J66: Estável | K66: Milena | L66: Risco de conflito | M66: Alta | N66: 430 → 430/423
A67: 426986 | B67: 426986 | C67: 2024 | D67: MMLV | E67: 15266 | F67: 45505 | G67: 45546 | H67: 716 | I67: 716 | J67: Estável | K67: Milena | L67: Risco de conflito | M67: Alta | N67: 716 | O67: Prontuário associado a identificações de paciente distintas
A68: 426986 | B68: 426986 | C68: 2024 | D68: MMLL | E68: 15266 | F68: 45552 | G68: 45561 | H68: 108 | I68: 108 | J68: Estável | K68: Catarina | L68: Reabordagem | M68: Alta | N68: 108 | O68: Prontuário associado a identificações de paciente distintas
A69: 6472702 | B69: 6472702 | C69: 2024 | D69: MAR | E69: 22848 | F69: 45541 | G69: 45558 | H69: 316 | I69: 316 | J69: Estável | K69: Carolina | L69: Risco de deterioração | M69: Alta | N69: 316
A70: 868878 | B70: 868878 | C70: 2024 | D70: JPR | E70: 21870 | F70: 45555 | G70: 45575 | H70: 318 | I70: 318 | J70: Crítico | K70: Oncologia | L70: TMO | M70: Alta | N70: 318
A71: 82610 | B71: 82610 | C71: 2024 | D71: EH | E71: 1952 | F71: 45518 | G71: 45572 | H71: 101 | I71: 320 | J71: Crítico | K71: Oncologia | L71: Quimioterapia | M71: Óbito | N71: 101 → 320
A72: 526828 | B72: 526828 | C72: 2024 | D72: LFA | E72: 32506 | F72: 45561 | G72: 45565 | H72: 108 | I72: 108 | J72: Estável | K72: Catarina | L72: Risco de suicídio | M72: Alta | N72: 108
A73: 92905 | B73: 92905 | C73: 2024 | D73: VMF | E73: 17904 | F73: 45562 | G73: 45565 | H73: 114 | I73: 114 | J73: Estável | K73: Oncologia | L73: Quimioterapia | M73: Alta | N73: 114
A74: 489641 | B74: 489641 | C74: 2024 | D74: PRM | E74: 22904 | F74: 45564 | G74: 45566 | H74: 804 | I74: 804 | J74: Estável | K74: Catarina | L74: Risco de deterioração | M74: Alta | N74: 804
A75: 365832 | B75: 365832 | C75: 2024 | D75: ENM | E75: 24964 | F75: 45566 | G75: 45579 | H75: 102 | I75: 204 | J75: Estável | K75: Clínica Médica | L75: Pós evento adverso | M75: Alta | N75: 102 → 416 → 204
A76: 75497 | B76: 75497 | C76: 2024 | D76: MAA | E76: 12940 | F76: 45567 | G76: 45572 | H76: 411 | I76: 411 | J76: Estável | K76: Catarina | L76: Risco de deterioração | M76: Alta | N76: 411
A77: 900876 | B77: 900876 | C77: 2024 | D77: MARA | E77: 42643 | F77: 45568 | G77: 45588 | H77: 401 | I77: 431A/426 | J77: Estável | K77: Milena | L77: Pós queixa crítica | M77: Alta | N77: 401 → 431A → 431A/426
A78: 788953 | B78: 788953 | C78: 2024 | D78: BCC | E78: 36177 | F78: 45572 | G78: 45574 | H78: 313 | I78: 313 | J78: Estável | K78: Carol | L78: Risco de suicídio | M78: Alta | N78: 313
A79: 768549 | B79: 768549 | C79: 2024 | D79: RRJ | E79: 44298 | F79: 45567 | G79: 45575 | H79: 423A | I79: 423A | J79: Estável | K79: Milena | L79: Pós queixa crítica | M79: Alta | N79: 423A
A80: 900848 | B80: 900848 | C80: 2024 | D80: ISIS | E80: 45038 | F80: 45569 | G80: 45579 | H80: 435 | I80: 435 | J80: Estável | K80: Milena | L80: Pós queixa crítica | M80: Alta | N80: 435
A81: 209507 | B81: 209507 | C81: 2024 | D81: SBC | E81: 14766 | F81: 45575 | G81: 45579 | H81: 111 | I81: 111 | J81: Crítico | K81: Oncologia | L81: Pós queixa crítica | M81: Alta | N81: 111
A82: 896188 | B82: 896188 | C82: 2024 | D82: MAG | E82: 24932 | F82: 45575 | G82: 45579 | H82: 102 | I82: 102 | J82: Crítico | K82: Oncologia | L82: Risco de suicídio | M82: Alta | N82: 102
A83: 329364 | B83: 329364 | C83: 2024 | D83: NNB | E83: 19959 | F83: 45575 | G83: 45579 | H83: 209 | I83: 209 | J83: Estável | K83: Catarina | L83: Risco de deterioração | M83: Alta | N83: 209
A84: 688014 | B84: 688014 | C84: 2024 | D84: IMO | E84: 34925 | F84: 45579 | G84: 45659 | H84: 108 | I84: 111 | J84: Estável | K84: Oncologia | L84: Quimioterapia | M84: Alta | N84: 108 → 111
A85: 791367 | B85: 791367 | C85: 2024 | D85: MCV | E85: 44687 | F85: 45561 | G85: 45582 | H85: 433 | I85: 433 | J85: Estável | K85: UTI PED | L85: Pós queixa crítica | M85: Alta | N85: 433
A86: 900403 | B86: 900403 | C86: 2024 | D86: FNS | E86: 45565 | F86: 45565 | G86: 45586 | H86: 506 | I86: 506 | J86: Estável | K86: UTI NEMater | L86: Pós evento adverso | M86: Alta | N86: 506
A87: 6541529 | B87: 6541529 | C87: 2024 | D87: JRS | E87: 19863 | F87: 45581 | G87: 45607 | H87: 609 | I87: 806 | J87: Estável | K87: Catarina/ Sara | L87: Reabordagem | M87: Alta | N87: 609 → 806 | O87: Mesmas iniciais e nascimento associados a prontuários distintos: 42080, 6541529
A88: 830399 | B88: 830399 | C88: 2024 | D88: LVDR | E88: 38278 | F88: 45580 | G88: 45583 | H88: 321A | I88: 321A | J88: Estável | K88: Carol | L88: Risco de agressão | M88: Alta | N88: 321A
A89: 762718 | B89: 762718 | C89: 2024 | D89: LBJ | E89: 20152 | F89: 45520 | G89: 45629 | H89: 804 | I89: 801 | J89: Estável | K89: Catarina | L89: Pós queixa crítica | M89: Alta | N89: 804 → 803 → 801
A90: 775873 | B90: 775873 | C90: 2024 | D90: SCDO | E90: 24657 | F90: 45573 | G90: 45614 | H90: 301 | I90: 301 | J90: Estável | K90: Catarina | L90: Pós queixa crítica | M90: Alta | N90: 301
A91: 618970 | B91: 618970 | C91: 2024 | D91: MVR | E91: 43559 | F91: 45584 | G91: 45589 | H91: 432 | I91: 432 | J91: Estável | K91: Milena | L91: Pós queixa crítica | M91: Alta | N91: 432
A92: 108564 | B92: 108564 | C92: 2024 | D92: TGO | E92: 15895 | F92: 45553 | G92: 45593 | H92: 412 | I92: 412 | J92: Crítico | K92: Catarina | L92: Risco de deterioração | M92: Óbito | N92: 412
A93: 855898 | B93: 855898 | C93: 2024 | D93: JCG | E93: 16706 | F93: 45569 | G93: 45593 | H93: 312 | I93: 312 | J93: Estável | K93: Catarina | L93: Pós queixa crítica | M93: Alta | N93: 312
A94: 6558494 | B94: 6558494 | C94: 2024 | D94: ELW | E94: 21234 | F94: 45589 | G94: 45604 | H94: 607 | I94: 607 / 107 | J94: Estável | K94: Carol / Catarina | L94: Reabordagem | M94: Estabilização | N94: 607 → 607 / 107
A95: 900150 | B95: 900150 | C95: 2024 | D95: JV | E95: 45562 | F95: 45562 | G95: 45723 | H95: 502 | I95: 502/432/423 | J95: Estável | K95: Milena | L95: Pós queixa crítica | M95: Alta | N95: 502 → 502/432 → 502/432/423
A96: 903370 | B96: 903370 | C96: 2024 | D96: LET | E96: 45064 | F96: 45582 | G96: 45602 | H96: 432 | I96: 432 | J96: Estável | K96: Milena | L96: Pós queixa crítica | M96: Alta | N96: 432
A97: 6560416 | B97: 6560416 | C97: 2024 | D97: ACM | E97: 21067 | F97: 45590 | G97: 45604 | H97: 331B | I97: 331A | J97: Estável | K97: Catarina/ Sara | L97: Reabordagem | M97: Alta | N97: 331B → 221B → 331A
A98: 555596 | B98: 555596 | C98: 2024 | D98: LRSO | E98: 43229 | F98: 0 | G98: 45678 | H98: 434 | I98: 434 | J98: Estável | K98: Milena | L98: Pós queixa crítica | M98: Alta | N98: 434 | O98: Data de entrada não pôde ser interpretada: RECOLOCADO 21/10/2024 | Data de entrada válida não disponível
A99: 6564223 | B99: 6564223 | C99: 2024 | D99: VLSMB | E99: 21291 | F99: 45600 | G99: 45601 | H99: 314 | I99: 314 | J99: Estável | K99: Carol | L99: Pós queixa crítica | M99: Alta | N99: 314
A100: 666136 | B100: 666136 | C100: 2024 | D100: DVVL | E100: 29762 | F100: 45591 | G100: 45632 | H100: 108 | I100: 108 | J100: Crítico | K100: Catarina/ Bia | L100: Risco de deterioração | M100: Alta | N100: 108 | O100: Mesmas iniciais e nascimento associados a prontuários distintos: 6378502, 666136
...

Sheet Foloow Up Huddle
A1: Data Ocorrência | B1: Mês | C1: Ano | D1: Unidade | E1: Área | F1: Categoria | G1: Descrição do Problema | H1: Status | I1: Responsável
A2: 45518 | B2: Agosto | C2: 2024 | D2: HVC | E2: Operações | F2: Assistencial | G2: Avental - Qualidade | H2: Concluído | I2: Simone
A3: 45518 | B3: Agosto | C3: 2024 | D3: HVC | E3: Laboratório | F3: Assistencial | G3: Hemoculturas - Atenção Global | H3: Em andamento | I3: Não informado
A4: 45518 | B4: Agosto | C4: 2024 | D4: HVC | E4: Operações / Enfermagem | F4: Sistemas de Informações | G4: Quality24 - Concierge: Adesão SLA | H4: Em andamento | I4: Simone / Lilian
A5: 45518 | B5: Agosto | C5: 2024 | D5: HVC | E5: Operações | F5: Assistencial | G5: Nutrição - atraso dieta | H5: Concluído | I5: Simone
A6: 45518 | B6: Agosto | C6: 2024 | D6: HVC | E6: Operações | F6: Infra e Hotelaria | G6: Higiene CME | H6: Concluído | I6: Simone
A7: 45518 | B7: Agosto | C7: 2024 | D7: HVC | E7: Operações | F7: Infra e Hotelaria | G7: Higiene Noturno | H7: Em andamento | I7: Simone
A8: 45518 | B8: Agosto | C8: 2024 | D8: HVC | E8: NSP | F8: Assistencial | G8: Falha na Identificação do Paciente PA | H8: Concluído | I8: Não informado
A9: 45518 | B9: Agosto | C9: 2024 | D9: HVC | E9: NSP | F9: Assistencial | G9: Número de Punções alto/ FLEBITE | H9: Em andamento | I9: Déborah
A10: 45518 | B10: Agosto | C10: 2024 | D10: HVC | E10: Enfermagem | F10: Assistencial | G10: Prótese com lateralidade errada | H10: Concluído | I10: Não informado
A11: 45518 | B11: Agosto | C11: 2024 | D11: HVC | E11: Operações | F11: Infra e Hotelaria | G11: Elevador parou com paciente entubado | H11: Concluído | I11: Januário
A12: 45518 | B12: Agosto | C12: 2024 | D12: HVC | E12: Operações / Enfermagem | F12: Sistemas de Informações | G12: Quality24 - Concierge: Uso da ferramenta | H12: Em andamento | I12: Regiane
A13: 45519 | B13: Agosto | C13: 2024 | D13: HVC | E13: Enfermagem | F13: Sistemas de Informações | G13: Processo Toten PS | H13: Concluído | I13: Bianca
... A2269: 46021 | B2269: Dezembro | C2269: 2025 | D2269: CSC | E2269: Manutenção | F2269: Infra e Hotelaria | G2269: 1 notificação ar condicionado | H2269: Concluído | I2269: Não informado
A2270: 46027 | B2270: Janeiro | C2270: 2026 | D2270: HVC | E2270: Enfermagem Alas | F2270: Assistencial | G2270: 1 código amarelo | H2270: Concluído | I2270: Letícia
A2271: 46027 | B2271: Janeiro | C2271: 2026 | D2271: HVC | E2271: Manutenção | F2271: Infra e Hotelaria | G2271: 715 reclamação ar via Q24 | H2271: Concluído | I2271: Januário
A2272: 46027 | B2272: Janeiro | C2272: 2026 | D2272: HVC | E2272: Engenharia Clínica | F2272: Infra e Hotelaria | G2272: Manutenção tomografia são camilo | H2272: Em andamento | I2272: Victório
A2273: 46027 | B2273: Janeiro | C2273: 2026 | D2273: HVC | E2273: NSP | F2273: Assistencial | G2273: 1 Notificação sobre dispensário da UTI | H2273: Concluído | I2273: Thalita
A2274: 46027 | B2274: Janeiro | C2274: 2026 | D2274: HVC | E2274: Nutrição | F2274: Infra e Hotelaria | G2274: 715 Nutrição queixa Via Q24 | H2274: Concluído | I2274: Juliana
A2275: 46027 | B2275: Janeiro | C2275: 2026 | D2275: HVC | E2275: NSP | F2275: Assistencial | G2275: Cateter Nasal Notificação | H2275: Em andamento | I2275: Julia
A2276: 46028 | B2276: Janeiro | C2276: 2026 | D2276: HVC | E2276: Manutenção | F2276: Infra e Hotelaria | G2276: conforto foi liberado pela manhã neuro | H2276: Concluído | I2276: Alan
A2277: 46028 | B2277: Janeiro | C2277: 2026 | D2277: HVC | E2277: Command Center | F2277: Fluxo do Paciente | G2277: 604 aguardando vaga de semi desde ontem | H2277: Em andamento | I2277: Lucas
A2278: 46028 | B2278: Janeiro | C2278: 2026 | D2278: HVC | E2278: Manutenção | F2278: Infra e Hotelaria | G2278: 715 bloqueado para manutenção do chuveiro | H2278: Em andamento | I2278: Alan
A2279: 46028 | B2279: Janeiro | C2279: 2026 | D2279: HVC | E2279: Enfermagem Centro Cirúrgico | F2279: Assistencial | G2279: Bastante Cirúrgias Eletivas | H2279: Em andamento | I2279: Adriana Furlan
A2280: 46028 | B2280: Janeiro | C2280: 2026 | D2280: HVC | E2280: Quality 24 | F2280: Sistemas de Informações | G2280: Transporte 39% | H2280: Concluído | I2280: Regiane
A2281: 46028 | B2281: Janeiro | C2281: 2026 | D2281: HVC | E2281: Quality 24 | F2281: Sistemas de Informações | G2281: Higiene 50% | H2281: Concluído | I2281: Regiane
... A3804: 46244 | B3804: Agosto | C3804: 2026 | D3804: HVC | E3804: Enfermagem Alas | F3804: Assistencial | G3804: 108 código amarelo | H3804: Concluído | I3804: Leticia
A3805: 46244 | B3805: Agosto | C3805: 2026 | D3805: HVC | E3805: Farmácia | F3805: Assistencial | G3805: 1 not de quantidade de frasco de medicamento encontrado no leito do paciente, era para ter 4 frascos e só foram encontrados 3, ultimo frasco encontrado no dia seguinte. | H3805: Concluído
A3806: 46244 | B3806: Agosto | C3806: 2026 | D3806: HVC | E3806: Especialistas | F3806: Assistencial | G3806: Falha de passagem de plantão 2°D | H3806: Concluído | I3806: Deborah
A3807: 46244 | B3807: Agosto | C3807: 2026 | D3807: HVC | E3807: Especialistas | F3807: Assistencial | G3807: 1 Not de falta de pulseira de identificação | H3807: Concluído | I3807: Deborah
A3808: 46244 | B3808: Agosto | C3808: 2026 | D3808: CMI | E3808: T.I | F3808: Sistemas de Informações | G3808: Computadores no CMI não estão funcionando | H3808: Concluído | I3808: Cris
A3809: 46244 | B3809: Agosto | C3809: 2026 | D3809: CMSC | E3809: T.I | F3809: Sistemas de Informações | G3809: Impressoras com problemas no CMSC | H3809: Concluído | I3809: Cris
A3810: 46244 | B3810: Agosto | C3810: 2026 | D3810: CMI | E3810: Eng. Clinica | F3810: Infra e Hotelaria | G3810: Equipamento alto refrator com problema no CMI (oftalmo) | H3810: Concluído | I3810: Victorio
A3811: 46244 | B3811: Agosto | C3811: 2026 | D3811: HVC | E3811: NSP | F3811: Assistencial | G3811: NOT Caixa de transporte de medicamentos, sendo transportada sem o cadeado | H3811: Concluído | I3811: Vivia
A3812: 46244 | B3812: Agosto | C3812: 2026 | D3812: CSC | E3812: Nutrição | F3812: Assistencial | G3812: Problema na alimentação servida aos médicos(Nutrição da Mandic) | H3812: Concluído | I3812: Carla
A3813: 46245 | B3813: Agosto | C3813: 2026 | D3813: HVC | E3813: Q24 | F3813: Assistencial | G3813: Questão de transporte de pacientes, (pacientes se perdem dentro do hospital) Solicitações estão sendo feitas via Quality | H3813: Concluído | I3813: Claudia
A3814: 46245 | B3814: Agosto | C3814: 2026 | D3814: HVC | E3814: Eng. Clinica | F3814: Infra e Hotelaria | G3814: Manutenção Robo da Vinci(Strattner) | H3814: Concluído | I3814: Victorio
A3815: 46245 | B3815: Agosto | C3815: 2026 | D3815: HVC | E3815: Eng. Clinica | F3815: Infra e Hotelaria | G3815: Raio x do PS não funcionante, aguardando peça para concerto. | H3815: Concluído | I3815: Victorio
A3816: 46245 | B3816: Agosto | C3816: 2026 | D3816: HVC | E3816: Especialistas | F3816: Assistencial | G3816: NOT de Pulseira improvisada de Indetificação | H3816: Concluído | I3816: Deborah
A3817: 46245 | B3817: Agosto | C3817: 2026 | D3817: HVC | E3817: NSP | F3817: Assistencial | G3817: 1 Falha de medicação no 2°D | H3817: Concluído | I3817: Deborah
... A3915: 46265 | B3915: Agosto | C3915: 2026 | D3915: HVC | E3915: Especialistas | F3915: Assistencial | G3915: Falha passagem de plantão | H3915: Concluído | I3915: Deborah
A3916: 46266 | B3916: Setembro | C3916: 2026 | D3916: HVC | E3916: Manutenção | F3916: Infra e Hotelaria | G3916: 432 Bloqueado por conta de vazamento durante a noite(Ainda sem previsão) | H3916: Concluído | I3916: Alan
A3917: 46266 | B3917: Setembro | C3917: 2026 | D3917: HVC | E3917: CAF | F3917: Assistencial | G3917: Notificações sobre atraso de entrega do Gimba | H3917: Concluído | I3917: Paloma
A3918: 46266 | B3918: Setembro | C3918: 2026 | D3918: HVC | E3918: Engenharia Clínica | F3918: Infra e Hotelaria | G3918: RM do Castelo foi Liberada na data de ontem por volta do Meio dia | H3918: Concluído | I3918: Victório
A3919: 46266 | B3919: Setembro | C3919: 2026 | D3919: HVC | E3919: Engenharia Clínica | F3919: Infra e Hotelaria | G3919: Lavadora das Pinças dos Robos, Strattner vai retornar hoje para manutenção | H3919: Concluído | I3919: Victório
A3920: 46266 | B3920: Setembro | C3920: 2026 | D3920: HVC | E3920: Manutenção | F3920: Infra e Hotelaria | G3920: Quarto 207 foi bloqueado para substituição do Ar Condicionado, o mesmo caiu no quarto por duas vezes e foi visto a necessidade de troca | H3920: Concluído | I3920: Alan
A3921: 46266 | B3921: Setembro | C3921: 2026 | D3921: HVC | E3921: Especialistas | F3921: Assistencial | G3921: 1 Falha de Identificação de paciente no Pronto Socorro | H3921: Concluído | I3921: Deborah
A3922: 46266 | B3922: Setembro | C3922: 2026 | D3922: HVC | E3922: Manutenção | F3922: Infra e Hotelaria | G3922: Está sendo realizada a retirada do telhado do 4°D, e realizar fornecimento dos protetores auriculares principais setores afetados vão ser o 3°D e 2°C | H3922: Concluído | I3922: Alan
A3923: 46267 | B3923: Setembro | C3923: 2026 | D3923: HVC | E3923: Eng. Clinica | F3923: Infra e Hotelaria | G3923: Lavadora do robo na CME concertada | H3923: Concluído | I3923: Victório
A3924: 46267 | B3924: Setembro | C3924: 2026 | D3924: HVC | E3924: Manutenção | F3924: Infra e Hotelaria | G3924: Previsão de liberação do 207 até o fim do dia | H3924: Concluído | I3924: Alan
A3925: 46267 | B3925: Setembro | C3925: 2026 | D3925: HVC | E3925: NSP | F3925: Assistencial | G3925: Not uso adorno (Falar na sexta) | H3925: Concluído | I3925: Thaiany
A3926: 46267 | B3926: Setembro | C3926: 2026 | D3926: HVC | E3926: NSP | F3926: Assistencial | G3926: Not falha na organização de prontuarios | H3926: Concluído | I3926: Thaiany
A3927: 46267 | B3927: Setembro | C3927: 2026 | D3927: CMI | E3927: Manutenção | F3927: Infra e Hotelaria | G3927: CMI problema no ar condicionado no PA | H3927: Concluído | I3927: Cris
... A3954: 46273 | B3954: Setembro | C3954: 2026 | D3954: HVC | E3954: Manutenção | F3954: Assistencial | G3954: Queixa de barulho na SEMI 1, Reforçar o uso de protetor auricular | H3954: Concluído | I3954: Alan
A3955: 46273 | B3955: Setembro | C3955: 2026 | D3955: HVC | E3955: Diretoria | F3955: Assistencial | G3955: Ponto de atenção da transferência da SEMI 2 para o 6°D, está no radar da diretoria. | H3955: Concluído
A3956: 46274 | B3956: Setembro | C3956: 2026 | D3956: HVC | E3956: Higuiene | F3956: Assistencial | G3956: Atraso da higuiene no noturno que gerou impacto na sala do robo (Centro Cirurgico) | H3956: Concluído | I3956: Adriana Furlam
A3957: 46274 | B3957: Setembro | C3957: 2026 | D3957: HVC | E3957: Eng. Clinica | F3957: Infra e Hotelaria | G3957: Semi 2 precisando de uma central para monitoramento dos pacientes, pois só tem na uti geral - 6°andar (será resolvido hoje, Eng. Clinica e T.I atuando) - Resolvido | H3957: Concluído | I3957: Juliana
A3958: 46274 | B3958: Setembro | C3958: 2026 | D3958: HVC | E3958: Alas de Internação | F3958: Assistencial | G3958: 1 código amarelo | H3958: Concluído | I3958: Leticia
A3959: 46274 | B3959: Setembro | C3959: 2026 | D3959: HVC | E3959: Manutenção | F3959: Infra e Hotelaria | G3959: Permanece como ponto de atenção o ruido do 4°D | H3959: Concluído | I3959: Alan
A3960: 46274 | B3960: Setembro | C3960: 2026 | D3960: HVC | E3960: Especialistas | F3960: Assistencial | G3960: Not de queda 2°C | H3960: Concluído | I3960: Deborah
A3961: 46274 | B3961: Setembro | C3961: 2026 | D3961: HVC | E3961: NSP | F3961: Assistencial | G3961: Not código roxo | H3961: Concluído | I3961: Vivia
A3962: 46274 | B3962: Setembro | C3962: 2026 | D3962: CSC | E3962: Manutenção | F3962: Infra e Hotelaria | G3962: Aberto OS para o Ar condicionado da SCIH e CME por mais de 15 dias e ainda estão pendentes | H3962: Concluído | I3962: Stefany
A3963: 46275 | B3963: Setembro | C3963: 2026 | D3963: HVC | E3963: GL | F3963: Infra e Hotelaria | G3963: 808 bloqueado (Liberado até o fim do dia) | H3963: Concluído | I3963: Mariana
A3964: 46275 | B3964: Setembro | C3964: 2026 | D3964: HVC | E3964: Manutenção | F3964: Infra e Hotelaria | G3964: Leito 101 com a campainha quebrada | H3964: Concluído | I3964: Alan
A3965: 46275 | B3965: Setembro | C3965: 2026 | D3965: HVC | E3965: Especialistas | F3965: Assistencial | G3965: Falha identificação de paciente Neuro | H3965: Concluído | I3965: Deborah
A3966: 46275 | B3966: Setembro | C3966: 2026 | D3966: HVC | E3966: Alas de internação | F3966: Assistencial | G3966: Código amarelo 803 | H3966: Concluído | I3966: Leticia
A3967: 46275 | B3967: Setembro | C3967: 2026 | D3967: CSC | E3967: Higuiene/Manutenção | F3967: Infra e Hotelaria | G3967: Piolhos de pombo na fármacia (OS aberta porém sem previsão de uma data) empresa de dedetização irá na casa de saude na data de hoje 11/09/2026 | H3967: Concluído | I3967: Katia
... A3974: 46276 | B3974: Setembro | C3974: 2026 | D3974: CSC | E3974: Manutenção | F3974: Infra e Hotelaria | G3974: Pontos de alagamento na Casa de Saude por conta da chuva, refeitorio dos colaboradores não tem nem como entrar, CME e Almoxarifado estão menos critico | H3974: Concluído | I3974: Stefany
A3975: 46276 | B3975: Setembro | C3975: 2026 | D3975: HVC | F3975: Assistencial Médico | G3975: Médica da unidade do Iguatemi se recusou a fazer atendimento manual por conta da queda do tasy | H3975: Concluído | I3975: Luciana
A3976: 46279 | B3976: Setembro | C3976: 2026 | D3976: HVC | E3976: Manutenção | F3976: Infra e Hotelaria | G3976: Vazamento na sala 7 do centro cirurgico | H3976: Concluído | I3976: Adriana Furlam
A3977: 46279 | B3977: Setembro | C3977: 2026 | D3977: HVC | E3977: Eng. Clinica | F3977: Infra e Hotelaria | G3977: Raio-x sala 2 do ps teve problemas no sábado e foi resolvido no sábado mesmo | H3977: Concluído | I3977: Victório
A3978: 46279 | B3978: Setembro | C3978: 2026 | D3978: HVC | E3978: Manutenção | F3978: Infra e Hotelaria | G3978: 808 Bloqueado para reforma | H3978: Concluído | I3978: Januario
A3979: 46279 | B3979: Setembro | C3979: 2026 | D3979: HVC | E3979: NSP | F3979: Infra e Hotelaria | G3979: Not relacionado a higiene | H3979: Concluído | I3979: Vivia
A3980: 46279 | B3980: Setembro | C3980: 2026 | D3980: CSC | E3980: Manutenção | F3980: Infra e Hotelaria | G3980: Vazamento no conforto do PS da Casa de Saúde, será verificado assim que a chuva passar | H3980: Concluído | I3980: Januario
A3981: 46280 | B3981: Setembro | C3981: 2026 | D3981: HVC | E3981: Manutenção | F3981: Infra e Hotelaria | G3981: A partir de agora teremos apenas um ponto de internação, o outro vai ser uma terceira triagem onde vai ser realizado o eletro. | H3981: Concluído | I3981: Alan
A3982: 46280 | B3982: Setembro | C3982: 2026 | D3982: HVC | E3982: Manutenção | F3982: Infra e Hotelaria | G3982: 212 Bloqueado por conta de vazamento na parede | H3982: Concluído | I3982: Alan
A3983: 46280 | B3983: Setembro | C3983: 2026 | D3983: HVC | E3983: Manutenção | F3983: Infra e Hotelaria | G3983: 311 Bloqueado, previsão até as 15 | H3983: Concluído | I3983: Alan
A3984: 46280 | B3984: Setembro | C3984: 2026 | D3984: HVC | E3984: Manutenção | F3984: Infra e Hotelaria | G3984: 408 Bloqueado previsão de liberação hoje | H3984: Concluído | I3984: Alan
A3985: 46280 | B3985: Setembro | C3985: 2026 | D3985: HVC | E3985: Enfermagem | F3985: Assistencial | G3985: 431 Criança Internada por tentativa de autoexterminio (provavel alta 16/09/26) | H3985: Concluído | I3985: Melissa Savy
A3986: 46280 | B3986: Setembro | C3986: 2026 | D3986: HVC | E3986: Centro cirúgico | F3986: Assistencial | G3986: Notificação Material vencido de OPME no Centro cirúrgico | H3986: Concluído
A3987: 46280 | B3987: Setembro | C3987: 2026 | D3987: HVC | E3987: Centro cirúgico | F3987: Assistencial | G3987: NOT para Farmácia Falta de material no Centro Obstetrico | H3987: Concluído
A3988: 46280 | B3988: Setembro | C3988: 2026 | D3988: HVC | E3988: Engenharia clínica | F3988: Infra e Hotelaria | G3988: RM do Castelo parada, está sendo verificada por técnico o ocorrido | H3988: Concluído | I3988: Victorio
A3989: 46280 | B3989: Setembro | C3989: 2026 | D3989: HVC | E3989: Manutenção | F3989: Infra e Hotelaria | G3989: Retorna o ruído, ponto de atenção | H3989: Concluído | I3989: Alan
A3990: 46280 | B3990: Setembro | C3990: 2026 | D3990: HVC | E3990: Manutenção | F3990: Infra e Hotelaria | G3990: Vazamento no conforto médico do 3°D | H3990: Concluído | I3990: Alan
A3991: 46280 | B3991: Setembro | C3991: 2026 | D3991: HVC | E3991: G&G | F3991: Assistencial | G3991: Ponto de atenção citado por muitas áreas, são as vagas em aberto para contratação | H3991: Concluído
A3992: 46280 | B3992: Setembro | C3992: 2026 | D3992: CSC | E3992: Nutrição | F3992: Assistencial | G3992: Sinalizado na Casa de Saúde que o café da manhã dos pacientes do florença estava atrasado, foi verificado com a RT da Nutrição da MANDIC(aberta Notificação) | H3992: Concluído | I3992: Carla
A3993: 46280 | B3993: Setembro | C3993: 2026 | D3993: CSC | E3993: Operações | F3993: Infra e Hotelaria | G3993: Problemas com Motoboy na Casa de Saúde, com atraso o mesmo entrou às 08:30 da noite | H3993: Concluído | I3993: Stefany
A3994: 46281 | B3994: Setembro | C3994: 2026 | D3994: HVC | E3994: Enfermagem | F3994: Sistemas de Informações | G3994: Sendo questionado o Ramal da T.I, enfermagem da UTI não consegue fazer contato | H3994: Concluído | I3994: Juliana
A3995: 46281 | B3995: Setembro | C3995: 2026 | D3995: HVC | E3995: Centro cirúgico | F3995: Assistencial | G3995: Muitos atrasos de procedimento cirurgico, por conta do atraso da recepção | H3995: Concluído | I3995: Adriana Furlam
A3996: 46281 | B3996: Setembro | C3996: 2026 | D3996: HVC | E3996: Centro cirúgico | F3996: Infra e Hotelaria | G3996: Sala 1, 2 e 3 do centro cirurgico com difcultades de marcar a pressão | H3996: Concluído | I3996: Adriana Furlam
A3997: 46281 | B3997: Setembro | C3997: 2026 | D3997: HVC | E3997: Centro cirúgico | F3997: Infra e Hotelaria | G3997: Problemas na passagem de plantão da higiene do centro cirurgico | H3997: Concluído | I3997: Adriana Furlam
A3998: 46281 | B3998: Setembro | C3998: 2026 | D3998: HVC | E3998: Higiene | F3998: Infra e Hotelaria | G3998: Higiene na CME (ponto de atenção) | H3998: Concluído | I3998: Adriana Furlam
A3999: 46281 | B3999: Setembro | C3999: 2026 | D3999: HVC | E3999: Manutenção | F3999: Infra e Hotelaria | G3999: Ruidos 4°D | H3999: Concluído | I3999: Alan
A4000: 46281 | B4000: Setembro | C4000: 2026 | D4000: HVC | E4000: Especialistas | F4000: Assistencial | G4000: Queda de paciente recepção | H4000: Concluído | I4000: Deborah
A4001: 46281 | B4001: Setembro | C4001: 2026 | D4001: HVC | E4001: Especialistas | F4001: Assistencial | G4001: Queda dois colaboradores da manutenção | H4001: Concluído | I4001: Deborah
A4002: 46281 | B4002: Setembro | C4002: 2026 | D4002: CSC | E4002: Especialistas | F4002: Assistencial | G4002: Queda de paciente | H4002: Concluído | I4002: Deborah
A4003: 46281 | B4003: Setembro | C4003: 2026 | D4003: CSC | E4003: NSP | F4003: Assistencial | G4003: Not de equipe da dor que não compareceu para atendimento do paciente | H4003: Concluído | I4003: Vivia
... A4017: 46283 | B4017: Setembro | C4017: 2026 | D4017: HVC | E4017: NSP | F4017: Assistencial | G4017: Not sobre a dieta na ped | H4017: Concluído | I4017: Thaiany
A4018: 46283 | B4018: Setembro | C4018: 2026 | D4018: HVC | E4018: T.I | F4018: Sistemas de Informações | G4018: Ramal T.I geral (afetando todos os setores por demora de atendimento) | H4018: Em Andamento
A4019: 46283 | B4019: Setembro | C4019: 2026 | D4019: HVC | E4019: Higiene | F4019: Infra e Hotelaria | G4019: Escala alinhada para higiene do Centro Cirurgico do noturno | H4019: Concluído | I4019: Marjorie
...

Sheet Planos de ação JCI
A1: Capítulo | B1: Padrões | C1: Elementos de Mensuração | D1: Descrição do elemento | E1: Classificação (C - N) | F1: Necessário Documento
A2: AOP | B2: Padrão AOP.01.00 Todos os pacientes têm suas necessidades de saúde identificadas por meio de um processo de avaliação definido pelo hospital. | C2: 1 | D2: A política do hospital define, por escrito, o conteúdo mínimo das avaliações para pacientes internados para cada disciplina clínica que realiza as avaliações. (Ver também AOP.01.01, EM 2) | E2: Não Conforme | F2: Sim
A3: AOP | B3: Padrão AOP.01.00 Todos os pacientes têm suas necessidades de saúde identificadas por meio de um processo de avaliação definido pelo hospital. | C3: 2 | D3: A política do hospital define, por escrito, o conteúdo mínimo das avaliações para pacientes ambulatoriais para cada disciplina clínica que realiza avaliações. (Ver também AOP.01.01, EM 2) | E3: Não Conforme | F3: Sim
A4: AOP | B4: Padrão AOP.01.00 Todos os pacientes têm suas necessidades de saúde identificadas por meio de um processo de avaliação definido pelo hospital. | C4: 3 | D4: Somente pessoas qualificadas e permitidas por licenciamento, leis e regulamentos aplicáveis ou certificação realizam as avaliações. (Ver também AOP.01.01, EM 3) | E4: Conforme | F4: Não
A5: AOP | B5: Padrão AOP.01.00 Todos os pacientes têm suas necessidades de saúde identificadas por meio de um processo de avaliação definido pelo hospital. | C5: 4 | D5: O hospital identifica as informações a serem documentadas para as avaliações. | E5: Conforme | F5: Não
A6: AOP | B6: Padrão AOP.01.01 A avaliação inicial de cada paciente inclui um histórico de saúde e uma avaliação das necessidades físicas, psicológicas, espirituais/culturais, sociais e econômicas do paciente. | C6: 1 | D6: Todo os pacientes têm uma avaliação inicial consistente com os requisitos definidos na política do hospital. | E6: Não Conforme | F6: Sim
A7: AOP | B7: Padrão AOP.01.01 A avaliação inicial de cada paciente inclui um histórico de saúde e uma avaliação das necessidades físicas, psicológicas, espirituais/culturais, sociais e econômicas do paciente. | C7: 2 | D7: A avaliação inclui o seguinte: • Exame físico • História de saúde • História do uso de medicamentos e alergias conhecidas • Avaliação psicológica inicial indicada pela condição do paciente • Avaliação socioeconômica inicial, quando indicada pelas necessidades do paciente • Avaliação espiritual e cultural inicial, quando indicada pelas necessidades do paciente (Veja também AOP.01.00, EMs 1 e 2) | E7: Conforme | F7: Não
A8: AOP | B8: Padrão AOP.01.01 A avaliação inicial de cada paciente inclui um histórico de saúde e uma avaliação das necessidades físicas, psicológicas, espirituais/culturais, sociais e econômicas do paciente. | C8: 3 | D8: O hospital descreve requisitos sobre quem é responsável pela avaliação inicial e o prazo da avaliação, incluindo o seguinte: • Quais partes da avaliação inicial cada disciplina é responsável por completar • Conteúdo mínimo para a avaliação médica inicial • Conteúdo mínimo para a avaliação inicial de enfermagem • Conteúdo mínimo para outras avaliações (por exemplo, fisioterapia, fonoaudiologia, serviço social) • Prazo para a conclusão da avaliação inicial • Requisitos de documentação para a avaliação inicial (Ver também AOP.01.00, EM 3) | E8: Não Conforme | F8: Sim
A9: AOP | B9: Padrão AOP.01.01 A avaliação inicial de cada paciente inclui um histórico de saúde e uma avaliação das necessidades físicas, psicológicas, espirituais/culturais, sociais e econômicas do paciente. | C9: 4 | D9: O hospital identifica, por escrito, os grupos de pacientes e populações atendidas que necessitam modificações em sua avaliação inicial. | E9: Conforme | F9: Sim
A10: AOP | B10: Padrão AOP.01.01 A avaliação inicial de cada paciente inclui um histórico de saúde e uma avaliação das necessidades físicas, psicológicas, espirituais/culturais, sociais e econômicas do paciente. | C10: 5 | D10: A avaliação inicial para populações especiais de pacientes é modificada para refletir suas necessidades. | E10: Não Conforme | F10: Não
A11: AOP | B11: Padrão AOP.01.01 A avaliação inicial de cada paciente inclui um histórico de saúde e uma avaliação das necessidades físicas, psicológicas, espirituais/culturais, sociais e econômicas do paciente. | C11: 6 | D11: A avaliação inicial de enfermagem é concluída em até 8 horas e a avaliação médica é concluída em até 24 horas após a admissão no hospital. | E11: Conforme | F11: Não
A12: AOP | B12: Padrão AOP.01.01 A avaliação inicial de cada paciente inclui um histórico de saúde e uma avaliação das necessidades físicas, psicológicas, espirituais/culturais, sociais e econômicas do paciente. | C12: 7 | D12: A avaliação inicial resulta em um diagnóstico inicial ou diagnósticos que requerem tratamento e monitoramento. | E12: Conforme | F12: Não
A13: AOP | B13: Padrão AOP.01.01 A avaliação inicial de cada paciente inclui um histórico de saúde e uma avaliação das necessidades físicas, psicológicas, espirituais/culturais, sociais e econômicas do paciente. | C13: 8 | D13: A avaliação inicial de enfermagem resulta em uma lista de necessidades ou condições específicas de enfermagem que requerem cuidados, intervenções ou monitoramento de enfermagem. | E13: Conforme | F13: Não
... A129: AOP | B129: Padrão AOP.05.06 O hospital garante a qualidade dos serviços prestados por todas as fontes externas contratadas de serviços de radiologia e diagnóstico por imagem. | C129: 5 | D129: Um relatório anual com os dados dos serviços contratados de radiologia e diagnóstico por imagem são fornecidos para quem toma decisões sobre gerenciamento e renovação de contratos. | E129: Conforme | F129: Sim
A130: AOP | B130: Padrão AOP.06.00 Quando aplicável, o hospital estabelece e implementa um programa de segurança em medicina nuclear que atende às normas, leis e regulamentos profissionais aplicáveis | C130: 1 | D130: Um indivíduo qualificado é responsável por supervisionar os serviços de medicina nuclear e os membros relevantes da equipe são devidamente treinados, qualificados e certificados para desempenhar suas respectivas funções em segurança e procedimentos de medicina nuclear. | E130: Não Se Aplica
A131: AOP | B131: Padrão AOP.06.00 Quando aplicável, o hospital estabelece e implementa um programa de segurança em medicina nuclear que atende às normas, leis e regulamentos profissionais aplicáveis | C131: 2 | D131: O hospital implementa protocolos de segurança radiológica, incluindo o uso de blindagem adequada, equipamentos de proteção individual (EPIs) e dispositivos de monitoramento para pacientes e profissionais. | E131: Não Se Aplica
A132: AOP | B132: Padrão AOP.06.00 Quando aplicável, o hospital estabelece e implementa um programa de segurança em medicina nuclear que atende às normas, leis e regulamentos profissionais aplicáveis | C132: 3 | D132: As doses de radiação administradas aos pacientes são otimizadas para fins diagnósticos e terapêuticos e o procedimento inclui monitorar e minimizar a exposição à radiação, obtendo as informações diagnósticas ou o efeito necessário. | E132: Não Se Aplica
A133: AOP | B133: Padrão AOP.06.00 Quando aplicável, o hospital estabelece e implementa um programa de segurança em medicina nuclear que atende às normas, leis e regulamentos profissionais aplicáveis | C133: 4 | D133: A aquisição, armazenamento, manuseio e descarte de radiofármacos está em conformidade com leis, regulamentos, normas profissionais e diretrizes dos fabricantes. | E133: Não Se Aplica
A134: AOP | B134: Padrão AOP.06.00 Quando aplicável, o hospital estabelece e implementa um programa de segurança em medicina nuclear que atende às normas, leis e regulamentos profissionais aplicáveis | C134: 5 | D134: Pacientes e familiares são informados sobre os procedimentos e precauções de segurança. | E134: Não Se Aplica
A135: PCC | B135: Padrão PCC.01.00 O hospital implementa processos que apoiam os direitos do paciente e da família durante o cuidado. | C135: 1 | D135: Líderes do hospital trabalham de forma colaborativa para proteger e promover os direitos dos pacientes e familiares. | E135: Conforme | F135: Não
A136: PCC | B136: Padrão PCC.01.00 O hospital implementa processos que apoiam os direitos do paciente e da família durante o cuidado. | C136: 2 | D136: Líderes do hospital implementam os direitos do paciente e da família conforme identificados nas leis e regulamentos. | E136: Conforme | F136: Sim
A137: PCC | B137: Padrão PCC.01.00 O hospital implementa processos que apoiam os direitos do paciente e da família durante o cuidado. | C137: 3 | D137: Líderes do hospital protegem os direitos do paciente e da família em relação às práticas culturais do pacientes comunitários ou individuais atendidos. | E137: Conforme | F137: Sim
A138: PCC | B138: Padrão PCC.01.00 O hospital implementa processos que apoiam os direitos do paciente e da família durante o cuidado. | C138: 4 | D138: Líderes do hospital protegem o direito do paciente de identificar quem o paciente deseja que participe das decisões de cuidado. | E138: Conforme | F138: Não
A139: PCC | B139: Padrão PCC.01.00 O hospital implementa processos que apoiam os direitos do paciente e da família durante o cuidado. | C139: 5 | D139: O hospital tem um processo para determinar as preferências do paciente ou da família em relação ao que e quando as informações são fornecidas ao paciente, família ou outras pessoas. | E139: Não Conforme | F139: Não
A140: PCC | B140: Padrão PCC.01.00 O hospital implementa processos que apoiam os direitos do paciente e da família durante o cuidado. | C140: 6 | D140: Todos da equipe clínica são treinados sobre como apoiar os direitos do paciente e da família e sobre sua participação no cuidado. | E140: Não Conforme | F140: Não
A141: PCC | B141: Padrão PCC.01.01 O hospital respeita, protege e promove os direitos dos pacientes. | C141: 1 | D141: Informações sobre os direitos e responsabilidades do paciente são fornecidos a cada paciente em um idioma que o paciente entenda. (Veja também MOI.02.02, EM 3) | E141: Não Conforme | F141: Não
A142: PCC | B142: Padrão PCC.01.01 O hospital respeita, protege e promove os direitos dos pacientes. | C142: 2 | D142: A política escrita do hospital sobre os direitos do paciente está disponível para a equipe. (Veja também SQE.01.06, EM 2) | E142: Conforme | F142: Sim
A143: PCC | B143: Padrão PCC.01.01 O hospital respeita, protege e promove os direitos dos pacientes. | C143: 3 | D143: O hospital trata o paciente de maneira respeitosa que apoia a dignidade do paciente. | E143: Conforme | F143: Não
A144: PCC | B144: Padrão PCC.01.01 O hospital respeita, protege e promove os direitos dos pacientes. | C144: 4 | D144: As crenças, valores e preferências espirituais e culturais do paciente são respeitados. | E144: Conforme | F144: Não
A145: PCC | B145: Padrão PCC.01.01 O hospital respeita, protege e promove os direitos dos pacientes. | C145: 5 | D145: O hospital responde a solicitações relacionadas ao apoio religioso ou espiritual. | E145: Conforme | F145: Não
A146: PCC | B146: Padrão PCC.01.02 O hospital protege a privacidade do paciente, a confidencialidade e o acesso às informações de saúde. | C146: 1 | D146: Privacidade do paciente é respeitada para todas as entrevistas clínicas, exames, procedimentos/tratamentos E transporte. (Veja também GLD.09.00, EM 3; HCT.01.03, EM 2; MOI.01.01, EM 1; MOI.01.02, EM 3) | E146: Não Conforme | F146: Não
... A241: ASC | B241: Padrão ASC.04.04 Os cuidados cirúrgicos que incluem a implantação de um dispositivo médico são planejados com consideração especial sobre como os processos padrão devem ser modificados. | C241: 5 | D241: O hospital implementa um processo para entrar em contato e acompanhar os pacientes em um período de tempo definido após receber a notificação de um recall de um dispositivo médico implantável. | E241: Conforme | F241: Não
A242: ACC | B242: Padrão ACC.01.00-Os pacientes internados no hospital ou que procuram serviços ambulatoriais são triados para identificar se suas necessidades de cuidados de saúde correspondem à missão, escopo de cuidados e recursos do hospital. | C242: 1 | D242: Os resultados da triagem determinam se os pacientes são aceitos ou admitidos no hospital, dependendo das necessidades do paciente que correspondem à missão, ao escopo do cuidado e aos recursos disponíveis do hospital. | E242: Conforme
A243: ACC | B243: Padrão ACC.01.00-Os pacientes internados no hospital ou que procuram serviços ambulatoriais são triados para identificar se suas necessidades de cuidados de saúde correspondem à missão, escopo de cuidados e recursos do hospital. | C243: 2 | D243: Pacientes fora da missão do hospital, escopo de cuidados ou recursos disponíveis são avaliados e estabilizados dentro da capacidade do hospital antes da transferência. | E243: Conforme
A244: ACC | B244: Padrão ACC.01.00-Os pacientes internados no hospital ou que procuram serviços ambulatoriais são triados para identificar se suas necessidades de cuidados de saúde correspondem à missão, escopo de cuidados e recursos do hospital. | C244: 3 | D244: O hospital transfere, encaminha ou auxilia o paciente ou família na identificação e/ou obtenção de fontes apropriadas de cuidados se suas necessidades não corresponderem à missão, escopo de cuidados ou recursos disponíveis do hospital. | E244: Não Conforme
A245: ACC | B245: Padrão ACC.01.00-Os pacientes internados no hospital ou que procuram serviços ambulatoriais são triados para identificar se suas necessidades de cuidados de saúde correspondem à missão, escopo de cuidados e recursos do hospital. | C245: 4 | D245: Os pacientes são admitidos no serviço ou unidade que atende às suas necessidades mais urgentes. | E245: Conforme
A246: ACC | B246: Padrão ACC.01.00-Os pacientes internados no hospital ou que procuram serviços ambulatoriais são triados para identificar se suas necessidades de cuidados de saúde correspondem à missão, escopo de cuidados e recursos do hospital. | C246: 5 | D246: As avaliações e tratamentos realizados antes da transferência estão documentados em um registo mantido pelo hospital que transfere. (Ver também ACC.03.00, EM 4) | E246: Conforme
A247: ACC | B247: Padrão ACC.01.00-Os pacientes internados no hospital ou que procuram serviços ambulatoriais são triados para identificar se suas necessidades de cuidados de saúde correspondem à missão, escopo de cuidados e recursos do hospital. | C247: 6 | D247: Existe um processo para fornecer os resultados dos exames diagnósticos aos responsáveis por determinar se o paciente deve ser internado, transferido ou encaminhado. | E247: Não Conforme
A248: ACC | B248: Padrão ACC.01.01-Pacientes com necessidades emergentes, urgentes ou imediatas são priorizados para avaliação e tratamento. | C248: 1 | D248: O hospital seleciona e utiliza um processo de triagem baseado em evidências, adequado à sua população de pacientes, para identificar e priorizar pacientes com necessidades emergentes, urgentes e imediatas. | E248: Não Conforme
A249: ACC | B249: Padrão ACC.01.01-Pacientes com necessidades emergentes, urgentes ou imediatas são priorizados para avaliação e tratamento. | C249: 2 | D249: O hospital identificou quais exames específicos ou exames de diagnóstico devem ser concluídos antes de admitir ou registrar pacientes. | E249: Conforme
A250: ACC | B250: Padrão ACC.01.01-Pacientes com necessidades emergentes, urgentes ou imediatas são priorizados para avaliação e tratamento. | C250: 3 | D250: O processo de triagem inclui o reconhecimento precoce de doenças transmissíveis. | E250: Conforme
A251: ACC | B251: Padrão ACC.01.01-Pacientes com necessidades emergentes, urgentes ou imediatas são priorizados para avaliação e tratamento. | C251: 4 | D251: A equipe é treinada para usar o processo de triagem, incluindo o reconhecimento precoce de doenças transmissíveis. | E251: Conforme
A252: ACC | B252: Padrão ACC.01.01-Pacientes com necessidades emergentes, urgentes ou imediatas são priorizados para avaliação e tratamento. | C252: 5 | D252: Existe um processo de observação dos pacientes quando clinicamente indicado. | E252: Não Conforme
A253: ACC | B253: Padrão- ACC.01.02- hospital considera as necessidades clínicas dos pacientes e informa quando há atrasos incomuns para os serviços de diagnóstico e/ou tratamento. | C253: 1 | D253: Pacientes são informados quando haverá atraso no atendimento e/ou tratamento. | E253: Não Conforme
... A571: SQE | B571: Padrão SQE.01.04 Há informações pessoais documentadas para cada membro da equipe. | C571: 3 | D571: Os arquivos pessoais contêm evidências documentadas do seguinte: • Descrição do cargo atual que inclui qualificações e responsabilidades do trabalho, conforme indicado (Veja também SQE.01.01, EM 4) • Histórico de trabalho do membro da equipe • Registro de orientação concluída sobre o hospital • Registro da orientação concluída sobre o cargo/função específica • Registro de treinamento e educação frequentados pelo membro da equipe • Avaliações anuais de desempenho concluídas e outras avaliações, conforme definido pela política do hospital ou consistente com leis e regulamentos • Avaliações anuais de competência do membro da equipe concluídas e outras avaliações de competência, conforme definido pela política do hospital ou consistente com leis e regulamentos | E571: Não Conforme
A572: SQE | B572: Padrão SQE.01.05 O hospital tem a equipe necessária para apoiar os cuidados, tratamentos e serviços que oferece. | C572: 1 | D572: Líderes do hospital implementam um processo de pessoal para o hospital que apoie o atendimento, o tratamento e os serviços que ele oferece. (Veja também GLD.03.01, EM 1)
A573: SQE | B573: Padrão SQE.01.05 O hospital tem a equipe necessária para apoiar os cuidados, tratamentos e serviços que oferece. | C573: 2 | D573: O processo de pessoal do hospital indica o número, os tipos e as qualificações desejadas da equipe, usando um método de pessoal reconhecido.
A574: SQE | B574: Padrão SQE.01.05 O hospital tem a equipe necessária para apoiar os cuidados, tratamentos e serviços que oferece. | C574: 3 | D574: O processo de pessoal do hospital descreve a atribuição e reatribuição de profissionais.
A575: SQE | B575: Padrão SQE.01.05 O hospital tem a equipe necessária para apoiar os cuidados, tratamentos e serviços que oferece. | C575: 4 | D575: O processo de pessoal do hospital está em conformidade com as leis e regulamentos locais.
A576: SQE | B576: Padrão SQE.01.05 O hospital tem a equipe necessária para apoiar os cuidados, tratamentos e serviços que oferece. | C576: 5 | D576: A efetividade do processo de pessoal do hospital é continuamente monitorada.
A577: SQE | B577: Padrão SQE.01.05 O hospital tem a equipe necessária para apoiar os cuidados, tratamentos e serviços que oferece. | C577: 6 | D577: O processo de pessoal do hospital é revisado e atualizado de acordo com a política do hospital e quando indicado.
A578: SQE | B578: Padrão SQE.01.05 O hospital tem a equipe necessária para apoiar os cuidados, tratamentos e serviços que oferece. | C578: 7 | D578: O processo de pessoal do hospital envolve a coordenação com vários líderes de departamentos/serviços do hospital.
A579: SQE | B579: Padrão SQE.01.06 O hospital fornece orientação para todos os profissionais. | C579: 1 | D579: O hospital completa a orientação antes que a equipe forneça cuidados, tratamento e serviços. (Veja também GHI.02.00, EM 4) | E579: Conforme
A580: SQE | B580: Padrão SQE.01.06 O hospital fornece orientação para todos os profissionais. | C580: 2 | D580: O hospital orienta a equipe sobre o seguinte, de acordo com a descrição de seu cargo: • Problemas de qualidade e segurança de alto risco (por exemplo, notificações de erros médicos, práticas de prevenção e controle de infecções, políticas do hospital sobre pedidos de medicamentos por telefone) • O hospital, o departamento e/ou unidade para o qual eles são designados • Suas responsabilidades específicas do cargo e quaisquer atribuições específicas • Políticas e procedimentos relevantes em todo o hospital e departamentos e/ou unidades • Direitos do paciente, incluindo aspectos éticos de cuidados, tratamento ou serviços e o processo usado para abordar questões éticas com base em seus deveres e responsabilidades de cargo (ver também PCC.01.01, EM 2)
A581: SQE | B581: Padrão SQE.01.06 O hospital fornece orientação para todos os profissionais. | C581: 3 | D581: Outros profissionais clínicos que acompanham o corpo médico e prestam cuidados, tratamentos e serviços são orientados sobre o hospital.
A582: SQE | B582: Padrão SQE.01.06 O hospital fornece orientação para todos os profissionais. | C582: 4 | D582: Estudantes, estagiários e voluntários são orientados sobre o hospital e têm responsabilidades designadas.
A583: SQE | B583: Padrão SQE.01.06 O hospital fornece orientação para todos os profissionais. | C583: 5 | D583: A conclusão da orientação e uma descrição dos objetivos são documentadas para todos os membros da equipe em seus arquivos pessoais.
A584: SQE | B584: Padrão SQE.01.07 Os membros da equipe participam da educação e do treinamento. | C584: 1 | D584: Os membros da equipe participam de educação e treinamento continuados para manter ou aumentar sua competência e conforme necessário. (Veja também AOP.05.02, EM 2) | E584: Não Conforme
A585: SQE | B585: Padrão SQE.01.07 Os membros da equipe participam da educação e do treinamento. | C585: 2 | D585: São fornecidos educação e treinamento continuados aos membros da equipe do hospital | E585: Não Conforme
A586: SQE | B586: Padrão SQE.01.07 Os membros da equipe participam da educação e do treinamento. | C586: 3 | D586: O hospital utiliza várias fontes de dados e informações, incluindo os resultados de qualidade e segurança e atividades de medição, para identificar as necessidades de educação dos membros da equipe. (Veja também GLD.07.01, EM 3)
A587: SQE | B587: Padrão SQE.01.07 Os membros da equipe participam da educação e do treinamento. | C587: 4 | D587: Os programas de educação da equipe são desenvolvidos e fornecidos com base nesses dados e informações. | E587: Conforme
A588: SQE | B588: Padrão SQE.01.07 Os membros da equipe participam da educação e do treinamento. | C588: 5 | D588: A educação é relevante para a capacidade de cada membro da equipe de atender às necessidades do paciente e/ou aos requisitos de educação continuada.
A589: SQE | B589: Padrão SQE.01.07 Os membros da equipe participam da educação e do treinamento. | C589: 6 | D589: O hospital fornece tempo e recursos adequados para que todos os membros da equipe participem de oportunidades relevantes de educação e treinamento. | E589: Não Conforme
A590: SQE | B590: Padrão SQE.01.07 Os membros da equipe participam da educação e do treinamento. | C590: 7 | D590: Conclusões de treinamento e educação são documentadas para todos os membros da equipe em seus arquivos pessoais. | E590: Conforme
A591: SQE | B591: Padrão SQE.01.08 Os membros da equipe são competentes em técnicas de ressuscitação apropriadas à sua função no hospital. | C591: 1 | D591: A equipe clínica que presta atendimento, tratamento e serviços ao paciente, incluindo o corpo médico, é treinada em pelo menos suporte básico de vida (basic life support - BLS). | E591: Conforme
A592: SQE | B592: Padrão SQE.01.08 Os membros da equipe são competentes em técnicas de ressuscitação apropriadas à sua função no hospital. | C592: 2 | D592: O hospital identifica o nível de treinamento (suporte básico ou avançado de vida), adequado às suas funções no hospital, para todo o corpo clínico que presta atendimento ao paciente. (Veja também ASC.02.00, EM 2) | E592: Conforme
A593: SQE | B593: Padrão SQE.01.08 Os membros da equipe são competentes em técnicas de ressuscitação apropriadas à sua função no hospital. | C593: 3 | D593: Evidencia de que o membro do corpo clínico concluiu e passou o nível de treinamento apropriado para sua função está documentada no arquivo pessoal.
A594: SQE | B594: Padrão SQE.01.08 Os membros da equipe são competentes em técnicas de ressuscitação apropriadas à sua função no hospital. | C594: 4 | D594: O nível de treinamento apropriado para sua função na equipe clínica é repetido com base nos requisitos e/ou prazos estabelecidos por um programa de treinamento reconhecido, ou a cada dois anos, se um programa de treinamento reconhecido não for usado.
A595: SQE | B595: Padrão SQE.01.08 Os membros da equipe são competentes em técnicas de ressuscitação apropriadas à sua função no hospital. | C595: 5 | D595: O hospital identifica pessoal não clínico a ser treinado em suporte básico de vida (BLS). | E595: Não Conforme
A596: SQE | B596: Padrão SQE.01.08 Os membros da equipe são competentes em técnicas de ressuscitação apropriadas à sua função no hospital. | C596: 6 | D596: Evidência de que o membro da equipe não clínica concluiu e foi aprovado no nível de treinamento apropriado para sua função está documentado no arquivo de pessoal.
A597: SQE | B597: Padrão SQE.01.08 Os membros da equipe são competentes em técnicas de ressuscitação apropriadas à sua função no hospital. | C597: 7 | D597: O nível de treinamento apropriado para sua função na equipe não clínica é repetido com base nos requisitos e/ou prazos estabelecidos por um programa de treinamento reconhecido, ou a cada dois anos, se um programa de treinamento reconhecido não é usado.
A598: SQE | B598: Padrão SQE.02.00 O hospital oferece um programa de saúde e segurança dos membros da equipe que aborda a saúde física e mental e condições de trabalho seguras. | C598: 1 | D598: O hospital implementa um programa de saúde e segurança para os membros da equipe que responde às necessidades urgentes e não urgentes da equipe por meio de tratamento direto e encaminhamento.
A599: SQE | B599: Padrão SQE.02.00 O hospital oferece um programa de saúde e segurança dos membros da equipe que aborda a saúde física e mental e condições de trabalho seguras. | C599: 2 | D599: O programa de saúde e segurança para os membros da equipe, no mínimo, inclui o seguinte: • Triagem inicial de saúde no emprego • Medidas para controlar exposições profissionais prejudiciais, como exposição a drogas tóxicas e níveis de ruído prejudiciais • Educação, treinamento e recursos sobre manuseio seguro de pacientes • Educação, treinamento e recursos para membros da equipe que podem ser segundas vítimas de eventos adversos ou sentinela • Tratamento para condições ou lesões comuns relacionadas ao trabalho (ver também PCI.08.01, EM 1)
A600: SQE | B600: Padrão SQE.02.00 O hospital oferece um programa de saúde e segurança dos membros da equipe que aborda a saúde física e mental e condições de trabalho seguras. | C600: 3 | D600: O programa de saúde e segurança para os membros da equipe avalia e fornece recursos para lidar com o seguinte: • Saúde mental da equipe • Burnout • Fadiga da compaixão • Risco de suicídio e automutilação
A601: SQE | B601: Padrão SQE.02.00 O hospital oferece um programa de saúde e segurança dos membros da equipe que aborda a saúde física e mental e condições de trabalho seguras. | C601: 4 | D601: O hospital implementa um processo de acompanhamento e apoio ao pessoal que é segunda vítima de eventos adversos ou sentinela.
A602: SQE | B602: Padrão SQE.02.00 O hospital oferece um programa de saúde e segurança dos membros da equipe que aborda a saúde física e mental e condições de trabalho seguras. | C602: 5 | D602: O hospital demonstra as ações tomadas para a prevenção da saúde mental da equipe para, no mínimo, abordar o seguinte: • Burnout • Fadiga da compaixão • Risco de automutilação • Suicídio
A603: SQE | B603: Padrão SQE.02.01 O hospital identifica membros da equipe em risco de exposição e possível transmissão de doenças evitáveis por vacinação e implementa um programa de vacinação e imunização da equipe. | C603: 1 | D603: O hospital identifica infecções epidemiologicamente significativas, bem como membros da equipe clínica com alto risco de exposição e transmissão de infecções. (Veja também PCI.08.01, EM 2) | E603: Não Conforme
A604: SQE | B604: Padrão SQE.02.01 O hospital identifica membros da equipe em risco de exposição e possível transmissão de doenças evitáveis por vacinação e implementa um programa de vacinação e imunização da equipe. | C604: 2 | D604: O hospital desenvolve e implementa um programa de vacinação e imunização ara membros da equipe clínica. (Veja também PCI.07.02, EM 5) | E604: Não Conforme
A605: SQE | B605: Padrão SQE.02.01 O hospital identifica membros da equipe em risco de exposição e possível transmissão de doenças evitáveis por vacinação e implementa um programa de vacinação e imunização da equipe. | C605: 3 | D605: O programa de vacinação e imunização para membros da equipe clínica inclui uma política e um processo para a administração e gerenciamento de vacinações e imunizações. | E605: Não Conforme
A606: SQE | B606: Padrão SQE.02.01 O hospital identifica membros da equipe em risco de exposição e possível transmissão de doenças evitáveis por vacinação e implementa um programa de vacinação e imunização da equipe. | C606: 4 | D606: O hospital avalia os riscos associados a membros da equipe clínica não vacinados e identifica estratégias para reduzir o risco de exposição de pacientes e profissionais a doenças infecciosas de membros da equipe clínica não vacinados. | E606: Não Conforme
A607: SQE | B607: Padrão SQE.02.01 O hospital identifica membros da equipe em risco de exposição e possível transmissão de doenças evitáveis por vacinação e implementa um programa de vacinação e imunização da equipe. | C607: 5 | D607: O programa de prevenção e controle de infecções orienta a avaliação, aconselhamento e acompanhamento de profissionais expostos a doenças infecciosas. (Veja também PCI.08.01, EM 1)
A608: SQE | B608: Padrão SQE.02.02 Líderes e membros da equipe são treinados e demonstram competência na prevenção da violência no local de trabalho. | C608: 1 | D608: O hospital fornece treinamento, educação e recursos (no momento da contratação, anualmente e sempre que ocorrerem mudanças em relação ao programa de prevenção da violência no local de trabalho) para líderes e membros da equipe. (Veja também GLD.07.02, EM 2) | E608: Não Conforme
A609: SQE | B609: Padrão SQE.02.02 Líderes e membros da equipe são treinados e demonstram competência na prevenção da violência no local de trabalho. | C609: 2 | D609: O hospital determina quais aspectos do treinamento são apropriados para indivíduos com base em suas funções e responsabilidades.
A610: SQE | B610: Padrão SQE.02.02 Líderes e membros da equipe são treinados e demonstram competência na prevenção da violência no local de trabalho. | C610: 3 | D610: O treinamento, educação e os recursos abordam a prevenção, reconhecimento, resposta e denúncia de violência no local de trabalho da seguinte forma: • O que constitui violência no local de trabalho (ver também GLD.07.02, EM 2) • Educação sobre as funções e responsabilidades dos líderes, equipe clínica, pessoal de segurança e aplicação da lei externa • Treinamento em detecção precoce, desescalada, habilidades de intervenção não física, técnicas de intervenção física e resposta a incidentes de emergência • O processo de notificação para incidentes de violência no local de trabalho (ver também GLD.07.02, EM 5) | E610: Não Conforme
A611: SQE | B611: Padrão SQE.03.00 O hospital possui um processo uniforme para coletar, verificar e avaliar as credenciais do corpo de enfermagem. | C611: 1 | D611: O hospital tem um procedimento padronizado para coletar, verificar e documentar a educação, certificações e experiência de cada membro corpo de enfermagem. | E611: Conforme
A612: SQE | B612: Padrão SQE.03.00 O hospital possui um processo uniforme para coletar, verificar e avaliar as credenciais do corpo de enfermagem. | C612: 2 | D612: Educação, treinamento e as certificações são verificadas a partir da fonte original de acordo com os parâmetros encontrados no propósito de SQE.05.01 e são documentadas. | E612: Conforme
A613: SQE | B613: Padrão SQE.03.00 O hospital possui um processo uniforme para coletar, verificar e avaliar as credenciais do corpo de enfermagem. | C613: 3 | D613: Licenciamento é verificado a partir da fonte original consistente com os seguintes parâmetros e está documentado: • O hospital deve verificar se o terceiro implementa o processo de verificação conforme descrito na política ou regulamentos do hospital e se o processo atende às expectativas descritas nesses padrões. • O hospital afiliado que já realizou a verificação da fonte primária de candidato para o corpo de enfermagem, é aceitável se o hospital tiver acreditação atual da Joint Commission International (JCI) com "total conformidade" em seu processo de verificação encontrado em SQE.03.00, EMs 1 e 2. • O hospital que baseia suas decisões em parte em informações de uma agência designada, oficial, governamental ou não governamental, deve avaliar a agência que fornece as informações inicialmente e depois periodicamente para garantir que os padrões da JCI continuem a ser atendidos
A614: SQE | B614: Padrão SQE.03.00 O hospital possui um processo uniforme para coletar, verificar e avaliar as credenciais do corpo de enfermagem. | C614: 4 | D614: Um arquivo é mantido com as credenciais de cada membro do corpo de enfermagem. | E614: Conforme
A615: SQE | B615: Padrão SQE.03.00 O hospital possui um processo uniforme para coletar, verificar e avaliar as credenciais do corpo de enfermagem. | C615: 5 | D615: O hospital tem um processo para garantir que as credenciais dos enfermeiros contratados sejam válidas e completas antes da atribuição da função. | E615: Conforme
A616: SQE | B616: Padrão SQE.03.00 O hospital possui um processo uniforme para coletar, verificar e avaliar as credenciais do corpo de enfermagem. | C616: 6 | D616: O hospital tem um processo para garantir que os enfermeiros que não são funcionários do hospital, mas acompanham médicos particulares e prestam serviços aos pacientes do hospital, tenham credenciais válidas. | E616: Conforme
A617: SQE | B617: Padrão SQE.03.01 O hospital possui um processo padronizado para identificar responsabilidades do cargo e planejar atribuições de trabalho clínico com base nas credenciais do membro do corpo de enfermagem e em quaisquer requisitos regulamentares. | C617: 1 | D617: O corpo de enfermagem tem educação, experiência, treinamento e/ou certificação, consistente com o escopo de serviços do hospital, conforme indicado em sua descrição de cargo e conforme aplicável à sua função. | E617: Conforme
A618: SQE | B618: Padrão SQE.03.01 O hospital possui um processo padronizado para identificar responsabilidades do cargo e planejar atribuições de trabalho clínico com base nas credenciais do membro do corpo de enfermagem e em quaisquer requisitos regulamentares. | C618: 2 | D618: Os critérios básicos para avaliar o corpo de enfermagem no programa incluem, no mínimo, licença atual e competência atual.
A619: SQE | B619: Padrão SQE.03.01 O hospital possui um processo padronizado para identificar responsabilidades do cargo e planejar atribuições de trabalho clínico com base nas credenciais do membro do corpo de enfermagem e em quaisquer requisitos regulamentares. | C619: 3 | D619: Licenciamento, educação, treinamento e experiência do membro do corpo de enfermagem são usados para planejar atribuições de trabalho clínico.
A620: SQE | B620: Padrão SQE.03.01 O hospital possui um processo padronizado para identificar responsabilidades do cargo e planejar atribuições de trabalho clínico com base nas credenciais do membro do corpo de enfermagem e em quaisquer requisitos regulamentares. | C620: 4 | D620: O processo considera as leis e regulamentos aplicáveis.
A621: SQE | B621: Padrão SQE.03.01 O hospital possui um processo padronizado para identificar responsabilidades do cargo e planejar atribuições de trabalho clínico com base nas credenciais do membro do corpo de enfermagem e em quaisquer requisitos regulamentares. | C621: 5 | D621: O processo apoia planos de pessoal de enfermagem.
A622: SQE | B622: Padrão SQE.03.02-O hospital possui um processo padronizado para a participação do corpo de enfermagem nas atividades de melhoria contínua da qualidade do hospital, incluindo a avaliação do desempenho individual, quando indicado | C622: 1 | D622: O corpo de enfermagem participa das atividades de melhoria contínua da qualidade do hospital. | E622: Conforme
A623: SQE | B623: Padrão SQE.03.02-O hospital possui um processo padronizado para a participação do corpo de enfermagem nas atividades de melhoria contínua da qualidade do hospital, incluindo a avaliação do desempenho individual, quando indicado | C623: 2 | D623: O desempenho de membros individuais do corpo de enfermagem é revisado quando indicado por variações observadas na tendência ou como desvios negativos para atividades de melhoria contínua da qualidade
A624: SQE | B624: Padrão SQE.03.02-O hospital possui um processo padronizado para a participação do corpo de enfermagem nas atividades de melhoria contínua da qualidade do hospital, incluindo a avaliação do desempenho individual, quando indicado | C624: 3 | D624: Informações do processo de revisão são documentadas nos arquivos pessoais do corpo de enfermagem ou em um arquivo de credenciais, consistente com a política do hospital.
A625: SQE | B625: Padrão SQE.04.00 O hospital tem um processo uniforme para coletar, verificar e avaliar credenciais de outros profissionais de saúde. | C625: 1 | D625: O hospital tem um processo padronizado para coletar, documentar e verificar a educação, certificações e experiência de cada membro de outros profissionais de saúde. | E625: Conforme
A626: SQE | B626: Padrão SQE.04.00 O hospital tem um processo uniforme para coletar, verificar e avaliar credenciais de outros profissionais de saúde. | C626: 2 | D626: A educação, o treinamento e as certificações são verificadas a partir da fonte original consistente com os parâmetros encontrados no propósito de SQE.05.01 e estão documentados. | E626: Conforme
...

Sheet Planos de Ação 
A1: ID_Plano | B1: Data_Reuniao | C1: Comite_Origem | D1: Plano_de_Acao | E1: Responsaveis | F1: Departamento | G1: Prazo_Informado | H1: 30 dias | I1: Status | J1: Historico | K1: Origem
